Workbook

Sheet 公司看板
H1: 公 司 看 板
D2: 毛利 | F2: =K16-'公司-汇总页'!C72 -> 245.73319 | L2: 现金流 | P2: =O16-'公司-汇总页'!D72 -> 4865.1795
E6: 产值 | F6: 自营产值 | J6: 营收 | K6: 自营营收 | O6: 收款 | P6: 净收款
B7: 1 | C7: 月计划 | E7: =OFFSET('公司-汇总页'!$E$12,0,$B$7-1) -> 421.4063 | F7: =OFFSET('公司-汇总页'!$E$22,0,$B$7-1) -> 198.40684 | J7: =OFFSET('公司-汇总页'!$E$32,0,$B$7-1) -> 398.57198 | K7: =OFFSET('公司-汇总页'!$E$42,0,$B$7-1) -> 187.34608 | O7: =OFFSET('公司-汇总页'!$E$52,0,$B$7-1) -> 1235.4281 | P7: =OFFSET('公司-汇总页'!$E$62,0,$B$7-1) -> 669.6243
B8: =B7 -> 1 | C8: 月完成 | E8: =OFFSET('公司-汇总页'!$Q$12,0,$B$7-1) -> 181.14625 | F8: =OFFSET('公司-汇总页'!$Q$22,0,$B$7-1) -> 61.703545 | J8: =OFFSET('公司-汇总页'!$Q$32,0,$B$7-1) -> 170.89269 | K8: =OFFSET('公司-汇总页'!$Q$42,0,$B$7-1) -> 58.210892 | O8: =OFFSET('公司-汇总页'!$Q$52,0,$B$7-1) -> 625.73117 | P8: =OFFSET('公司-汇总页'!$Q$62,0,$B$7-1) -> 254.4613
B9: =B8 -> 1 | C9: 月完成率 | E9: =E8/E7 -> 0.42986128 | F9: =F8/F7 -> 0.31099504 | J9: =J8/J7 -> 0.42876243 | K9: =K8/K7 -> 0.31071316 | O9: =O8/O7 -> 0.50648935 | P9: =P8/P7 -> 0.38000607
B11: 一 | C11: 季度计划 | E11: =SUM(OFFSET('公司-汇总页'!$E$12,0,(MATCH(B11,{"一","二","三","四"},0)-1)*3,1,3)) -> 1316.7068 | F11: =SUM(OFFSET('公司-汇总页'!$E$22,0,(MATCH(B11,{"一","二","三","四"},0)-1)*3,1,3)) -> 502.58661 | J11: =SUM(OFFSET('公司-汇总页'!$E$32,0,(MATCH(B11,{"一","二","三","四"},0)-1)*3,1,3)) -> 1242.2515 | K11: =SUM(OFFSET('公司-汇总页'!$E$42,0,(MATCH(B11,{"一","二","三","四"},0)-1)*3,1,3)) -> 474.1172 | O11: =SUM(OFFSET('公司-汇总页'!$E$52,0,(MATCH(B11,{"一","二","三","四"},0)-1)*3,1,3)) -> 4718.5956 | P11: =SUM(OFFSET('公司-汇总页'!$E$62,0,(MATCH(B11,{"一","二","三","四"},0)-1)*3,1,3)) -> 2222.2987
B12: =B11 -> 一 | C12: 季度完成 | E12: =SUM(OFFSET('公司-汇总页'!$Q$12,0,(MATCH(B11,{"一","二","三","四"},0)-1)*3,1,3)) -> 557.72825 | F12: =SUM(OFFSET('公司-汇总页'!$Q$22,0,(MATCH(B11,{"一","二","三","四"},0)-1)*3,1,3)) -> 180.48055 | J12: =SUM(OFFSET('公司-汇总页'!$Q$32,0,(MATCH(B11,{"一","二","三","四"},0)-1)*3,1,3)) -> 526.15873 | K12: =SUM(OFFSET('公司-汇总页'!$Q$42,0,(MATCH(B11,{"一","二","三","四"},0)-1)*3,1,3)) -> 170.26467 | O12: =SUM(OFFSET('公司-汇总页'!$Q$52,0,(MATCH(B11,{"一","二","三","四"},0)-1)*3,1,3)) -> 3120.1604 | P12: =SUM(OFFSET('公司-汇总页'!$Q$62,0,(MATCH(B11,{"一","二","三","四"},0)-1)*3,1,3)) -> 1280.244
B13: =B12 -> 一 | C13: 季度完成率 | E13: =E12/E11 -> 0.42357817 | F13: =F12/F11 -> 0.35910337 | J13: =J12/J11 -> 0.42355249 | K13: =K12/K11 -> 0.35911936 | O13: =O12/O11 -> 0.66124768 | P13: =P12/P11 -> 0.57608998
C15: 全年指标
C16: 累计完成 | E16: ='公司-汇总页'!D12 -> 721.1183 | F16: ='公司-汇总页'!D22 -> 261.36343 | J16: ='公司-汇总页'!D32 -> 677.51875 | K16: ='公司-汇总页'!D42 -> 245.73319 | O16: ='公司-汇总页'!D52 -> 4865.1795 | P16: ='公司-汇总页'!D62 -> 1978.8403
C17: 累计完成率 | E17: =E16/E15 -> #DIV/0! | F17: =F16/F15 -> #DIV/0! | J17: =J16/J15 -> #DIV/0! | K17: =K16/K15 -> #DIV/0! | O17: =O16/O15 -> #DIV/0! | P17: =P16/P15 -> #DIV/0!
C22: 说明：
C23: 1、自营产值/营收及净收款根据合同整体自营率换算，可能与实际情况有出入
C24: 2、毛利=自营营收-人工成本-报销
C25: 3、现金流=收款-人工成本-报销-分包支付
C31: =MATCH(B11,{"一","二","三","四"},0) -> 1

Sheet 看板
F1: 公司 | J1: 看板 | Z1: 数字建造中心
D2: 毛利 | L2: 现金流 | Z2: 智能运管中心
Z3: 数智管理中心
Z4: 福建分公司
Z5: 广东分公司
E6: 产值 | F6: 自营产值 | J6: 营收 | K6: 自营营收 | O6: 收款 | P6: 净收款 | Z6: 产品研发中心
B7: 4 | C7: 月计划 | E7: =OFFSET('公司-汇总页'!$E$5,MATCH(F1,Z1:Z8,0)-1,$B$7-1) -> 1116.3342 | F7: =OFFSET('公司-汇总页'!$E$15,MATCH(F1,Z1:Z8,0)-1,$B$7-1) -> 350.02594 | J7: =OFFSET('公司-汇总页'!$E$25,MATCH(F1,Z1:Z8,0)-1,$B$7-1) -> 1050.3193 | K7: =OFFSET('公司-汇总页'!$E$35,MATCH(F1,Z1:Z8,0)-1,$B$7-1) -> 330.97499 | O7: =OFFSET('公司-汇总页'!$E$45,MATCH(F1,Z1:Z8,0)-1,$B$7-1) -> 1085.3586 | P7: =OFFSET('公司-汇总页'!$E$55,MATCH(F1,Z1:Z8,0)-1,$B$7-1) -> 513.30544 | Z7: 市场经营拓展中心
B8: =B7 -> 4 | C8: 月完成 | E8: =OFFSET('公司-汇总页'!$Q$5,MATCH(F1,Z1:Z8,0)-1,$B$7-1) -> 86.576596 | F8: =OFFSET('公司-汇总页'!$Q$15,MATCH(F1,Z1:Z8,0)-1,$B$7-1) -> 31.269332 | J8: =OFFSET('公司-汇总页'!$Q$25,MATCH(F1,Z1:Z8,0)-1,$B$7-1) -> 80.221192 | K8: =OFFSET('公司-汇总页'!$Q$35,MATCH(F1,Z1:Z8,0)-1,$B$7-1) -> 29.559627 | O8: =OFFSET('公司-汇总页'!$Q$45,MATCH(F1,Z1:Z8,0)-1,$B$7-1) -> 1286.7913 | P8: =OFFSET('公司-汇总页'!$Q$55,MATCH(F1,Z1:Z8,0)-1,$B$7-1) -> 590.42267 | Z8: 公司
B9: =B8 -> 4 | C9: 月完成率 | E9: =E8/E7 -> 0.077554373 | F9: =F8/F7 -> 0.089334326 | J9: =J8/J7 -> 0.076377912 | K9: =K8/K7 -> 0.089310755 | O9: =O8/O7 -> 1.1855909 | P9: =P8/P7 -> 1.1502365
B11: 二 | C11: 季度计划 | E11: =SUM(OFFSET('公司-汇总页'!$E$5,MATCH(F1,Z1:Z8,0)-1,(MATCH(B11,{"一","二","三","四"},0)-1)*3,1,3)) -> 4771.1105 | F11: =SUM(OFFSET('公司-汇总页'!$E$15,MATCH(F1,Z1:Z8,0)-1,(MATCH(B11,{"一","二","三","四"},0)-1)*3,1,3)) -> 2303.1523 | J11: =SUM(OFFSET('公司-汇总页'!$E$25,MATCH(F1,Z1:Z8,0)-1,(MATCH(B11,{"一","二","三","四"},0)-1)*3,1,3)) -> 4488.3614 | K11: =SUM(OFFSET('公司-汇总页'!$E$35,MATCH(F1,Z1:Z8,0)-1,(MATCH(B11,{"一","二","三","四"},0)-1)*3,1,3)) -> 2170.7447 | O11: =SUM(OFFSET('公司-汇总页'!$E$45,MATCH(F1,Z1:Z8,0)-1,(MATCH(B11,{"一","二","三","四"},0)-1)*3,1,3)) -> 4917.7774 | P11: =SUM(OFFSET('公司-汇总页'!$E$55,MATCH(F1,Z1:Z8,0)-1,(MATCH(B11,{"一","二","三","四"},0)-1)*3,1,3)) -> 2425.3881
B12: =B11 -> 二 | C12: 季度完成 | E12: =SUM(OFFSET('公司-汇总页'!$Q$5,MATCH(F1,Z1:Z8,0)-1,(MATCH(B11,{"一","二","三","四"},0)-1)*3,1,3)) -> 163.39005 | F12: =SUM(OFFSET('公司-汇总页'!$Q$15,MATCH(F1,Z1:Z8,0)-1,(MATCH(B11,{"一","二","三","四"},0)-1)*3,1,3)) -> 80.882889 | J12: =SUM(OFFSET('公司-汇总页'!$Q$25,MATCH(F1,Z1:Z8,0)-1,(MATCH(B11,{"一","二","三","四"},0)-1)*3,1,3)) -> 151.36002 | K12: =SUM(OFFSET('公司-汇总页'!$Q$35,MATCH(F1,Z1:Z8,0)-1,(MATCH(B11,{"一","二","三","四"},0)-1)*3,1,3)) -> 75.468524 | O12: =SUM(OFFSET('公司-汇总页'!$Q$45,MATCH(F1,Z1:Z8,0)-1,(MATCH(B11,{"一","二","三","四"},0)-1)*3,1,3)) -> 1745.019 | P12: =SUM(OFFSET('公司-汇总页'!$Q$55,MATCH(F1,Z1:Z8,0)-1,(MATCH(B11,{"一","二","三","四"},0)-1)*3,1,3)) -> 698.59634
B13: =B12 -> 二 | C13: 季度完成率 | E13: =E12/E11 -> 0.034245706 | F13: =F12/F11 -> 0.035118342 | J13: =J12/J11 -> 0.033722779 | K13: =K12/K11 -> 0.034766191 | O13: =O12/O11 -> 0.35483897 | P13: =P12/P11 -> 0.28803486
B15: 一 | C15: 季度计划 | E15: =SUM(OFFSET('公司-汇总页'!$E$5,MATCH(F1,Z1:Z8,0)-1,(MATCH(B15,{"一","二","三","四"},0)-1)*3,1,3)) -> 1316.7068 | F15: =SUM(OFFSET('公司-汇总页'!$E$15,MATCH(F1,Z1:Z8,0)-1,(MATCH(B15,{"一","二","三","四"},0)-1)*3,1,3)) -> 502.58661 | J15: =SUM(OFFSET('公司-汇总页'!$E$25,MATCH(F1,Z1:Z8,0)-1,(MATCH(B15,{"一","二","三","四"},0)-1)*3,1,3)) -> 1242.2515 | K15: =SUM(OFFSET('公司-汇总页'!$E$35,MATCH(F1,Z1:Z8,0)-1,(MATCH(B15,{"一","二","三","四"},0)-1)*3,1,3)) -> 474.1172 | O15: =SUM(OFFSET('公司-汇总页'!$E$45,MATCH(F1,Z1:Z8,0)-1,(MATCH(B15,{"一","二","三","四"},0)-1)*3,1,3)) -> 4718.5956 | P15: =SUM(OFFSET('公司-汇总页'!$E$55,MATCH(F1,Z1:Z8,0)-1,(MATCH(B15,{"一","二","三","四"},0)-1)*3,1,3)) -> 2222.2987
B16: 一 | C16: 季度完成 | E16: =SUM(OFFSET('公司-汇总页'!$Q$5,MATCH(F1,Z1:Z8,0)-1,(MATCH(B15,{"一","二","三","四"},0)-1)*3,1,3)) -> 557.72825 | F16: =SUM(OFFSET('公司-汇总页'!$Q$15,MATCH(F1,Z1:Z8,0)-1,(MATCH(B15,{"一","二","三","四"},0)-1)*3,1,3)) -> 180.48055 | J16: =SUM(OFFSET('公司-汇总页'!$Q$25,MATCH(F1,Z1:Z8,0)-1,(MATCH(B15,{"一","二","三","四"},0)-1)*3,1,3)) -> 526.15873 | K16: =SUM(OFFSET('公司-汇总页'!$Q$35,MATCH(F1,Z1:Z8,0)-1,(MATCH(B15,{"一","二","三","四"},0)-1)*3,1,3)) -> 170.26467 | O16: =SUM(OFFSET('公司-汇总页'!$Q$45,MATCH(F1,Z1:Z8,0)-1,(MATCH(B15,{"一","二","三","四"},0)-1)*3,1,3)) -> 3120.1604 | P16: =SUM(OFFSET('公司-汇总页'!$Q$55,MATCH(F1,Z1:Z8,0)-1,(MATCH(B15,{"一","二","三","四"},0)-1)*3,1,3)) -> 1280.244
B17: 一 | C17: 季度完成率 | E17: =E16/E15 -> 0.42357817 | F17: =F16/F15 -> 0.35910337 | J17: =J16/J15 -> 0.42355249 | K17: =K16/K15 -> 0.35911936 | O17: =O16/O15 -> 0.66124768 | P17: =P16/P15 -> 0.57608998
C19: 全年指标
C20: 累计完成 | E20: ='公司-汇总页'!D12 -> 721.1183 | F20: ='公司-汇总页'!D22 -> 261.36343 | J20: ='公司-汇总页'!D32 -> 677.51875 | K20: ='公司-汇总页'!D42 -> 245.73319 | O20: ='公司-汇总页'!D52 -> 4865.1795 | P20: ='公司-汇总页'!D62 -> 1978.8403
C21: 累计完成率 | E21: =E20/E19 -> #DIV/0! | F21: =F20/F19 -> #DIV/0! | J21: =J20/J19 -> #DIV/0! | K21: =K20/K19 -> #DIV/0! | O21: =O20/O19 -> #DIV/0! | P21: =P20/P19 -> #DIV/0!
C26: 说明：
C27: 1、自营产值/营收及净收款根据合同整体自营率换算，可能与实际情况有出入
C28: 2、毛利=自营营收-人工成本-报销
C29: 3、现金流=收款-人工成本-报销-分包支付

Sheet 公司-汇总页
B1: 2026年度各部门项目跟进数据汇总表 | E1: 数字建造中心 | F1: 智能运管中心 | G1: 数智管理中心 | H1: 福建分公司 | I1: 广东分公司 | J1: 市场经营拓展中心 | K1: 产品研发中心
AD3: 1月经营会数据（0122） | AQ3: 2月经营会数据 | BD3: 3月经营会数据（0324）
B4: 产值 | C4: 计划 | D4: 实际 | E4: 2026-01计划 | F4: 2026-02计划 | G4: 2026-03计划 | H4: 2026-04计划 | I4: 2026-05计划 | J4: 2026-06计划 | K4: 2026-07计划 | L4: 2026-08计划 | M4: 2026-09计划 | N4: 2026-10计划 | O4: 2026-11计划 | P4: 2026-12计划 | Q4: 2026-01实际 | R4: 2026-02实际 | S4: 2026-03实际 | T4: 2026-04实际 | U4: 2026-05实际 | V4: 2026-06实际 | W4: 2026-07实际 | X4: 2026-08实际 | Y4: 2026-09实际 | Z4: 2026-10实际 | AA4: 2026-11实际 | AB4: 2026-12实际 | AD4: 2026-01计划 | AE4: 2026-02计划 | AF4: 2026-03计划 | AG4: 2026-04计划 | AH4: 2026-05计划 | AI4: 2026-06计划 | AJ4: 2026-07计划 | AK4: 2026-08计划 | AL4: 2026-09计划 | AM4: 2026-10计划 | AN4: 2026-11计划 | AO4: 2026-12计划 | AQ4: 2026-01计划 | AR4: 2026-02计划 | AS4: 2026-03计划 | AT4: 2026-04计划 | AU4: 2026-05计划 | AV4: 2026-06计划 | AW4: 2026-07计划 | AX4: 2026-08计划 | AY4: 2026-09计划 | AZ4: 2026-10计划 | BA4: 2026-11计划 | BB4: 2026-12计划 | BD4: 2026-01计划 | BE4: 2026-02计划 | BF4: 2026-03计划 | BG4: 2026-04计划 | BH4: 2026-05计划 | BI4: 2026-06计划 | BJ4: 2026-07计划 | BK4: 2026-08计划 | BL4: 2026-09计划 | BM4: 2026-10计划 | BN4: 2026-11计划 | BO4: 2026-12计划
B5: 数字建造中心 | C5: =SUM(E5:P5) -> 5302.8036 | D5: =SUM(Q5:AB5) -> 126.74845 | E5: ='[1]部门-汇总页'!E3 -> 9 | F5: ='[1]部门-汇总页'!F3 -> 21.5887 | G5: ='[1]部门-汇总页'!G3 -> 9 | H5: ='[1]部门-汇总页'!H3 -> 66.9637 | I5: ='[1]部门-汇总页'!I3 -> 146.42368 | J5: ='[1]部门-汇总页'!J3 -> 782.65999 | K5: ='[1]部门-汇总页'!K3 -> 1.5 | L5: ='[1]部门-汇总页'!L3 -> 121.6 | ... AB5: ='[1]部门-汇总页'!AB3 -> 0 | AD5: 0 | AE5: 12.12 | AF5: 404.80919 | AG5: 0 | AH5: 0 | AI5: 0 | AJ5: 0 | AK5: 0 | AL5: 0 | AM5: 0 | AN5: 0 | AO5: 0 | AQ5: 9 | AR5: 21.5887 | AS5: 323.84919 | AT5: 0 | AU5: 0 | AV5: 0 | AW5: 0 | AX5: 0 | AY5: 0 | AZ5: 0 | BA5: 0 | BB5: 0 | BD5: 9 | BE5: 21.5887 | BF5: 9 | BG5: 73.2187 | BH5: 72.819988 | BI5: 555.08166 | BJ5: 24.405 | BK5: 117.6 | BL5: 324.806 | BM5: 0 | BN5: 359.1762 | BO5: 73.746
B6: 智能运管中心 | C6: =SUM(E6:P6) -> 3337.1076 | D6: =SUM(Q6:AB6) -> 92.1516 | E6: ='[2]部门-汇总页'!E3 -> 0 | F6: ='[2]部门-汇总页'!F3 -> 33.5725 | G6: ='[2]部门-汇总页'!G3 -> 77.0773 | H6: ='[2]部门-汇总页'!H3 -> 748.21046 | I6: ='[2]部门-汇总页'!I3 -> 414.814 | J6: ='[2]部门-汇总页'!J3 -> 596.96883 | K6: ='[2]部门-汇总页'!K3 -> 45.25 | L6: ='[2]部门-汇总页'!L3 -> 401.49 | ... AB6: ='[2]部门-汇总页'!AB3 -> 0 | AD6: 0 | AE6: 6.055 | AF6: 401.2052 | AG6: 0 | AH6: 0 | AI6: 0 | AJ6: 0 | AK6: 0 | AL6: 0 | AM6: 0 | AN6: 0 | AO6: 0 | AQ6: 0 | AR6: 33.5725 | AS6: 495.22872 | AT6: 29.4126 | AU6: 0 | AV6: 0 | AW6: 0 | AX6: 0 | AY6: 0 | AZ6: 0 | BA6: 0 | BB6: 0 | BD6: 0 | BE6: 33.5725 | BF6: 121.1137 | BG6: 505.18152 | BH6: 89.5 | BI6: 1011.564 | BJ6: 1.74 | BK6: 54.1 | BL6: 45.395 | BM6: 0 | BN6: 25.886 | BO6: 0
B7: 数智管理中心 | C7: =SUM(E7:P7) -> 2013.1003 | D7: =SUM(Q7:AB7) -> 179.26925 | E7: ='[3]部门-汇总页'!E3 -> 316.2693 | F7: ='[3]部门-汇总页'!F3 -> 53.1 | G7: ='[3]部门-汇总页'!G3 -> 484.15 | H7: ='[3]部门-汇总页'!H3 -> 301.16 | I7: ='[3]部门-汇总页'!I3 -> 121.6 | J7: ='[3]部门-汇总页'!J3 -> 340.6935 | K7: ='[3]部门-汇总页'!K3 -> 97.5 | L7: ='[3]部门-汇总页'!L3 -> 19 | ... AB7: ='[3]部门-汇总页'!AB3 -> 0 | AD7: 290 | AE7: 71.025 | AF7: 653.8678 | AG7: 63.65 | AH7: 16.785 | AI7: 305.145 | AJ7: 44 | AK7: 0 | AL7: 148.2 | AM7: 1 | AN7: 0 | AO7: 118.5275 | AQ7: 316.2693 | AR7: 53.1 | AS7: 758.4 | AT7: 73.61 | AU7: 21.6 | AV7: 401.4935 | AW7: 44 | AX7: 0 | AY7: 148.2 | AZ7: 1 | BA7: 0 | BB7: 118.5275 | BD7: 316.2693 | BE7: 53.1 | BF7: 542.15 | BG7: 231.26 | BH7: 121.6 | BI7: 340.6935 | BJ7: 97.5 | BK7: 19 | BL7: 148.2 | BM7: 1 | BN7: 0 | BO7: 118.5275
B8: 福建分公司 | C8: =SUM(E8:P8) -> 1683.5791 | D8: =SUM(Q8:AB8) -> 270.2865 | E8: ='[4]部门-汇总页'!E3 -> 53.474503 | F8: ='[4]部门-汇总页'!F3 -> 216.812 | G8: ='[4]部门-汇总页'!G3 -> 0 | H8: ='[4]部门-汇总页'!H3 -> 0 | I8: ='[4]部门-汇总页'!I3 -> 78.629 | J8: ='[4]部门-汇总页'!J3 -> 215.99141 | K8: ='[4]部门-汇总页'!K3 -> 8.3125 | L8: ='[4]部门-汇总页'!L3 -> 162.937 | ... AB8: ='[4]部门-汇总页'!AB3 -> 0 | AD8: 53.474503 | AE8: 244.2835 | AF8: 0 | AG8: 0 | AH8: 0 | AI8: 0 | AJ8: 0 | AK8: 0 | AL8: 0 | AM8: 0 | AN8: 0 | AO8: 0 | AQ8: 53.474503 | AR8: 216.812 | AS8: 27.4715 | AT8: 0 | AU8: 0 | AV8: 0 | AW8: 0 | AX8: 0 | AY8: 0 | AZ8: 0 | BA8: 0 | BB8: 0 | BD8: 53.474503 | BE8: 216.812 | BF8: 0 | BG8: 0 | BH8: 61.8115 | BI8: 105.05141 | BJ8: 0 | BK8: 0 | BL8: 0 | BM8: 0 | BN8: 0 | BO8: 0
B9: 广东分公司 | C9: =SUM(E9:P9) -> 2379.2009 | D9: =SUM(Q9:AB9) -> 42.6625 | E9: ='[5]部门-汇总页'!E3 -> 42.6625 | F9: ='[5]部门-汇总页'!F3 -> 0 | G9: ='[5]部门-汇总页'!G3 -> 0 | H9: ='[5]部门-汇总页'!H3 -> 0 | I9: ='[5]部门-汇总页'!I3 -> 65.3416 | J9: ='[5]部门-汇总页'!J3 -> 891.65435 | K9: ='[5]部门-汇总页'!K3 -> 42.35 | L9: ='[5]部门-汇总页'!L3 -> 70.6325 | ... AB9: ='[5]部门-汇总页'!AB3 -> 0 | AD9: 42.6625 | AE9: 111 | AF9: 96.4008 | AG9: 0 | AH9: 0 | AI9: 0 | AJ9: 0 | AK9: 0 | AL9: 0 | AM9: 0 | AN9: 0 | AO9: 0 | AQ9: 42.6625 | AR9: 0 | AS9: 96.4008 | AT9: 0 | AU9: 0 | AV9: 0 | AW9: 0 | AX9: 0 | AY9: 0 | AZ9: 0 | BA9: 0 | BB9: 0 | BD9: 42.6625 | BE9: 0 | BF9: 0 | BG9: 25.3416 | BH9: 40 | BI9: 770.87265 | BJ9: 0 | BK9: 0 | BL9: 0 | BM9: 0 | BN9: 0 | BO9: 0
B10: 产品研发中心 | C10: =SUM(E10:P10) -> 0 | D10: =SUM(Q10:AB10) -> 10 | E10: ='[6]部门-汇总页'!E3 -> 0 | F10: ='[6]部门-汇总页'!F3 -> 0 | G10: ='[6]部门-汇总页'!G3 -> 0 | H10: ='[6]部门-汇总页'!H3 -> 0 | I10: ='[6]部门-汇总页'!I3 -> 0 | J10: ='[6]部门-汇总页'!J3 -> 0 | K10: ='[6]部门-汇总页'!K3 -> 0 | L10: ='[6]部门-汇总页'!L3 -> 0 | ... AB10: ='[6]部门-汇总页'!AB3 -> 0 | AD10: 0 | AE10: 0 | AF10: 0 | AG10: 0 | AH10: 0 | AI10: 0 | AJ10: 0 | AK10: 0 | AL10: 0 | AM10: 0 | AN10: 0 | AO10: 0 | AQ10: 0 | AR10: 0 | AS10: 0 | AT10: 0 | AU10: 0 | AV10: 0 | AW10: 0 | AX10: 0 | AY10: 0 | AZ10: 0 | BA10: 0 | BB10: 0 | BD10: 0 | BE10: 0 | BF10: 0 | BG10: 0 | BH10: 0 | BI10: 0 | BJ10: 0 | BK10: 0 | BL10: 0 | BM10: 0 | BN10: 0 | BO10: 0
B11: 市场经营拓展中心 | C11: =SUM(E11:P11) -> 28.88 | D11: =SUM(Q11:AB11) -> 0 | E11: ='[7]部门-汇总页'!E3 -> 0 | F11: ='[7]部门-汇总页'!F3 -> 0 | G11: ='[7]部门-汇总页'!G3 -> 0 | H11: ='[7]部门-汇总页'!H3 -> 0 | I11: ='[7]部门-汇总页'!I3 -> 0 | J11: ='[7]部门-汇总页'!J3 -> 0 | K11: ='[7]部门-汇总页'!K3 -> 0 | L11: ='[7]部门-汇总页'!L3 -> 0 | ... AB11: ='[7]部门-汇总页'!AB3 -> 0 | AD11: 0 | AE11: 0 | AF11: 0 | AG11: 0 | AH11: 0 | AI11: 0 | AJ11: 0 | AK11: 0 | AL11: 0 | AM11: 0 | AN11: 0 | AO11: 0 | AQ11: 0 | AR11: 0 | AS11: 0 | AT11: 0 | AU11: 0 | AV11: 0 | AW11: 0 | AX11: 0 | AY11: 0 | AZ11: 0 | BA11: 0 | BB11: 0 | BD11: 0 | BE11: 0 | BF11: 0 | BG11: 0 | BH11: 0 | BI11: 0 | BJ11: 0 | BK11: 0 | BL11: 0 | BM11: 0 | BN11: 0 | BO11: 0
B12: 合计 | C12: =SUM(C5:C11) -> 14744.672 | D12: =SUM(D5:D11) -> 721.1183 | E12: =SUM(E5:E11) -> 421.4063 | F12: =SUM(F5:F11) -> 325.0732 | G12: =SUM(G5:G11) -> 570.2273 | H12: =SUM(H5:H11) -> 1116.3342 | I12: =SUM(I5:I11) -> 826.80828 | J12: =SUM(J5:J11) -> 2827.9681 | ... AB12: =SUM(AB5:AB11) -> 0 | AD12: 386.137 | AE12: 444.4835 | AF12: 1556.283 | AG12: 63.65 | AH12: 16.785 | AI12: 305.145 | AJ12: 44 | AK12: 0 | AL12: 148.2 | AM12: 1 | AN12: 0 | AO12: 118.5275 | AQ12: 421.4063 | AR12: 325.0732 | AS12: 1701.3502 | AT12: 103.0226 | AU12: 21.6 | AV12: 401.4935 | AW12: 44 | AX12: 0 | AY12: 148.2 | AZ12: 1 | BA12: 0 | BB12: 118.5275 | BD12: 421.4063 | BE12: 325.0732 | BF12: 672.2637 | BG12: 835.00182 | BH12: 385.73149 | BI12: 2783.2632 | BJ12: 123.645 | BK12: 190.7 | BL12: 518.401 | BM12: 1 | BN12: 385.0622 | BO12: 192.2735
B14: 自营产值 | C14: 计划 | D14: 实际 | E14: 2026-01计划 | F14: 2026-02计划 | G14: 2026-03计划 | H14: 2026-04计划 | I14: 2026-05计划 | J14: 2026-06计划 | K14: 2026-07计划 | L14: 2026-08计划 | M14: 2026-09计划 | N14: 2026-10计划 | O14: 2026-11计划 | P14: 2026-12计划 | Q14: 2026-01实际 | R14: 2026-02实际 | S14: 2026-03实际 | T14: 2026-04实际 | U14: 2026-05实际 | V14: 2026-06实际 | W14: 2026-07实际 | X14: 2026-08实际 | Y14: 2026-09实际 | Z14: 2026-10实际 | AA14: 2026-11实际 | AB14: 2026-12实际 | AD14: 2026-01计划 | AE14: 2026-02计划 | AF14: 2026-03计划 | AG14: 2026-04计划 | AH14: 2026-05计划 | AI14: 2026-06计划 | AJ14: 2026-07计划 | AK14: 2026-08计划 | AL14: 2026-09计划 | AM14: 2026-10计划 | AN14: 2026-11计划 | AO14: 2026-12计划 | AQ14: 2026-01计划 | AR14: 2026-02计划 | AS14: 2026-03计划 | AT14: 2026-04计划 | AU14: 2026-05计划 | AV14: 2026-06计划 | AW14: 2026-07计划 | AX14: 2026-08计划 | AY14: 2026-09计划 | AZ14: 2026-10计划 | BA14: 2026-11计划 | BB14: 2026-12计划 | BD14: 2026-01计划 | BE14: 2026-02计划 | BF14: 2026-03计划 | BG14: 2026-04计划 | BH14: 2026-05计划 | BI14: 2026-06计划 | BJ14: 2026-07计划 | BK14: 2026-08计划 | BL14: 2026-09计划 | BM14: 2026-10计划 | BN14: 2026-11计划 | BO14: 2026-12计划
B15: 数字建造中心 | C15: =SUM(E15:P15) -> 3103.9522 | D15: =SUM(Q15:AB15) -> 85.461289 | E15: ='[1]部门-汇总页'!E4 -> 7.919988 | F15: ='[1]部门-汇总页'!F4 -> 16.888693 | G15: ='[1]部门-汇总页'!G4 -> 7.919988 | H15: ='[1]部门-汇总页'!H4 -> 44.560484 | I15: ='[1]部门-汇总页'!I4 -> 58.43053 | J15: ='[1]部门-汇总页'!J4 -> 456.35502 | K15: ='[1]部门-汇总页'!K4 -> 1.5 | L15: ='[1]部门-汇总页'!L4 -> 42.767882 | ... AB15: ='[1]部门-汇总页'!AB4 -> 0 | AD15: 0 | AE15: 12.12 | AF15: 228.8119 | AG15: 0 | AH15: 0 | AI15: 0 | AJ15: 0 | AK15: 0 | AL15: 0 | AM15: 0 | AN15: 0 | AO15: 0 | AQ15: 7.919988 | AR15: 16.888693 | AS15: 187.3719 | AT15: 0 | AU15: 0 | AV15: 0 | AW15: 0 | AX15: 0 | AY15: 0 | AZ15: 0 | BA15: 0 | BB15: 0 | BD15: 7.919988 | BE15: 16.888693 | BF15: 7.919988 | BG15: 38.111238 | BH15: 16.515859 | BI15: 308.27742 | BJ15: 19.5 | BK15: 39.247887 | BL15: 185.806 | BM15: 0 | BN15: 279.33901 | BO15: 67.082
B16: 智能运管中心 | C16: =SUM(E16:P16) -> 1789.3676 | D16: =SUM(Q16:AB16) -> 23.5266 | E16: ='[2]部门-汇总页'!E4 -> 0 | F16: ='[2]部门-汇总页'!F4 -> 12.012679 | G16: ='[2]部门-汇总页'!G4 -> 17.684688 | H16: ='[2]部门-汇总页'!H4 -> 225.04546 | I16: ='[2]部门-汇总页'!I4 -> 87.434 | J16: ='[2]部门-汇总页'!J4 -> 419.29383 | K16: ='[2]部门-汇总页'!K4 -> 23.4804 | L16: ='[2]部门-汇总页'!L4 -> 133.94208 | ... AB16: ='[2]部门-汇总页'!AB4 -> 0 | AD16: 0 | AE16: 1.47 | AF16: 87.300635 | AG16: 0 | AH16: 0 | AI16: 0 | AJ16: 0 | AK16: 0 | AL16: 0 | AM16: 0 | AN16: 0 | AO16: 0 | AQ16: 0 | AR16: 12.012679 | AS16: 218.82111 | AT16: 5.8826 | AU16: 0 | AV16: 0 | AW16: 0 | AX16: 0 | AY16: 0 | AZ16: 0 | BA16: 0 | BB16: 0 | BD16: 0 | BE16: 12.012679 | BF16: 24.721088 | BG16: 244.65652 | BH16: 47.5 | BI16: 455.11405 | BJ16: 0.9804 | BK16: 29.633582 | BL16: 26.145 | BM16: 0 | BN16: 25.886 | BO16: 0
B17: 数智管理中心 | C17: =SUM(E17:P17) -> 742.30561 | D17: =SUM(Q17:AB17) -> 84.149354 | E17: ='[3]部门-汇总页'!E4 -> 152.00266 | F17: ='[3]部门-汇总页'!F4 -> 25.5 | G17: ='[3]部门-汇总页'!G4 -> 204.43172 | H17: ='[3]部门-汇总页'!H4 -> 80.42 | I17: ='[3]部门-汇总页'!I4 -> 53.988445 | J17: ='[3]部门-汇总页'!J4 -> 154.27593 | K17: ='[3]部门-汇总页'!K4 -> 13.65 | L17: ='[3]部门-汇总页'!L4 -> 7.7093544 | ... AB17: ='[3]部门-汇总页'!AB4 -> 0 | AD17: 136.29616 | AE17: 32.531658 | AF17: 178.27316 | AG17: 27.225138 | AH17: 1.845 | AI17: 108.08082 | AJ17: 9.6451376 | AK17: 0 | AL17: 21.575 | AM17: 0.25 | AN17: 0 | AO17: 27.7525 | AQ17: 152.00266 | AR17: 25.5 | AS17: 277.29081 | AT17: 25.279354 | AU17: 12.33 | AV17: 162.86593 | AW17: 11.209354 | AX17: 0 | AY17: 21.575 | AZ17: 1 | BA17: 0 | BB17: 27.7525 | BD17: 152.00266 | BE17: 25.5 | BF17: 242.03172 | BG17: 42.82 | BH17: 53.988445 | BI17: 154.27593 | BJ17: 13.65 | BK17: 7.7093544 | BL17: 21.575 | BM17: 1 | BN17: 0 | BO17: 27.7525
B18: 福建分公司 | C18: =SUM(E18:P18) -> 520.89285 | D18: =SUM(Q18:AB18) -> 45.238066 | E18: ='[4]部门-汇总页'!E4 -> 25.496066 | F18: ='[4]部门-汇总页'!F4 -> 19.742 | G18: ='[4]部门-汇总页'!G4 -> 0 | H18: ='[4]部门-汇总页'!H4 -> 0 | I18: ='[4]部门-汇总页'!I4 -> 29.790517 | J18: ='[4]部门-汇总页'!J4 -> 79.477759 | K18: ='[4]部门-汇总页'!K4 -> 0.3125 | L18: ='[4]部门-汇总页'!L4 -> 85.483154 | ... AB18: ='[4]部门-汇总页'!AB4 -> 0 | AD18: 25.496066 | AE18: 44.213369 | AF18: 0 | AG18: 0 | AH18: 0 | AI18: 0 | AJ18: 0 | AK18: 0 | AL18: 0 | AM18: 0 | AN18: 0 | AO18: 0 | AQ18: 25.496066 | AR18: 19.742 | AS18: 24.471369 | AT18: 0 | AU18: 0 | AV18: 0 | AW18: 0 | AX18: 0 | AY18: 0 | AZ18: 0 | BA18: 0 | BB18: 0 | BD18: 25.496066 | BE18: 19.742 | BF18: 0 | BG18: 0 | BH18: 43.638017 | BI18: 18.748911 | BJ18: 0 | BK18: 0 | BL18: 0 | BM18: 0 | BN18: 0 | BO18: 0
B19: 广东分公司 | C19: =SUM(E19:P19) -> 1397.5278 | D19: =SUM(Q19:AB19) -> 12.988125 | E19: ='[5]部门-汇总页'!E4 -> 12.988125 | F19: ='[5]部门-汇总页'!F4 -> 0 | G19: ='[5]部门-汇总页'!G4 -> 0 | H19: ='[5]部门-汇总页'!H4 -> 0 | I19: ='[5]部门-汇总页'!I4 -> 39.018873 | J19: ='[5]部门-汇总页'!J4 -> 575.06145 | K19: ='[5]部门-汇总页'!K4 -> 11.6396 | L19: ='[5]部门-汇总页'!L4 -> 59.7325 | ... AB19: ='[5]部门-汇总页'!AB4 -> 0 | AD19: 12.988125 | AE19: 58.550465 | AF19: 25.5508 | AG19: 0 | AH19: 0 | AI19: 0 | AJ19: 0 | AK19: 0 | AL19: 0 | AM19: 0 | AN19: 0 | AO19: 0 | AQ19: 12.988125 | AR19: 0 | AS19: 33.3508 | AT19: 0 | AU19: 0 | AV19: 0 | AW19: 0 | AX19: 0 | AY19: 0 | AZ19: 0 | BA19: 0 | BB19: 0 | BD19: 12.988125 | BE19: 0 | BF19: 0 | BG19: 15.2916 | BH19: 23.727273 | BI19: 257.75975 | BJ19: 0 | BK19: 0 | BL19: 0 | BM19: 0 | BN19: 0 | BO19: 0
B20: 产品研发中心 | C20: =SUM(E20:P20) -> 0 | D20: =SUM(Q20:AB20) -> 10 | E20: ='[6]部门-汇总页'!E4 -> 0 | F20: ='[6]部门-汇总页'!F4 -> 0 | G20: ='[6]部门-汇总页'!G4 -> 0 | H20: ='[6]部门-汇总页'!H4 -> 0 | I20: ='[6]部门-汇总页'!I4 -> 0 | J20: ='[6]部门-汇总页'!J4 -> 0 | K20: ='[6]部门-汇总页'!K4 -> 0 | L20: ='[6]部门-汇总页'!L4 -> 0 | ... AB20: ='[6]部门-汇总页'!AB4 -> 0 | AD20: 0 | AE20: 0 | AF20: 0 | AG20: 0 | AH20: 0 | AI20: 0 | AJ20: 0 | AK20: 0 | AL20: 0 | AM20: 0 | AN20: 0 | AO20: 0 | AQ20: 0 | AR20: 0 | AS20: 0 | AT20: 0 | AU20: 0 | AV20: 0 | AW20: 0 | AX20: 0 | AY20: 0 | AZ20: 0 | BA20: 0 | BB20: 0 | BD20: 0 | BE20: 0 | BF20: 0 | BG20: 0 | BH20: 0 | BI20: 0 | BJ20: 0 | BK20: 0 | BL20: 0 | BM20: 0 | BN20: 0 | BO20: 0
B21: 市场经营拓展中心 | C21: =SUM(E21:P21) -> 2.38 | D21: =SUM(Q21:AB21) -> 0 | E21: ='[7]部门-汇总页'!E4 -> 0 | F21: ='[7]部门-汇总页'!F4 -> 0 | G21: ='[7]部门-汇总页'!G4 -> 0 | H21: ='[7]部门-汇总页'!H4 -> 0 | I21: ='[7]部门-汇总页'!I4 -> 0 | J21: ='[7]部门-汇总页'!J4 -> 0 | K21: ='[7]部门-汇总页'!K4 -> 0 | L21: ='[7]部门-汇总页'!L4 -> 0 | ... AB21: ='[7]部门-汇总页'!AB4 -> 0 | AD21: 0 | AE21: 0 | AF21: 0 | AG21: 0 | AH21: 0 | AI21: 0 | AJ21: 0 | AK21: 0 | AL21: 0 | AM21: 0 | AN21: 0 | AO21: 0 | AQ21: 0 | AR21: 0 | AS21: 0 | AT21: 0 | AU21: 0 | AV21: 0 | AW21: 0 | AX21: 0 | AY21: 0 | AZ21: 0 | BA21: 0 | BB21: 0 | BD21: 0 | BE21: 0 | BF21: 0 | BG21: 0 | BH21: 0 | BI21: 0 | BJ21: 0 | BK21: 0 | BL21: 0 | BM21: 0 | BN21: 0 | BO21: 0
B22: 合计 | C22: =SUM(C15:C21) -> 7556.4261 | D22: =SUM(D15:D21) -> 261.36343 | E22: =SUM(E15:E21) -> 198.40684 | F22: =SUM(F15:F21) -> 74.143372 | G22: =SUM(G15:G21) -> 230.0364 | H22: =SUM(H15:H21) -> 350.02594 | I22: =SUM(I15:I21) -> 268.66237 | J22: =SUM(J15:J21) -> 1684.464 | ... AB22: =SUM(AB15:AB21) -> 0 | AD22: 174.78035 | AE22: 148.88549 | AF22: 519.9365 | AG22: 27.225138 | AH22: 1.845 | AI22: 108.08082 | AJ22: 9.6451376 | AK22: 0 | AL22: 21.575 | AM22: 0.25 | AN22: 0 | AO22: 27.7525 | AQ22: 198.40684 | AR22: 74.143372 | AS22: 741.30599 | AT22: 31.161954 | AU22: 12.33 | AV22: 162.86593 | AW22: 11.209354 | AX22: 0 | AY22: 21.575 | AZ22: 1 | BA22: 0 | BB22: 27.7525 | BD22: 198.40684 | BE22: 74.143372 | BF22: 274.6728 | BG22: 340.87936 | BH22: 185.36959 | BI22: 1194.1761 | BJ22: 34.1304 | BK22: 76.590824 | BL22: 233.526 | BM22: 1 | BN22: 305.22501 | BO22: 94.8345
B24: 营收 | C24: 计划 | D24: 实际 | E24: 2026-01计划 | F24: 2026-02计划 | G24: 2026-03计划 | H24: 2026-04计划 | I24: 2026-05计划 | J24: 2026-06计划 | K24: 2026-07计划 | L24: 2026-08计划 | M24: 2026-09计划 | N24: 2026-10计划 | O24: 2026-11计划 | P24: 2026-12计划 | Q24: 2026-01实际 | R24: 2026-02实际 | S24: 2026-03实际 | T24: 2026-04实际 | U24: 2026-05实际 | V24: 2026-06实际 | W24: 2026-07实际 | X24: 2026-08实际 | Y24: 2026-09实际 | Z24: 2026-10实际 | AA24: 2026-11实际 | AB24: 2026-12实际 | AD24: 2026-01计划 | AE24: 2026-02计划 | AF24: 2026-03计划 | AG24: 2026-04计划 | AH24: 2026-05计划 | AI24: 2026-06计划 | AJ24: 2026-07计划 | AK24: 2026-08计划 | AL24: 2026-09计划 | AM24: 2026-10计划 | AN24: 2026-11计划 | AO24: 2026-12计划 | AQ24: 2026-01计划 | AR24: 2026-02计划 | AS24: 2026-03计划 | AT24: 2026-04计划 | AU24: 2026-05计划 | AV24: 2026-06计划 | AW24: 2026-07计划 | AX24: 2026-08计划 | AY24: 2026-09计划 | AZ24: 2026-10计划 | BA24: 2026-11计划 | BB24: 2026-12计划 | BD24: 2026-01计划 | BE24: 2026-02计划 | BF24: 2026-03计划 | BG24: 2026-04计划 | BH24: 2026-05计划 | BI24: 2026-06计划 | BJ24: 2026-07计划 | BK24: 2026-08计划 | BL24: 2026-09计划 | BM24: 2026-10计划 | BN24: 2026-11计划 | BO24: 2026-12计划
B25: 数字建造中心 | C25: =SUM(E25:P25) -> 4985.5687 | D25: =SUM(Q25:AB25) -> 119.36598 | E25: ='[1]部门-汇总页'!E5 -> 8.490566 | F25: ='[1]部门-汇总页'!F5 -> 20.198213 | G25: ='[1]部门-汇总页'!G5 -> 8.490566 | H25: ='[1]部门-汇总页'!H5 -> 65.255675 | I25: ='[1]部门-汇总页'!I5 -> 137.96706 | J25: ='[1]部门-汇总页'!J5 -> 737.18834 | K25: ='[1]部门-汇总页'!K5 -> 1.4150943 | L25: ='[1]部门-汇总页'!L5 -> 114.71698 | ... AB25: ='[1]部门-汇总页'!AB5 -> 0 | AD25: 0 | AE25: 11.433962 | AF25: 380.0921 | AG25: 0 | AH25: 0 | AI25: 0 | AJ25: 0 | AK25: 0 | AL25: 0 | AM25: 0 | AN25: 0 | AO25: 0 | AQ25: 8.490566 | AR25: 20.198213 | AS25: 303.71474 | AT25: 0 | AU25: 0 | AV25: 0 | AW25: 0 | AX25: 0 | AY25: 0 | AZ25: 0 | BA25: 0 | BB25: 0 | BD25: 8.490566 | BE25: 20.198213 | BF25: 8.490566 | BG25: 70.024426 | BH25: 68.698102 | BI25: 517.58212 | BJ25: 23.023585 | BK25: 110.9434 | BL25: 300.46766 | BM25: 0 | BN25: 338.31924 | BO25: 69.571698
B26: 智能运管中心 | C26: =SUM(E26:P26) -> 3133.2613 | D26: =SUM(Q26:AB26) -> 84.361964 | E26: ='[2]部门-汇总页'!E5 -> 0 | F26: ='[2]部门-汇总页'!F5 -> 31.602921 | G26: ='[2]部门-汇总页'!G5 -> 72.387352 | H26: ='[2]部门-汇总页'!H5 -> 702.65151 | I26: ='[2]部门-汇总页'!I5 -> 391.33396 | J26: ='[2]部门-汇总页'!J5 -> 555.51019 | K26: ='[2]部门-汇总页'!K5 -> 42.688679 | L26: ='[2]部门-汇总页'!L5 -> 375.0824 | ... AB26: ='[2]部门-汇总页'!AB5 -> 0 | AD26: 0 | AE26: 5.7122642 | AF26: 375.57345 | AG26: 0 | AH26: 0 | AI26: 0 | AJ26: 0 | AK26: 0 | AL26: 0 | AM26: 0 | AN26: 0 | AO26: 0 | AQ26: 0 | AR26: 31.602921 | AS26: 466.86982 | AT26: 27.747736 | AU26: 0 | AV26: 0 | AW26: 0 | AX26: 0 | AY26: 0 | AZ26: 0 | BA26: 0 | BB26: 0 | BD26: 0 | BE26: 31.602921 | BF26: 111.35762 | BG26: 475.49995 | BH26: 84.433962 | BI26: 953.7326 | BJ26: 1.6415094 | BK26: 51.037736 | BL26: 42.825472 | BM26: 0 | BN26: 24.420755 | BO26: 0
B27: 数智管理中心 | C27: =SUM(E27:P27) -> 1893.2479 | D27: =SUM(Q27:AB27) -> 169.12193 | E27: ='[3]部门-汇总页'!E5 -> 299.38613 | F27: ='[3]部门-汇总页'!F5 -> 50.09434 | G27: ='[3]部门-汇总页'!G5 -> 456.36652 | H27: ='[3]部门-汇总页'!H5 -> 282.41208 | I27: ='[3]部门-汇总页'!I5 -> 113.86348 | J27: ='[3]部门-汇总页'!J5 -> 321.40896 | K27: ='[3]部门-汇总页'!K5 -> 90.837269 | L27: ='[3]部门-汇总页'!L5 -> 17.924528 | ... AB27: ='[3]部门-汇总页'!AB5 -> 0 | AD27: 274.32728 | AE27: 67.638679 | AF27: 614.19952 | AG27: 60.318868 | AH27: 15.834906 | AI27: 287.70132 | AJ27: 41.216136 | AK27: 0 | AL27: 138.11019 | AM27: 0.94339623 | AN27: 0 | AO27: 110.67453 | AQ27: 299.38613 | AR27: 50.09434 | AS27: 712.53831 | AT27: 69.443396 | AU27: 20.377358 | AV27: 377.91689 | AW27: 41.216136 | AX27: 0 | AY27: 138.11019 | AZ27: 0.94339623 | BA27: 0 | BB27: 110.67453 | BD27: 299.38613 | BE27: 50.09434 | BF27: 511.0835 | BG27: 216.46868 | BH27: 113.86348 | BI27: 321.40896 | BJ27: 90.837269 | BK27: 17.924528 | BL27: 138.11019 | BM27: 0.94339623 | BN27: 0 | BO27: 110.67453
B28: 福建分公司 | C28: =SUM(E28:P28) -> 1588.2822 | D28: =SUM(Q28:AB28) -> 254.98727 | E28: ='[4]部门-汇总页'!E5 -> 50.447644 | F28: ='[4]部门-汇总页'!F5 -> 204.53962 | G28: ='[4]部门-汇总页'!G5 -> 0 | H28: ='[4]部门-汇总页'!H5 -> 0 | I28: ='[4]部门-汇总页'!I5 -> 74.178302 | J28: ='[4]部门-汇总页'!J5 -> 203.76548 | K28: ='[4]部门-汇总页'!K5 -> 7.8419811 | L28: ='[4]部门-汇总页'!L5 -> 153.71415 | ... AB28: ='[4]部门-汇总页'!AB5 -> 0 | AD28: 50.447644 | AE28: 230.45613 | AF28: 0 | AG28: 0 | AH28: 0 | AI28: 0 | AJ28: 0 | AK28: 0 | AL28: 0 | AM28: 0 | AN28: 0 | AO28: 0 | AQ28: 50.447644 | AR28: 204.53962 | AS28: 25.916509 | AT28: 0 | AU28: 0 | AV28: 0 | AW28: 0 | AX28: 0 | AY28: 0 | AZ28: 0 | BA28: 0 | BB28: 0 | BD28: 50.447644 | BE28: 204.53962 | BF28: 0 | BG28: 0 | BH28: 58.312736 | BI28: 99.105102 | BJ28: 0 | BK28: 0 | BL28: 0 | BM28: 0 | BN28: 0 | BO28: 0
B29: 广东分公司 | C29: =SUM(E29:P29) -> 2241.1938 | D29: =SUM(Q29:AB29) -> 40.247642 | E29: ='[5]部门-汇总页'!E5 -> 40.247642 | F29: ='[5]部门-汇总页'!F5 -> 0 | G29: ='[5]部门-汇总页'!G5 -> 0 | H29: ='[5]部门-汇总页'!H5 -> 0 | I29: ='[5]部门-汇总页'!I5 -> 61.643019 | J29: ='[5]部门-汇总页'!J5 -> 841.18334 | K29: ='[5]部门-汇总页'!K5 -> 39.798547 | L29: ='[5]部门-汇总页'!L5 -> 63.453373 | ... AB29: ='[5]部门-汇总页'!AB5 -> 0 | AD29: 40.247642 | AE29: 98.230088 | AF29: 93.898868 | AG29: 0 | AH29: 0 | AI29: 0 | AJ29: 0 | AK29: 0 | AL29: 0 | AM29: 0 | AN29: 0 | AO29: 0 | AQ29: 40.247642 | AR29: 0 | AS29: 92.981887 | AT29: 0 | AU29: 0 | AV29: 0 | AW29: 0 | AX29: 0 | AY29: 0 | AZ29: 0 | BA29: 0 | BB29: 0 | BD29: 40.247642 | BE29: 0 | BF29: 0 | BG29: 23.90717 | BH29: 37.735849 | BI29: 747.31004 | BJ29: 0 | BK29: 0 | BL29: 0 | BM29: 0 | BN29: 0 | BO29: 0
B30: 产品研发中心 | C30: =SUM(E30:P30) -> 0 | D30: =SUM(Q30:AB30) -> 9.4339623 | E30: ='[6]部门-汇总页'!E5 -> 0 | F30: ='[6]部门-汇总页'!F5 -> 0 | G30: ='[6]部门-汇总页'!G5 -> 0 | H30: ='[6]部门-汇总页'!H5 -> 0 | I30: ='[6]部门-汇总页'!I5 -> 0 | J30: ='[6]部门-汇总页'!J5 -> 0 | K30: ='[6]部门-汇总页'!K5 -> 0 | L30: ='[6]部门-汇总页'!L5 -> 0 | ... AB30: ='[6]部门-汇总页'!AB5 -> 0 | AD30: 0 | AE30: 0 | AF30: 0 | AG30: 0 | AH30: 0 | AI30: 0 | AJ30: 0 | AK30: 0 | AL30: 0 | AM30: 0 | AN30: 0 | AO30: 0 | AQ30: 0 | AR30: 0 | AS30: 0 | AT30: 0 | AU30: 0 | AV30: 0 | AW30: 0 | AX30: 0 | AY30: 0 | AZ30: 0 | BA30: 0 | BB30: 0 | BD30: 0 | BE30: 0 | BF30: 0 | BG30: 0 | BH30: 0 | BI30: 0 | BJ30: 0 | BK30: 0 | BL30: 0 | BM30: 0 | BN30: 0 | BO30: 0
B31: 市场经营拓展中心 | C31: =SUM(E31:P31) -> 27.245283 | D31: =SUM(Q31:AB31) -> 0 | E31: ='[7]部门-汇总页'!E5 -> 0 | F31: ='[7]部门-汇总页'!F5 -> 0 | G31: ='[7]部门-汇总页'!G5 -> 0 | H31: ='[7]部门-汇总页'!H5 -> 0 | I31: ='[7]部门-汇总页'!I5 -> 0 | J31: ='[7]部门-汇总页'!J5 -> 0 | K31: ='[7]部门-汇总页'!K5 -> 0 | L31: ='[7]部门-汇总页'!L5 -> 0 | ... AB31: ='[7]部门-汇总页'!AB5 -> 0 | AD31: 0 | AE31: 0 | AF31: 0 | AG31: 0 | AH31: 0 | AI31: 0 | AJ31: 0 | AK31: 0 | AL31: 0 | AM31: 0 | AN31: 0 | AO31: 0 | AQ31: 0 | AR31: 0 | AS31: 0 | AT31: 0 | AU31: 0 | AV31: 0 | AW31: 0 | AX31: 0 | AY31: 0 | AZ31: 0 | BA31: 0 | BB31: 0 | BD31: 0 | BE31: 0 | BF31: 0 | BG31: 0 | BH31: 0 | BI31: 0 | BJ31: 0 | BK31: 0 | BL31: 0 | BM31: 0 | BN31: 0 | BO31: 0
B32: 合计 | C32: =SUM(C25:C31) -> 13868.799 | D32: =SUM(D25:D31) -> 677.51875 | E32: =SUM(E25:E31) -> 398.57198 | F32: =SUM(F25:F31) -> 306.4351 | G32: =SUM(G25:G31) -> 537.24444 | H32: =SUM(H25:H31) -> 1050.3193 | I32: =SUM(I25:I31) -> 778.98583 | J32: =SUM(J25:J31) -> 2659.0563 | ... AB32: =SUM(AB25:AB31) -> 0 | AD32: 365.02257 | AE32: 413.47113 | AF32: 1463.7639 | AG32: 60.318868 | AH32: 15.834906 | AI32: 287.70132 | AJ32: 41.216136 | AK32: 0 | AL32: 138.11019 | AM32: 0.94339623 | AN32: 0 | AO32: 110.67453 | AQ32: 398.57198 | AR32: 306.4351 | AS32: 1602.0213 | AT32: 97.191132 | AU32: 20.377358 | AV32: 377.91689 | AW32: 41.216136 | AX32: 0 | AY32: 138.11019 | AZ32: 0.94339623 | BA32: 0 | BB32: 110.67453 | BD32: 398.57198 | BE32: 306.4351 | BF32: 630.93168 | BG32: 785.90023 | BH32: 363.04413 | BI32: 2639.1388 | BJ32: 115.50236 | BK32: 179.90566 | BL32: 481.40332 | BM32: 0.94339623 | BN32: 362.73999 | BO32: 180.24623
B34: 自营营收 | C34: 计划 | D34: 实际 | E34: 2026-01计划 | F34: 2026-02计划 | G34: 2026-03计划 | H34: 2026-04计划 | I34: 2026-05计划 | J34: 2026-06计划 | K34: 2026-07计划 | L34: 2026-08计划 | M34: 2026-09计划 | N34: 2026-10计划 | O34: 2026-11计划 | P34: 2026-12计划 | Q34: 2026-01实际 | R34: 2026-02实际 | S34: 2026-03实际 | T34: 2026-04实际 | U34: 2026-05实际 | V34: 2026-06实际 | W34: 2026-07实际 | X34: 2026-08实际 | Y34: 2026-09实际 | Z34: 2026-10实际 | AA34: 2026-11实际 | AB34: 2026-12实际 | AD34: 2026-01计划 | AE34: 2026-02计划 | AF34: 2026-03计划 | AG34: 2026-04计划 | AH34: 2026-05计划 | AI34: 2026-06计划 | AJ34: 2026-07计划 | AK34: 2026-08计划 | AL34: 2026-09计划 | AM34: 2026-10计划 | AN34: 2026-11计划 | AO34: 2026-12计划 | AQ34: 2026-01计划 | AR34: 2026-02计划 | AS34: 2026-03计划 | AT34: 2026-04计划 | AU34: 2026-05计划 | AV34: 2026-06计划 | AW34: 2026-07计划 | AX34: 2026-08计划 | AY34: 2026-09计划 | AZ34: 2026-10计划 | BA34: 2026-11计划 | BB34: 2026-12计划 | BD34: 2026-01计划 | BE34: 2026-02计划 | BF34: 2026-03计划 | BG34: 2026-04计划 | BH34: 2026-05计划 | BI34: 2026-06计划 | BJ34: 2026-07计划 | BK34: 2026-08计划 | BL34: 2026-09计划 | BM34: 2026-10计划 | BN34: 2026-11计划 | BO34: 2026-12计划
B35: 数字建造中心 | C35: =SUM(E35:P35) -> 2926.4725 | D35: =SUM(Q35:AB35) -> 80.198979 | E35: ='[1]部门-汇总页'!E6 -> 7.4716868 | F35: ='[1]部门-汇总页'!F6 -> 15.918828 | G35: ='[1]部门-汇总页'!G6 -> 7.4716868 | H35: ='[1]部门-汇总页'!H6 -> 43.627883 | I35: ='[1]部门-汇总页'!I6 -> 55.10924 | J35: ='[1]部门-汇总页'!J6 -> 430.28898 | K35: ='[1]部门-汇总页'!K6 -> 1.4150943 | L35: ='[1]部门-汇总页'!L6 -> 40.347058 | ... AB35: ='[1]部门-汇总页'!AB6 -> 0 | AD35: 0 | AE35: 11.433962 | AF35: 215.78418 | AG35: 0 | AH35: 0 | AI35: 0 | AJ35: 0 | AK35: 0 | AL35: 0 | AM35: 0 | AN35: 0 | AO35: 0 | AQ35: 7.4716868 | AR35: 15.918828 | AS35: 176.68983 | AT35: 0 | AU35: 0 | AV35: 0 | AW35: 0 | AX35: 0 | AY35: 0 | AZ35: 0 | BA35: 0 | BB35: 0 | BD35: 7.4716868 | BE35: 15.918828 | BF35: 7.4716868 | BG35: 36.411564 | BH35: 15.580999 | BI35: 289.60872 | BJ35: 18.396226 | BK35: 37.026309 | BL35: 173.3972 | BM35: 0 | BN35: 263.1473 | BO35: 63.284906
B36: 智能运管中心 | C36: =SUM(E36:P36) -> 1683.8897 | D36: =SUM(Q36:AB36) -> 21.783695 | E36: ='[2]部门-汇总页'!E6 -> 0 | F36: ='[2]部门-汇总页'!F6 -> 11.322533 | G36: ='[2]部门-汇总页'!G6 -> 16.580441 | H36: ='[2]部门-汇总页'!H6 -> 211.71735 | I36: ='[2]部门-汇总页'!I6 -> 82.484906 | J36: ='[2]部门-汇总页'!J6 -> 393.23917 | K36: ='[2]部门-汇总页'!K6 -> 22.151321 | L36: ='[2]部门-汇总页'!L6 -> 125.19165 | ... AB36: ='[2]部门-汇总页'!AB6 -> 0 | AD36: 0 | AE36: 1.3867925 | AF36: 81.253371 | AG36: 0 | AH36: 0 | AI36: 0 | AJ36: 0 | AK36: 0 | AL36: 0 | AM36: 0 | AN36: 0 | AO36: 0 | AQ36: 0 | AR36: 11.322533 | AS36: 206.33178 | AT36: 5.5496226 | AU36: 0 | AV36: 0 | AW36: 0 | AX36: 0 | AY36: 0 | AZ36: 0 | BA36: 0 | BB36: 0 | BD36: 0 | BE36: 11.322533 | BF36: 22.807344 | BG36: 230.29981 | BH36: 44.811321 | BI36: 429.14642 | BJ36: 0.92490566 | BK36: 27.95621 | BL36: 24.665094 | BM36: 0 | BN36: 24.420755 | BO36: 0
B37: 数智管理中心 | C37: =SUM(E37:P37) -> 699.36514 | D37: =SUM(Q37:AB37) -> 79.386183 | E37: ='[3]部门-汇总页'!E6 -> 143.56855 | F37: ='[3]部门-汇总页'!F6 -> 24.056604 | G37: ='[3]部门-汇总页'!G6 -> 192.7965 | H37: ='[3]部门-汇总页'!H6 -> 75.629766 | I37: ='[3]部门-汇总页'!I6 -> 50.699724 | J37: ='[3]部门-汇总页'!J6 -> 145.54333 | K37: ='[3]部门-汇总页'!K6 -> 12.717218 | L37: ='[3]部门-汇总页'!L6 -> 7.2729758 | ... AB37: ='[3]部门-汇总页'!AB6 -> 0 | AD37: 128.71066 | AE37: 31.007224 | AF37: 167.69085 | AG37: 25.819941 | AH37: 1.740566 | AI37: 101.95717 | AJ37: 9.0581246 | AK37: 0 | AL37: 20.115616 | AM37: 0.23584906 | AN37: 0 | AO37: 26.021463 | AQ37: 143.56855 | AR37: 24.056604 | AS37: 261.06056 | AT37: 23.848448 | AU37: 11.632075 | AV37: 153.52802 | AW37: 10.533801 | AX37: 0 | AY37: 20.115616 | AZ37: 0.94339623 | BA37: 0 | BB37: 26.021463 | BD37: 143.56855 | BE37: 24.056604 | BF37: 228.2682 | BG37: 40.158068 | BH37: 50.699724 | BI37: 145.54333 | BJ37: 12.717218 | BK37: 7.2729758 | BL37: 20.115616 | BM37: 0.94339623 | BN37: 0 | BO37: 26.021463
B38: 福建分公司 | C38: =SUM(E38:P38) -> 491.40835 | D38: =SUM(Q38:AB38) -> 42.677421 | E38: ='[4]部门-汇总页'!E6 -> 24.052892 | F38: ='[4]部门-汇总页'!F6 -> 18.624528 | G38: ='[4]部门-汇总页'!G6 -> 0 | H38: ='[4]部门-汇总页'!H6 -> 0 | I38: ='[4]部门-汇总页'!I6 -> 28.104261 | J38: ='[4]部门-汇总页'!J6 -> 74.979018 | K38: ='[4]部门-汇总页'!K6 -> 0.29481132 | L38: ='[4]部门-汇总页'!L6 -> 80.644485 | ... AB38: ='[4]部门-汇总页'!AB6 -> 0 | AD38: 24.052892 | AE38: 41.710725 | AF38: 0 | AG38: 0 | AH38: 0 | AI38: 0 | AJ38: 0 | AK38: 0 | AL38: 0 | AM38: 0 | AN38: 0 | AO38: 0 | AQ38: 24.052892 | AR38: 18.624528 | AS38: 23.086197 | AT38: 0 | AU38: 0 | AV38: 0 | AW38: 0 | AX38: 0 | AY38: 0 | AZ38: 0 | BA38: 0 | BB38: 0 | BD38: 24.052892 | BE38: 18.624528 | BF38: 0 | BG38: 0 | BH38: 41.167941 | BI38: 17.687651 | BJ38: 0 | BK38: 0 | BL38: 0 | BM38: 0 | BN38: 0 | BO38: 0
B39: 广东分公司 | C39: =SUM(E39:P39) -> 1315.2838 | D39: =SUM(Q39:AB39) -> 12.252948 | E39: ='[5]部门-汇总页'!E6 -> 12.252948 | F39: ='[5]部门-汇总页'!F6 -> 0 | G39: ='[5]部门-汇总页'!G6 -> 0 | H39: ='[5]部门-汇总页'!H6 -> 0 | I39: ='[5]部门-汇总页'!I6 -> 36.810257 | J39: ='[5]部门-汇总页'!J6 -> 542.5108 | K39: ='[5]部门-汇总页'!K6 -> 10.877086 | L39: ='[5]部门-汇总页'!L6 -> 53.316455 | ... AB39: ='[5]部门-汇总页'!AB6 -> 0 | AD39: 12.252948 | AE39: 51.814571 | AF39: 24.104528 | AG39: 0 | AH39: 0 | AI39: 0 | AJ39: 0 | AK39: 0 | AL39: 0 | AM39: 0 | AN39: 0 | AO39: 0 | AQ39: 12.252948 | AR39: 0 | AS39: 31.463019 | AT39: 0 | AU39: 0 | AV39: 0 | AW39: 0 | AX39: 0 | AY39: 0 | AZ39: 0 | BA39: 0 | BB39: 0 | BD39: 12.252948 | BE39: 0 | BF39: 0 | BG39: 14.426038 | BH39: 22.38422 | BI39: 243.16957 | BJ39: 0 | BK39: 0 | BL39: 0 | BM39: 0 | BN39: 0 | BO39: 0
B40: 产品研发中心 | C40: =SUM(E40:P40) -> 0 | D40: =SUM(Q40:AB40) -> 9.4339623 | E40: ='[6]部门-汇总页'!E6 -> 0 | F40: ='[6]部门-汇总页'!F6 -> 0 | G40: ='[6]部门-汇总页'!G6 -> 0 | H40: ='[6]部门-汇总页'!H6 -> 0 | I40: ='[6]部门-汇总页'!I6 -> 0 | J40: ='[6]部门-汇总页'!J6 -> 0 | K40: ='[6]部门-汇总页'!K6 -> 0 | L40: ='[6]部门-汇总页'!L6 -> 0 | ... AB40: ='[6]部门-汇总页'!AB6 -> 0 | AD40: 0 | AE40: 0 | AF40: 0 | AG40: 0 | AH40: 0 | AI40: 0 | AJ40: 0 | AK40: 0 | AL40: 0 | AM40: 0 | AN40: 0 | AO40: 0 | AQ40: 0 | AR40: 0 | AS40: 0 | AT40: 0 | AU40: 0 | AV40: 0 | AW40: 0 | AX40: 0 | AY40: 0 | AZ40: 0 | BA40: 0 | BB40: 0 | BD40: 0 | BE40: 0 | BF40: 0 | BG40: 0 | BH40: 0 | BI40: 0 | BJ40: 0 | BK40: 0 | BL40: 0 | BM40: 0 | BN40: 0 | BO40: 0
B41: 市场经营拓展中心 | C41: =SUM(E41:P41) -> 2.245283 | D41: =SUM(Q41:AB41) -> 0 | E41: ='[7]部门-汇总页'!E6 -> 0 | F41: ='[7]部门-汇总页'!F6 -> 0 | G41: ='[7]部门-汇总页'!G6 -> 0 | H41: ='[7]部门-汇总页'!H6 -> 0 | I41: ='[7]部门-汇总页'!I6 -> 0 | J41: ='[7]部门-汇总页'!J6 -> 0 | K41: ='[7]部门-汇总页'!K6 -> 0 | L41: ='[7]部门-汇总页'!L6 -> 0 | ... AB41: ='[7]部门-汇总页'!AB6 -> 0 | AD41: 0 | AE41: 0 | AF41: 0 | AG41: 0 | AH41: 0 | AI41: 0 | AJ41: 0 | AK41: 0 | AL41: 0 | AM41: 0 | AN41: 0 | AO41: 0 | AQ41: 0 | AR41: 0 | AS41: 0 | AT41: 0 | AU41: 0 | AV41: 0 | AW41: 0 | AX41: 0 | AY41: 0 | AZ41: 0 | BA41: 0 | BB41: 0 | BD41: 0 | BE41: 0 | BF41: 0 | BG41: 0 | BH41: 0 | BI41: 0 | BJ41: 0 | BK41: 0 | BL41: 0 | BM41: 0 | BN41: 0 | BO41: 0
B42: 合计 | C42: =SUM(C35:C41) -> 7118.6649 | D42: =SUM(D35:D41) -> 245.73319 | E42: =SUM(E35:E41) -> 187.34608 | F42: =SUM(F35:F41) -> 69.922494 | G42: =SUM(G35:G41) -> 216.84863 | H42: =SUM(H35:H41) -> 330.97499 | I42: =SUM(I35:I41) -> 253.20839 | J42: =SUM(J35:J41) -> 1586.5613 | ... AB42: =SUM(AB35:AB41) -> 0 | AD42: 165.0165 | AE42: 137.35328 | AF42: 488.83292 | AG42: 25.819941 | AH42: 1.740566 | AI42: 101.95717 | AJ42: 9.0581246 | AK42: 0 | AL42: 20.115616 | AM42: 0.23584906 | AN42: 0 | AO42: 26.021463 | AQ42: 187.34608 | AR42: 69.922494 | AS42: 698.63139 | AT42: 29.39807 | AU42: 11.632075 | AV42: 153.52802 | AW42: 10.533801 | AX42: 0 | AY42: 20.115616 | AZ42: 0.94339623 | BA42: 0 | BB42: 26.021463 | BD42: 187.34608 | BE42: 69.922494 | BF42: 258.54723 | BG42: 321.29548 | BH42: 174.6442 | BI42: 1125.1557 | BJ42: 32.03835 | BK42: 72.255494 | BL42: 218.17791 | BM42: 0.94339623 | BN42: 287.56805 | BO42: 89.306369
B44: 收款 | C44: 计划 | D44: 实际 | E44: 2026-01计划 | F44: 2026-02计划 | G44: 2026-03计划 | H44: 2026-04计划 | I44: 2026-05计划 | J44: 2026-06计划 | K44: 2026-07计划 | L44: 2026-08计划 | M44: 2026-09计划 | N44: 2026-10计划 | O44: 2026-11计划 | P44: 2026-12计划 | Q44: 2026-01实际 | R44: 2026-02实际 | S44: 2026-03实际 | T44: 2026-04实际 | U44: 2026-05实际 | V44: 2026-06实际 | W44: 2026-07实际 | X44: 2026-08实际 | Y44: 2026-09实际 | Z44: 2026-10实际 | AA44: 2026-11实际 | AB44: 2026-12实际 | AD44: 2026-01计划 | AE44: 2026-02计划 | AF44: 2026-03计划 | AG44: 2026-04计划 | AH44: 2026-05计划 | AI44: 2026-06计划 | AJ44: 2026-07计划 | AK44: 2026-08计划 | AL44: 2026-09计划 | AM44: 2026-10计划 | AN44: 2026-11计划 | AO44: 2026-12计划 | AQ44: 2026-01计划 | AR44: 2026-02计划 | AS44: 2026-03计划 | AT44: 2026-04计划 | AU44: 2026-05计划 | AV44: 2026-06计划 | AW44: 2026-07计划 | AX44: 2026-08计划 | AY44: 2026-09计划 | AZ44: 2026-10计划 | BA44: 2026-11计划 | BB44: 2026-12计划 | BD44: 2026-01计划 | BE44: 2026-02计划 | BF44: 2026-03计划 | BG44: 2026-04计划 | BH44: 2026-05计划 | BI44: 2026-06计划 | BJ44: 2026-07计划 | BK44: 2026-08计划 | BL44: 2026-09计划 | BM44: 2026-10计划 | BN44: 2026-11计划 | BO44: 2026-12计划
B45: 数字建造中心 | C45: =SUM(E45:P45) -> 4995.5344 | D45: =SUM(Q45:AB45) -> 1132.1252 | E45: ='[1]部门-汇总页'!E7 -> 24.1 | F45: ='[1]部门-汇总页'!F7 -> 534.8933 | G45: ='[1]部门-汇总页'!G7 -> 36.3648 | H45: ='[1]部门-汇总页'!H7 -> 0 | I45: ='[1]部门-汇总页'!I7 -> 174.02285 | J45: ='[1]部门-汇总页'!J7 -> 462.79545 | K45: ='[1]部门-汇总页'!K7 -> 0 | L45: ='[1]部门-汇总页'!L7 -> 518 | ... AB45: ='[1]部门-汇总页'!AB7 -> 0 | AD45: 15.1 | AE45: 302.9084 | AF45: 671.1985 | AG45: 0 | AH45: 0 | AI45: 0 | AJ45: 0 | AK45: 0 | AL45: 0 | AM45: 0 | AN45: 0 | AO45: 0 | AQ45: 24.1 | AR45: 534.8933 | AS45: 539.24 | AT45: 0 | AU45: 0 | AV45: 0 | AW45: 0 | AX45: 0 | AY45: 0 | AZ45: 0 | BA45: 0 | BB45: 0 | BD45: 24.1 | BE45: 534.8933 | BF45: 36.3648 | BG45: 136.3405 | BH45: 10 | BI45: 756.74876 | BJ45: 0 | BK45: 0 | BL45: 0 | BM45: 0 | BN45: 0 | BO45: 92.08
B46: 智能运管中心 | C46: =SUM(E46:P46) -> 5536.9945 | D46: =SUM(Q46:AB46) -> 2054.1274 | E46: ='[2]部门-汇总页'!E7 -> 49.9 | F46: ='[2]部门-汇总页'!F7 -> 519.6044 | G46: ='[2]部门-汇总页'!G7 -> 1043.325 | H46: ='[2]部门-汇总页'!H7 -> 821.36205 | I46: ='[2]部门-汇总页'!I7 -> 659.81843 | J46: ='[2]部门-汇总页'!J7 -> 779.497 | K46: ='[2]部门-汇总页'!K7 -> 336.75272 | L46: ='[2]部门-汇总页'!L7 -> 0 | ... AB46: ='[2]部门-汇总页'!AB7 -> 0 | AD46: 124.61242 | AE46: 890.93532 | AF46: 1139.5674 | AG46: 0 | AH46: 0 | AI46: 0 | AJ46: 0 | AK46: 0 | AL46: 0 | AM46: 0 | AN46: 0 | AO46: 0 | AQ46: 49.9 | AR46: 519.6044 | AS46: 1863.0291 | AT46: 1.47063 | AU46: 0 | AV46: 0 | AW46: 0 | AX46: 0 | AY46: 0 | AZ46: 0 | BA46: 0 | BB46: 0 | BD46: 49.9 | BE46: 519.6044 | BF46: 1072.5368 | BG46: 508.15489 | BH46: 666.34657 | BI46: 179.55 | BJ46: 0 | BK46: 0 | BL46: 0 | BM46: 0 | BN46: 0 | BO46: 0
B47: 数智管理中心 | C47: =SUM(E47:P47) -> 2751.1453 | D47: =SUM(Q47:AB47) -> 747.51265 | E47: ='[3]部门-汇总页'!E7 -> 699.9493 | F47: ='[3]部门-汇总页'!F7 -> 422.96 | G47: ='[3]部门-汇总页'!G7 -> 533.735 | H47: ='[3]部门-汇总页'!H7 -> 218.1935 | I47: ='[3]部门-汇总页'!I7 -> 231.635 | J47: ='[3]部门-汇总页'!J7 -> 240.545 | K47: ='[3]部门-汇总页'!K7 -> 8.3 | L47: ='[3]部门-汇总页'!L7 -> 107.85 | ... AB47: ='[3]部门-汇总页'!AB7 -> 0 | AD47: 673.68 | AE47: 158.485 | AF47: 487.4993 | AG47: 197.6485 | AH47: 32.585 | AI47: 103.845 | AJ47: 99.8 | AK47: 27.25 | AL47: 3.2 | AM47: 146 | AN47: 0 | AO47: 119.7775 | AQ47: 699.9493 | AR47: 422.96 | AS47: 549.97 | AT47: 268.2235 | AU47: 32.585 | AV47: 155.545 | AW47: 99.8 | AX47: 27.25 | AY47: 3.2 | AZ47: 146 | BA47: 0 | BB47: 119.7775 | BD47: 699.9493 | BE47: 422.96 | BF47: 563.435 | BG47: 241.0935 | BH47: 212.635 | BI47: 215.045 | BJ47: 8.3 | BK47: 99.75 | BL47: 22.2 | BM47: 146 | BN47: 0 | BO47: 119.7775
B48: 福建分公司 | C48: =SUM(E48:P48) -> 2327.6898 | D48: =SUM(Q48:AB48) -> 329.957 | E48: ='[4]部门-汇总页'!E7 -> 71.003521 | F48: ='[4]部门-汇总页'!F7 -> 284.397 | G48: ='[4]部门-汇总页'!G7 -> 61.045 | H48: ='[4]部门-汇总页'!H7 -> 17.56 | I48: ='[4]部门-汇总页'!I7 -> 214.79651 | J48: ='[4]部门-汇总页'!J7 -> 233.18612 | K48: ='[4]部门-汇总页'!K7 -> 63.81 | L48: ='[4]部门-汇总页'!L7 -> 54.202 | ... AB48: ='[4]部门-汇总页'!AB7 -> 0 | AD48: 71.003521 | AE48: 239.352 | AF48: 234.1296 | AG48: 0 | AH48: 0 | AI48: 0 | AJ48: 0 | AK48: 0 | AL48: 0 | AM48: 0 | AN48: 0 | AO48: 0 | AQ48: 71.003521 | AR48: 284.397 | AS48: 106.7646 | AT48: 0 | AU48: 0 | AV48: 0 | AW48: 0 | AX48: 0 | AY48: 0 | AZ48: 0 | BA48: 0 | BB48: 0 | BD48: 71.003521 | BE48: 284.397 | BF48: 61.045 | BG48: 89.4531 | BH48: 63.035032 | BI48: 182.153 | BJ48: 0 | BK48: 0 | BL48: 0 | BM48: 0 | BN48: 0 | BO48: 0
B49: 广东分公司 | C49: =SUM(E49:P49) -> 2892.139 | D49: =SUM(Q49:AB49) -> 579.91083 | E49: ='[5]部门-汇总页'!E7 -> 390.47527 | F49: ='[5]部门-汇总页'!F7 -> 30.64306 | G49: ='[5]部门-汇总页'!G7 -> 16.2 | H49: ='[5]部门-汇总页'!H7 -> 28.24306 | I49: ='[5]部门-汇总页'!I7 -> 285 | J49: ='[5]部门-汇总页'!J7 -> 551.1224 | K49: ='[5]部门-汇总页'!K7 -> 36 | L49: ='[5]部门-汇总页'!L7 -> 373.21214 | ... AB49: ='[5]部门-汇总页'!AB7 -> 0 | AD49: 390.47527 | AE49: 117.72 | AF49: 335.5624 | AG49: 0 | AH49: 0 | AI49: 0 | AJ49: 0 | AK49: 0 | AL49: 0 | AM49: 0 | AN49: 0 | AO49: 0 | AQ49: 390.47527 | AR49: 30.64306 | AS49: 435.81222 | AT49: 0 | AU49: 0 | AV49: 0 | AW49: 0 | AX49: 0 | AY49: 0 | AZ49: 0 | BA49: 0 | BB49: 0 | BD49: 390.47527 | BE49: 30.64306 | BF49: 0.86 | BG49: 304.44306 | BH49: 298.94 | BI49: 544.35688 | BJ49: 0 | BK49: 0 | BL49: 0 | BM49: 0 | BN49: 0 | BO49: 0
B50: 产品研发中心 | C50: =SUM(E50:P50) -> 0 | D50: =SUM(Q50:AB50) -> 10 | E50: ='[6]部门-汇总页'!E7 -> 0 | F50: ='[6]部门-汇总页'!F7 -> 0 | G50: ='[6]部门-汇总页'!G7 -> 0 | H50: ='[6]部门-汇总页'!H7 -> 0 | I50: ='[6]部门-汇总页'!I7 -> 0 | J50: ='[6]部门-汇总页'!J7 -> 0 | K50: ='[6]部门-汇总页'!K7 -> 0 | L50: ='[6]部门-汇总页'!L7 -> 0 | ... AB50: ='[6]部门-汇总页'!AB7 -> 0 | AD50: 0 | AE50: 0 | AF50: 0 | AG50: 0 | AH50: 0 | AI50: 0 | AJ50: 0 | AK50: 0 | AL50: 0 | AM50: 0 | AN50: 0 | AO50: 0 | AQ50: 0 | AR50: 0 | AS50: 0 | AT50: 0 | AU50: 0 | AV50: 0 | AW50: 0 | AX50: 0 | AY50: 0 | AZ50: 0 | BA50: 0 | BB50: 0 | BD50: 0 | BE50: 0 | BF50: 0 | BG50: 0 | BH50: 0 | BI50: 0 | BJ50: 0 | BK50: 0 | BL50: 0 | BM50: 0 | BN50: 0 | BO50: 0
B51: 市场经营拓展中心 | C51: =SUM(E51:P51) -> 0 | D51: =SUM(Q51:AB51) -> 11.546356 | E51: ='[7]部门-汇总页'!E7 -> 0 | F51: ='[7]部门-汇总页'!F7 -> 0 | G51: ='[7]部门-汇总页'!G7 -> 0 | H51: ='[7]部门-汇总页'!H7 -> 0 | I51: ='[7]部门-汇总页'!I7 -> 0 | J51: ='[7]部门-汇总页'!J7 -> 0 | K51: ='[7]部门-汇总页'!K7 -> 0 | L51: ='[7]部门-汇总页'!L7 -> 0 | ... AB51: ='[7]部门-汇总页'!AB7 -> 0 | AD51: 0 | AE51: 0 | AF51: 0 | AG51: 0 | AH51: 0 | AI51: 0 | AJ51: 0 | AK51: 0 | AL51: 0 | AM51: 0 | AN51: 0 | AO51: 0 | AQ51: 0 | AR51: 0 | AS51: 0 | AT51: 0 | AU51: 0 | AV51: 0 | AW51: 0 | AX51: 0 | AY51: 0 | AZ51: 0 | BA51: 0 | BB51: 0 | BD51: 0 | BE51: 0 | BF51: 0 | BG51: 0 | BH51: 0 | BI51: 0 | BJ51: 0 | BK51: 0 | BL51: 0 | BM51: 0 | BN51: 0 | BO51: 0
B52: 合计 | C52: =SUM(C45:C51) -> 18503.503 | D52: =SUM(D45:D51) -> 4865.1795 | E52: =SUM(E45:E51) -> 1235.4281 | F52: =SUM(F45:F51) -> 1792.4978 | G52: =SUM(G45:G51) -> 1690.6698 | H52: =SUM(H45:H51) -> 1085.3586 | I52: =SUM(I45:I51) -> 1565.2728 | J52: =SUM(J45:J51) -> 2267.146 | ... AB52: =SUM(AB45:AB51) -> 0 | AD52: 1274.8712 | AE52: 1709.4007 | AF52: 2867.9572 | AG52: 197.6485 | AH52: 32.585 | AI52: 103.845 | AJ52: 99.8 | AK52: 27.25 | AL52: 3.2 | AM52: 146 | AN52: 0 | AO52: 119.7775 | AQ52: 1235.4281 | AR52: 1792.4978 | AS52: 3494.8159 | AT52: 269.69413 | AU52: 32.585 | AV52: 155.545 | AW52: 99.8 | AX52: 27.25 | AY52: 3.2 | AZ52: 146 | BA52: 0 | BB52: 119.7775 | BD52: 1235.4281 | BE52: 1792.4978 | BF52: 1734.2416 | BG52: 1279.4851 | BH52: 1250.9566 | BI52: 1877.8536 | BJ52: 8.3 | BK52: 99.75 | BL52: 22.2 | BM52: 146 | BN52: 0 | BO52: 211.8575
B54: 净收款 | C54: 计划 | D54: 实际 | E54: 2026-01计划 | F54: 2026-02计划 | G54: 2026-03计划 | H54: 2026-04计划 | I54: 2026-05计划 | J54: 2026-06计划 | K54: 2026-07计划 | L54: 2026-08计划 | M54: 2026-09计划 | N54: 2026-10计划 | O54: 2026-11计划 | P54: 2026-12计划 | Q54: 2026-01实际 | R54: 2026-02实际 | S54: 2026-03实际 | T54: 2026-04实际 | U54: 2026-05实际 | V54: 2026-06实际 | W54: 2026-07实际 | X54: 2026-08实际 | Y54: 2026-09实际 | Z54: 2026-10实际 | AA54: 2026-11实际 | AB54: 2026-12实际 | AD54: 2026-01计划 | AE54: 2026-02计划 | AF54: 2026-03计划 | AG54: 2026-04计划 | AH54: 2026-05计划 | AI54: 2026-06计划 | AJ54: 2026-07计划 | AK54: 2026-08计划 | AL54: 2026-09计划 | AM54: 2026-10计划 | AN54: 2026-11计划 | AO54: 2026-12计划 | AQ54: 2026-01计划 | AR54: 2026-02计划 | AS54: 2026-03计划 | AT54: 2026-04计划 | AU54: 2026-05计划 | AV54: 2026-06计划 | AW54: 2026-07计划 | AX54: 2026-08计划 | AY54: 2026-09计划 | AZ54: 2026-10计划 | BA54: 2026-11计划 | BB54: 2026-12计划 | BD54: 2026-01计划 | BE54: 2026-02计划 | BF54: 2026-03计划 | BG54: 2026-04计划 | BH54: 2026-05计划 | BI54: 2026-06计划 | BJ54: 2026-07计划 | BK54: 2026-08计划 | BL54: 2026-09计划 | BM54: 2026-10计划 | BN54: 2026-11计划 | BO54: 2026-12计划
B55: 数字建造中心 | C55: =SUM(E55:P55) -> 3076.7737 | D55: =SUM(Q55:AB55) -> 359.07599 | E55: ='[1]部门-汇总页'!E8 -> 14.519988 | F55: ='[1]部门-汇总页'!F8 -> 271.24978 | G55: ='[1]部门-汇总页'!G8 -> 36.3648 | H55: ='[1]部门-汇总页'!H8 -> 0 | I55: ='[1]部门-汇总页'!I8 -> 102.44442 | J55: ='[1]部门-汇总页'!J8 -> 361.10927 | K55: ='[1]部门-汇总页'!K8 -> 0 | L55: ='[1]部门-汇总页'!L8 -> 263.94436 | ... AB55: ='[1]部门-汇总页'!AB8 -> 0 | AD55: 6.6 | AE55: 176.00892 | AF55: 488.19698 | AG55: 0 | AH55: 0 | AI55: 0 | AJ55: 0 | AK55: 0 | AL55: 0 | AM55: 0 | AN55: 0 | AO55: 0 | AQ55: 14.519988 | AR55: 271.24978 | AS55: 497.72977 | AT55: 0 | AU55: 0 | AV55: 0 | AW55: 0 | AX55: 0 | AY55: 0 | AZ55: 0 | BA55: 0 | BB55: 0 | BD55: 14.519988 | BE55: 271.24978 | BF55: 36.3648 | BG55: 57.421872 | BH55: 10 | BI55: 553.06257 | BJ55: 0 | BK55: 0 | BL55: 0 | BM55: 0 | BN55: 0 | BO55: 76.731515
B56: 智能运管中心 | C56: =SUM(E56:P56) -> 2643.762 | D56: =SUM(Q56:AB56) -> 835.77223 | E56: ='[2]部门-汇总页'!E8 -> 20.229794 | F56: ='[2]部门-汇总页'!F8 -> 349.37001 | G56: ='[2]部门-汇总页'!G8 -> 331.2893 | H56: ='[2]部门-汇总页'!H8 -> 374.73451 | I56: ='[2]部门-汇总页'!I8 -> 416.79436 | J56: ='[2]部门-汇总页'!J8 -> 249.394 | K56: ='[2]部门-汇总页'!K8 -> 119.95272 | L56: ='[2]部门-汇总页'!L8 -> 0 | ... AB56: ='[2]部门-汇总页'!AB8 -> 0 | AD56: 46.899224 | AE56: 511.31316 | AF56: 582.31417 | AG56: 0 | AH56: 0 | AI56: 0 | AJ56: 0 | AK56: 0 | AL56: 0 | AM56: 0 | AN56: 0 | AO56: 0 | AQ56: 20.229794 | AR56: 349.37001 | AS56: 811.16986 | AT56: 0.29413 | AU56: 0 | AV56: 0 | AW56: 0 | AX56: 0 | AY56: 0 | AZ56: 0 | BA56: 0 | BB56: 0 | BD56: 20.229794 | BE56: 349.37001 | BF56: 354.77114 | BG56: 339.33335 | BH56: 389.9355 | BI56: 14.25 | BJ56: 0 | BK56: 0 | BL56: 0 | BM56: 0 | BN56: 0 | BO56: 0
B57: 数智管理中心 | C57: =SUM(E57:P57) -> 1165.844 | D57: =SUM(Q57:AB57) -> 369.28599 | E57: ='[3]部门-汇总页'!E8 -> 346.43598 | F57: ='[3]部门-汇总页'!F8 -> 217.85668 | G57: ='[3]部门-汇总页'!G8 -> 225.58484 | H57: ='[3]部门-汇总页'!H8 -> 121.46788 | I57: ='[3]部门-汇总页'!I8 -> 55.734354 | J57: ='[3]部门-汇总页'!J8 -> 118.21834 | K57: ='[3]部门-汇总页'!K8 -> 3.9 | L57: ='[3]部门-汇总页'!L8 -> 18.109091 | ... AB57: ='[3]部门-汇总页'!AB8 -> 0 | AD57: 323.16947 | AE57: 28.503342 | AF57: 228.33718 | AG57: 43.098638 | AH57: 9.245 | AI57: 51.398342 | AJ57: 19.395138 | AK57: 4.25 | AL57: 1.275 | AM57: 20.55 | AN57: 0 | AO57: 28.2525 | AQ57: 346.43598 | AR57: 217.85668 | AS57: 254.52422 | AT57: 75.771945 | AU57: 10.245 | AV57: 85.918342 | AW57: 21.759354 | AX57: 5.75 | AY57: 1.275 | AZ57: 21.3 | BA57: 0 | BB57: 28.2525 | BD57: 346.43598 | BE57: 217.85668 | BF57: 233.68484 | BG57: 129.87697 | BH57: 48.025 | BI57: 111.6277 | BJ57: 3.9 | BK57: 15.9 | BL57: 8.9843544 | BM57: 21.3 | BN57: 0 | BO57: 28.2525
B58: 福建分公司 | C58: =SUM(E58:P58) -> 1003.8496 | D58: =SUM(Q58:AB58) -> 95.63872 | E58: ='[4]部门-汇总页'!E8 -> 39.183996 | F58: ='[4]部门-汇总页'!F8 -> 58.970905 | G58: ='[4]部门-汇总页'!G8 -> 46.795 | H58: ='[4]部门-汇总页'!H8 -> 10.46 | I58: ='[4]部门-汇总页'!I8 -> 50.260352 | J58: ='[4]部门-汇总页'!J8 -> 78.544295 | K58: ='[4]部门-汇总页'!K8 -> 31.393235 | L58: ='[4]部门-汇总页'!L8 -> 12.602 | ... AB58: ='[4]部门-汇总页'!AB8 -> 0 | AD58: 39.183996 | AE58: 28.175905 | AF58: 72.41047 | AG58: 0 | AH58: 0 | AI58: 0 | AJ58: 0 | AK58: 0 | AL58: 0 | AM58: 0 | AN58: 0 | AO58: 0 | AQ58: 39.183996 | AR58: 58.970905 | AS58: 60.469076 | AT58: 0 | AU58: 0 | AV58: 0 | AW58: 0 | AX58: 0 | AY58: 0 | AZ58: 0 | BA58: 0 | BB58: 0 | BD58: 39.183996 | BE58: 58.970905 | BF58: 46.795 | BG58: 32.061628 | BH58: 38.912784 | BI58: 55.01564 | BJ58: 0 | BK58: 0 | BL58: 0 | BM58: 0 | BN58: 0 | BO58: 0
B59: 广东分公司 | C59: =SUM(E59:P59) -> 1695.7002 | D59: =SUM(Q59:AB59) -> 308.36011 | E59: ='[5]部门-汇总页'!E8 -> 249.25454 | F59: ='[5]部门-汇总页'!F8 -> 7.39306 | G59: ='[5]部门-汇总页'!G8 -> 7.8 | H59: ='[5]部门-汇总页'!H8 -> 6.64306 | I59: ='[5]部门-汇总页'!I8 -> 182.34091 | J59: ='[5]部门-汇总页'!J8 -> 297.24238 | K59: ='[5]部门-汇总页'!K8 -> 6 | L59: ='[5]部门-汇总页'!L8 -> 219.82889 | ... AB59: ='[5]部门-汇总页'!AB8 -> 0 | AD59: 252.61889 | AE59: 74.571401 | AF59: 194.44211 | AG59: 0 | AH59: 0 | AI59: 0 | AJ59: 0 | AK59: 0 | AL59: 0 | AM59: 0 | AN59: 0 | AO59: 0 | AQ59: 249.25454 | AR59: 7.39306 | AS59: 301.22571 | AT59: 0 | AU59: 0 | AV59: 0 | AW59: 0 | AX59: 0 | AY59: 0 | AZ59: 0 | BA59: 0 | BB59: 0 | BD59: 249.25454 | BE59: 7.39306 | BF59: 0.081132075 | BG59: 44.44306 | BH59: 196.28091 | BI59: 300.17478 | BJ59: 0 | BK59: 0 | BL59: 0 | BM59: 0 | BN59: 0 | BO59: 0
B60: 产品研发中心 | C60: =SUM(E60:P60) -> 0 | D60: =SUM(Q60:AB60) -> 10 | E60: ='[6]部门-汇总页'!E8 -> 0 | F60: ='[6]部门-汇总页'!F8 -> 0 | G60: ='[6]部门-汇总页'!G8 -> 0 | H60: ='[6]部门-汇总页'!H8 -> 0 | I60: ='[6]部门-汇总页'!I8 -> 0 | J60: ='[6]部门-汇总页'!J8 -> 0 | K60: ='[6]部门-汇总页'!K8 -> 0 | L60: ='[6]部门-汇总页'!L8 -> 0 | ... AB60: ='[6]部门-汇总页'!AB8 -> 0 | AD60: 0 | AE60: 0 | AF60: 0 | AG60: 0 | AH60: 0 | AI60: 0 | AJ60: 0 | AK60: 0 | AL60: 0 | AM60: 0 | AN60: 0 | AO60: 0 | AQ60: 0 | AR60: 0 | AS60: 0 | AT60: 0 | AU60: 0 | AV60: 0 | AW60: 0 | AX60: 0 | AY60: 0 | AZ60: 0 | BA60: 0 | BB60: 0 | BD60: 0 | BE60: 0 | BF60: 0 | BG60: 0 | BH60: 0 | BI60: 0 | BJ60: 0 | BK60: 0 | BL60: 0 | BM60: 0 | BN60: 0 | BO60: 0
B61: 市场经营拓展中心 | C61: =SUM(E61:P61) -> 0 | D61: =SUM(Q61:AB61) -> 0.70731289 | E61: ='[7]部门-汇总页'!E8 -> 0 | F61: ='[7]部门-汇总页'!F8 -> 0 | G61: ='[7]部门-汇总页'!G8 -> 0 | H61: ='[7]部门-汇总页'!H8 -> 0 | I61: ='[7]部门-汇总页'!I8 -> 0 | J61: ='[7]部门-汇总页'!J8 -> 0 | K61: ='[7]部门-汇总页'!K8 -> 0 | L61: ='[7]部门-汇总页'!L8 -> 0 | ... AB61: ='[7]部门-汇总页'!AB8 -> 0 | AD61: 0 | AE61: 0 | AF61: 0 | AG61: 0 | AH61: 0 | AI61: 0 | AJ61: 0 | AK61: 0 | AL61: 0 | AM61: 0 | AN61: 0 | AO61: 0 | AQ61: 0 | AR61: 0 | AS61: 0 | AT61: 0 | AU61: 0 | AV61: 0 | AW61: 0 | AX61: 0 | AY61: 0 | AZ61: 0 | BA61: 0 | BB61: 0 | BD61: 0 | BE61: 0 | BF61: 0 | BG61: 0 | BH61: 0 | BI61: 0 | BJ61: 0 | BK61: 0 | BL61: 0 | BM61: 0 | BN61: 0 | BO61: 0
B62: 合计 | C62: =SUM(C55:C61) -> 9585.9295 | D62: =SUM(D55:D61) -> 1978.8403 | E62: =SUM(E55:E61) -> 669.6243 | F62: =SUM(F55:F61) -> 904.84044 | G62: =SUM(G55:G61) -> 647.83395 | H62: =SUM(H55:H61) -> 513.30544 | I62: =SUM(I55:I61) -> 807.57439 | J62: =SUM(J55:J61) -> 1104.5083 | ... AB62: =SUM(AB55:AB61) -> 0 | AD62: 668.47158 | AE62: 818.57273 | AF62: 1565.7009 | AG62: 43.098638 | AH62: 9.245 | AI62: 51.398342 | AJ62: 19.395138 | AK62: 4.25 | AL62: 1.275 | AM62: 20.55 | AN62: 0 | AO62: 28.2525 | AQ62: 669.6243 | AR62: 904.84044 | AS62: 1925.1186 | AT62: 76.066075 | AU62: 10.245 | AV62: 85.918342 | AW62: 21.759354 | AX62: 5.75 | AY62: 1.275 | AZ62: 21.3 | BA62: 0 | BB62: 28.2525 | BD62: 669.6243 | BE62: 904.84044 | BF62: 671.69692 | BG62: 603.13688 | BH62: 683.15419 | BI62: 1034.1307 | BJ62: 3.9 | BK62: 15.9 | BL62: 8.9843544 | BM62: 21.3 | BN62: 0 | BO62: 104.98402
C64: 成本 | D64: 开支 | E64: 2026-01成本 | F64: 2026-02成本 | G64: 2026-03成本 | H64: 2026-04成本 | I64: 2026-05成本 | J64: 2026-06成本 | K64: 2026-07成本 | L64: 2026-08成本 | M64: 2026-09成本 | N64: 2026-10成本 | O64: 2026-11成本 | P64: 2026-12成本 | Q64: 2026-01开支 | R64: 2026-02开支 | S64: 2026-03开支 | T64: 2026-04开支 | U64: 2026-05开支 | V64: 2026-06开支 | W64: 2026-07开支 | X64: 2026-08开支 | Y64: 2026-09开支 | Z64: 2026-10开支 | AA64: 2026-11开支 | AB64: 2026-12开支 | AD64: 2026-01成本 | AE64: 2026-02成本 | AF64: 2026-03成本 | AG64: 2026-04成本 | AH64: 2026-05成本 | AI64: 2026-06成本 | AJ64: 2026-07成本 | AK64: 2026-08成本 | AL64: 2026-09成本 | AM64: 2026-10成本 | AN64: 2026-11成本 | AO64: 2026-12成本
B65: 数字建造中心 | C65: =SUM(E65:P65) -> 0 | D65: =SUM(Q65:AB65) -> 0
B66: 智能运管中心 | C66: =SUM(E66:P66) -> 0 | D66: =SUM(Q66:AB66) -> 0
B67: 数智管理中心 | C67: =SUM(E67:P67) -> 0 | D67: =SUM(Q67:AB67) -> 0
B68: 福建分公司 | C68: =SUM(E68:P68) -> 0 | D68: =SUM(Q68:AB68) -> 0
B69: 广东分公司 | C69: =SUM(E69:P69) -> 0 | D69: =SUM(Q69:AB69) -> 0
B70: 产品研发中心 | C70: =SUM(E70:P70) -> 0 | D70: =SUM(Q70:AB70) -> 0
B71: 市场经营拓展中心 | C71: =SUM(E71:P71) -> 0 | D71: =SUM(Q71:AB71) -> 0
B72: 合计 | C72: =SUM(C65:C71) -> 0 | D72: =SUM(D65:D71) -> 0 | E72: =SUM(E65:E71) -> 0 | F72: =SUM(F65:F71) -> 0 | G72: =SUM(G65:G71) -> 0 | H72: =SUM(H65:H71) -> 0 | I72: =SUM(I65:I71) -> 0 | J72: =SUM(J65:J71) -> 0 | ... AB72: =SUM(AB65:AB71) -> 0 | AD72: 0 | AE72: 0 | AF72: 0 | AG72: 0 | AH72: 0 | AI72: 0 | AJ72: 0 | AK72: 0 | AL72: 0 | AM72: 0 | AN72: 0 | AO72: 0
C74: 应收未收合同数 | D74: 应收未收金额 | E74: 2025年初 | F74: 2026-01应收未收合同数 | G74: 2026-02应收未收合同数 | H74: 2026-03应收未收合同数 | I74: 2026-04应收未收合同数 | J74: 2026-05应收未收合同数 | K74: 2026-06应收未收合同数 | L74: 2026-07应收未收合同数 | M74: 2026-08应收未收合同数 | N74: 2026-09应收未收合同数 | O74: 2026-10应收未收合同数 | P74: 2026-11应收未收合同数 | Q74: 2025年初 | R74: 2026-01应收未收金额 | S74: 2026-02应收未收金额 | T74: 2026-03应收未收金额 | U74: 2026-04应收未收金额 | V74: 2026-05应收未收金额 | W74: 2026-06应收未收金额 | X74: 2026-07应收未收金额 | Y74: 2026-08应收未收金额 | Z74: 2026-09应收未收金额 | AA74: 2026-10应收未收金额 | AB74: 2026-11应收未收金额
B75: 数字建造中心 | C75: {=INDEX($E75:$P75,1,COUNTA($E75:$P75))} -> 88 | D75: {=INDEX($Q75:$AB75,1,COUNTA($Q75:$AB75))} -> 9605.5147 | E75: 0 | F75: 88 | Q75: 0 | R75: 9605.5147
B76: 智能运管中心 | C76: {=INDEX($E76:$P76,1,COUNTA($E76:$P76))} -> 96 | D76: {=INDEX($Q76:$AB76,1,COUNTA($Q76:$AB76))} -> 5172.4446 | E76: 0 | F76: 96 | Q76: 0 | R76: 5172.4446
B77: 数智管理中心 | C77: {=INDEX($E77:$P77,1,COUNTA($E77:$P77))} -> 18 | D77: {=INDEX($Q77:$AB77,1,COUNTA($Q77:$AB77))} -> 636.53208 | E77: 0 | F77: 18 | Q77: 0 | R77: 636.53208
B78: 福建分公司 | C78: {=INDEX($E78:$P78,1,COUNTA($E78:$P78))} -> 25 | D78: {=INDEX($Q78:$AB78,1,COUNTA($Q78:$AB78))} -> 2002.0807 | E78: 0 | F78: 25 | Q78: 0 | R78: 2002.0807
B79: 广东分公司 | C79: {=INDEX($E79:$P79,1,COUNTA($E79:$P79))} -> 72 | D79: {=INDEX($Q79:$AB79,1,COUNTA($Q79:$AB79))} -> 3829.6505 | E79: 0 | F79: 72 | Q79: 0 | R79: 3829.6505
B80: 产品研发中心 | C80: {=INDEX($E80:$P80,1,COUNTA($E80:$P80))} -> 0 | D80: {=INDEX($Q80:$AB80,1,COUNTA($Q80:$AB80))} -> 0 | E80: 0 | F80: 0 | Q80: 0 | R80: 0
B81: 市场经营拓展中心 | C81: {=INDEX($E81:$P81,1,COUNTA($E81:$P81))} -> 5 | D81: {=INDEX($Q81:$AB81,1,COUNTA($Q81:$AB81))} -> 1166.0064 | E81: 0 | F81: 5 | Q81: 0 | R81: 1166.0064
B82: 合计 | C82: {=INDEX($E82:$P82,1,COUNTA($E82:$P82))} -> 304 | D82: {=INDEX($Q82:$AB82,1,COUNTA($Q82:$AB82))} -> 22412.229 | E82: 147 | F82: =SUM(F75:F81) -> 304 | Q82: 13479.199 | R82: =SUM(R75:R81) -> 22412.229
B83: 注意：CD列动态提取最新值，一定要等【会后】再固定本次会议相关数值

Sheet 产值及收款计划
B1: 2026年产值及收款计划 | U1: =SUMIF(U5:U1053,"<>#N/A") -> #NAME? | V1: =SUMIF(V5:V1053,"<>#N/A") -> #NAME? | AA1: =SUMIF(AA5:AA1053,"<>#N/A") -> #NAME? | AB1: =SUMIF(AB5:AB1053,"<>#N/A") -> #NAME? | AC1: =SUMIF(AC5:AC1053,"<>#N/A") -> #NAME? | AD1: =SUMIF(AD5:AD1053,"<>#N/A") -> #NAME? | AE1: =SUMIF(AE5:AE1053,"<>#N/A") -> #NAME? | AF1: =SUMIF(AF5:AF1053,"<>#N/A") -> #NAME? | AG1: =SUMIF(AG5:AG1053,"<>#N/A") -> #NAME? | AH1: =SUMIF(AH5:AH1053,"<>#N/A") -> #NAME? | ... AO1: =SUMIF(AO5:AO1053,"<>#N/A") -> #NAME? | AX1: =SUMIF(AX5:AX1053,"<>#N/A") -> #NAME? | AY1: =SUMIF(AY5:AY1053,"<>#N/A") -> #NAME? | AZ1: =SUMIF(AZ5:AZ1053,"<>#N/A") -> #NAME? | BA1: =SUMIF(BA5:BA1053,"<>#N/A") -> #NAME? | BB1: =SUMIF(BB5:BB1053,"<>#N/A") -> #NAME? | BC1: =SUMIF(BC5:BC1053,"<>#N/A") -> #NAME? | BD1: =SUMIF(BD5:BD1053,"<>#N/A") -> #NAME? | BE1: =SUMIF(BE5:BE1053,"<>#N/A") -> #NAME? | ... BL1: =SUMIF(BL5:BL1053,"<>#N/A") -> #NAME? | CA1: =SUMIF(CA5:CA1053,"<>#N/A") -> #NAME? | CB1: =SUMIF(CB5:CB1053,"<>#N/A") -> #NAME? | CC1: =SUMIF(CC5:CC1053,"<>#N/A") -> #NAME? | CD1: =SUMIF(CD5:CD1053,"<>#N/A") -> #NAME? | CE1: =SUMIF(CE5:CE1053,"<>#N/A") -> #NAME? | CF1: =SUMIF(CF5:CF1053,"<>#N/A") -> #NAME? | CG1: =SUMIF(CG5:CG1053,"<>#N/A") -> #NAME? | CH1: =SUMIF(CH5:CH1053,"<>#N/A") -> #NAME? | ... CL1: =SUMIF(CL5:CL1053,"<>#N/A") -> #NAME? | DA1: =SUMIF(DA5:DA1053,"<>#N/A") -> #NAME? | DB1: =SUMIF(DB5:DB1053,"<>#N/A") -> #NAME? | DC1: =SUMIF(DC5:DC1053,"<>#N/A") -> #NAME? | DD1: =SUMIF(DD5:DD1053,"<>#N/A") -> #NAME? | DE1: =SUMIF(DE5:DE1053,"<>#N/A") -> #NAME? | DF1: =SUMIF(DF5:DF1053,"<>#N/A") -> #NAME? | DG1: =SUMIF(DG5:DG1053,"<>#N/A") -> #NAME? | DH1: =SUMIF(DH5:DH1053,"<>#N/A") -> #NAME? | ... DL1: =SUMIF(DL5:DL1053,"<>#N/A") -> #NAME?
U2: =SUBTOTAL(9,U5:U1055) -> #NAME? | V2: =SUBTOTAL(9,V5:V1055) -> #NAME? | AA2: =SUBTOTAL(9,AA5:AA1055) -> #NAME? | AB2: =SUBTOTAL(9,AB5:AB1055) -> #NAME? | AC2: =_xlfn.AGGREGATE(9,6,AC5:AC1053) -> 570.2273 | AD2: =_xlfn.AGGREGATE(9,6,AD5:AD1053) -> 1116.3342 | AE2: =_xlfn.AGGREGATE(9,6,AE5:AE1053) -> 826.80828 | AF2: =_xlfn.AGGREGATE(9,6,AF5:AF1053) -> 2827.9681 | AG2: =_xlfn.AGGREGATE(9,6,AG5:AG1053) -> 194.9125 | AH2: =_xlfn.AGGREGATE(9,6,AH5:AH1053) -> 775.6595 | AI2: =_xlfn.AGGREGATE(9,6,AI5:AI1053) -> 2200.2945 | AJ2: =_xlfn.AGGREGATE(9,6,AJ5:AJ1053) -> 199.6515 | ... AO2: =_xlfn.AGGREGATE(9,6,AO5:AO1053) -> 13985.693 | AX2: =SUBTOTAL(9,AX5:AX1055) -> #NAME? | AY2: =SUBTOTAL(9,AY5:AY1055) -> #NAME? | AZ2: =SUBTOTAL(9,AZ5:AZ1055) -> #NAME? | BA2: =SUBTOTAL(9,BA5:BA1055) -> #NAME? | BB2: =SUBTOTAL(9,BB5:BB1055) -> #NAME? | BC2: =_xlfn.AGGREGATE(9,6,BC5:BC1053) -> 1690.6698 | BD2: =_xlfn.AGGREGATE(9,6,BD5:BD1053) -> 1085.3586 | BE2: =_xlfn.AGGREGATE(9,6,BE5:BE1053) -> 1565.2728 | BF2: =_xlfn.AGGREGATE(9,6,BF5:BF1053) -> 2267.146 | BG2: =_xlfn.AGGREGATE(9,6,BG5:BG1053) -> 444.86272 | BH2: =_xlfn.AGGREGATE(9,6,BH5:BH1053) -> 1053.2641 | BI2: =_xlfn.AGGREGATE(9,6,BI5:BI1053) -> 1739.9967 | BJ2: =_xlfn.AGGREGATE(9,6,BJ5:BJ1053) -> 727.121 | ... BL2: =_xlfn.AGGREGATE(9,6,BL5:BL1053) -> 4023.3894 | CA2: =_xlfn.AGGREGATE(9,6,CA5:CA1053) -> 181.14625 | CB2: =_xlfn.AGGREGATE(9,6,CB5:CB1053) -> 278.342 | CC2: =_xlfn.AGGREGATE(9,6,CC5:CC1053) -> 114.56 | CD2: =_xlfn.AGGREGATE(9,6,CD5:CD1053) -> 129.11679 | CE2: =_xlfn.AGGREGATE(9,6,CE5:CE1053) -> 144.7017 | CF2: =_xlfn.AGGREGATE(9,6,CF5:CF1053) -> 0 | CG2: =_xlfn.AGGREGATE(9,6,CG5:CG1053) -> 0 | CH2: =_xlfn.AGGREGATE(9,6,CH5:CH1053) -> 0 | ... CL2: =_xlfn.AGGREGATE(9,6,CL5:CL1053) -> 0 | DA2: =_xlfn.AGGREGATE(9,6,DA5:DA1053) -> 650.99247 | DB2: =_xlfn.AGGREGATE(9,6,DB5:DB1053) -> 3030.1978 | DC2: =_xlfn.AGGREGATE(9,6,DC5:DC1053) -> 413.65686 | DD2: =_xlfn.AGGREGATE(9,6,DD5:DD1053) -> 1444.2297 | DE2: =_xlfn.AGGREGATE(9,6,DE5:DE1053) -> 458.22778 | DF2: =_xlfn.AGGREGATE(9,6,DF5:DF1053) -> 0 | DG2: =_xlfn.AGGREGATE(9,6,DG5:DG1053) -> 0 | DH2: =_xlfn.AGGREGATE(9,6,DH5:DH1053) -> 0 | ... DL2: =_xlfn.AGGREGATE(9,6,DL5:DL1053) -> 0
M3: 非主导不需填写 | P3: 已完结合同只填收款计划
A4: 序号 | B4: 部门 | C4: 合同编号 | D4: 合同名称 | E4: 合同金额 | F4: 部门合同额/总产值 | G4: 部门-有效产值 | H4: 部门-自营产值 | I4: 部门-自营率 | J4: 综合税率 | K4: 备用列 | L4: 备用列 | M4: 是否生产主导 | N4: 团队 | O4: 项目经理 | P4: 合同类型 | Q4: 备用列 | R4: 备用列 | S4: 备用列 | T4: 历年已确认产值（未拆分） | U4: 2026已确认产值（未拆分） | V4: 剩余产值 | W4: 备用列 | X4: 备用列 | Y4: 备用列 | Z4: 备用列 | AA4: 2026-01产值计划 | AB4: 2026-02产值计划 | AC4: 2026-03产值计划 | AD4: 2026-04产值计划 | AE4: 2026-05产值计划 | AF4: 2026-06产值计划 | AG4: 2026-07产值计划 | AH4: 2026-08产值计划 | AI4: 2026-09产值计划 | AJ4: 2026-10产值计划 | AK4: 2026-11产值计划 | AL4: 2026-12产值计划 | AM4: 重要辅助列，计算top10-计划 | AN4: 重要辅助列，计算top10-实际 | AO4: 成本分摊表Q1辅助列 | AS4: 备用列 | AT4: 备用列 | AU4: 备用列 | AV4: 备用列 | AW4: 历年已收款（未拆分） | AX4: 2026已收款（未拆分） | AY4: 剩余收款（按合同额） | AZ4: 剩余收款（按已确认产值） | BA4: 2026-01收款计划 | BB4: 2026-02收款计划 | BC4: 2026-03收款计划 | BD4: 2026-04收款计划 | BE4: 2026-05收款计划 | BF4: 2026-06收款计划 | BG4: 2026-07收款计划 | BH4: 2026-08收款计划 | BI4: 2026-09收款计划 | BJ4: 2026-10收款计划 | BK4: 2026-11收款计划 | BL4: 2026-12收款计划 | BQ4: 合同甲方 | BR4: 情况说明 | BT4: 春节前落实且已上报一季度计划 | BU4: 春节后一季度内落实且已上报一季度计划 | BV4: 一季度内无法落实 | BW4: 总计 | CA4: 2026-01实际产值 | CB4: 2026-02实际产值 | CC4: 2026-03实际产值 | CD4: 2026-04实际产值 | CE4: 2026-05实际产值 | CF4: 2026-06实际产值 | CG4: 2026-07实际产值 | CH4: 2026-08实际产值 | CI4: 2026-09实际产值 | CJ4: 2026-10实际产值 | CK4: 2026-11实际产值 | CL4: 2026-12实际产值 | DA4: 2026-01实际收款 | DB4: 2026-02实际收款 | DC4: 2026-03实际收款 | DD4: 2026-04实际收款 | DE4: 2026-05实际收款 | DF4: 2026-06实际收款 | DG4: 2026-07实际收款 | DH4: 2026-08实际收款 | DI4: 2026-09实际收款 | DJ4: 2026-10实际收款 | DK4: 2026-11实际收款 | DL4: 2026-12实际收款
A5: 1 | B5: 数字建造中心 | C5: {=_xlfn.XLOOKUP($A5&$B5,'[1]产值及收款计划（2026）'!$A:$A&'[1]产值及收款计划（2026）'!$B:$B,'[1]产值及收款计划（2026）'!C:C)} -> #NAME? | D5: {=_xlfn.XLOOKUP($A5&$B5,'[1]产值及收款计划（2026）'!$A:$A&'[1]产值及收款计划（2026）'!$B:$B,'[1]产值及收款计划（2026）'!D:D)} -> #NAME? | E5: {=_xlfn.XLOOKUP($A5&$B5,'[1]产值及收款计划（2026）'!$A:$A&'[1]产值及收款计划（2026）'!$B:$B,'[1]产值及收款计划（2026）'!E:E)} -> #NAME? | F5: {=_xlfn.XLOOKUP($A5&$B5,'[1]产值及收款计划（2026）'!$A:$A&'[1]产值及收款计划（2026）'!$B:$B,'[1]产值及收款计划（2026）'!F:F)} -> #NAME? | G5: {=_xlfn.XLOOKUP($A5&$B5,'[1]产值及收款计划（2026）'!$A:$A&'[1]产值及收款计划（2026）'!$B:$B,'[1]产值及收款计划（2026）'!G:G)} -> #NAME? | H5: {=_xlfn.XLOOKUP($A5&$B5,'[1]产值及收款计划（2026）'!$A:$A&'[1]产值及收款计划（2026）'!$B:$B,'[1]产值及收款计划（2026）'!H:H)} -> #NAME? | I5: {=_xlfn.XLOOKUP($A5&$B5,'[1]产值及收款计划（2026）'!$A:$A&'[1]产值及收款计划（2026）'!$B:$B,'[1]产值及收款计划（2026）'!I:I)} -> #NAME? | J5: {=_xlfn.XLOOKUP($A5&$B5,'[1]产值及收款计划（2026）'!$A:$A&'[1]产值及收款计划（2026）'!$B:$B,'[1]产值及收款计划（2026）'!J:J)} -> #NAME? | K5: {=_xlfn.XLOOKUP($A5&$B5,'[1]产值及收款计划（2026）'!$A:$A&'[1]产值及收款计划（2026）'!$B:$B,'[1]产值及收款计划（2026）'!K:K)} -> #NAME? | L5: {=_xlfn.XLOOKUP($A5&$B5,'[1]产值及收款计划（2026）'!$A:$A&'[1]产值及收款计划（2026）'!$B:$B,'[1]产值及收款计划（2026）'!L:L)} -> #NAME? | M5: {=_xlfn.XLOOKUP($A5&$B5,'[1]产值及收款计划（2026）'!$A:$A&'[1]产值及收款计划（2026）'!$B:$B,'[1]产值及收款计划（2026）'!M:M)} -> #NAME? | N5: {=_xlfn.XLOOKUP($A5&$B5,'[1]产值及收款计划（2026）'!$A:$A&'[1]产值及收款计划（2026）'!$B:$B,'[1]产值及收款计划（2026）'!N:N)} -> #NAME? | O5: {=_xlfn.XLOOKUP($A5&$B5,'[1]产值及收款计划（2026）'!$A:$A&'[1]产值及收款计划（2026）'!$B:$B,'[1]产值及收款计划（2026）'!O:O)} -> #NAME? | P5: {=_xlfn.XLOOKUP($A5&$B5,'[1]产值及收款计划（2026）'!$A:$A&'[1]产值及收款计划（2026）'!$B:$B,'[1]产值及收款计划（2026）'!P:P)} -> #NAME? | Q5: {=_xlfn.XLOOKUP($A5&$B5,'[1]产值及收款计划（2026）'!$A:$A&'[1]产值及收款计划（2026）'!$B:$B,'[1]产值及收款计划（2026）'!Q:Q)} -> #NAME? | R5: {=_xlfn.XLOOKUP($A5&$B5,'[1]产值及收款计划（2026）'!$A:$A&'[1]产值及收款计划（2026）'!$B:$B,'[1]产值及收款计划（2026）'!R:R)} -> #NAME? | S5: {=_xlfn.XLOOKUP($A5&$B5,'[1]产值及收款计划（2026）'!$A:$A&'[1]产值及收款计划（2026）'!$B:$B,'[1]产值及收款计划（2026）'!S:S)} -> #NAME? | T5: {=_xlfn.XLOOKUP($A5&$B5,'[1]产值及收款计划（2026）'!$A:$A&'[1]产值及收款计划（2026）'!$B:$B,'[1]产值及收款计划（2026）'!T:T)} -> #NAME? | U5: {=_xlfn.XLOOKUP($A5&$B5,'[1]产值及收款计划（2026）'!$A:$A&'[1]产值及收款计划（2026）'!$B:$B,'[1]产值及收款计划（2026）'!U:U)} -> #NAME? | V5: {=_xlfn.XLOOKUP($A5&$B5,'[1]产值及收款计划（2026）'!$A:$A&'[1]产值及收款计划（2026）'!$B:$B,'[1]产值及收款计划（2026）'!V:V)} -> #NAME? | W5: {=_xlfn.XLOOKUP($A5&$B5,'[1]产值及收款计划（2026）'!$A:$A&'[1]产值及收款计划（2026）'!$B:$B,'[1]产值及收款计划（2026）'!W:W)} -> #NAME? | X5: {=_xlfn.XLOOKUP($A5&$B5,'[1]产值及收款计划（2026）'!$A:$A&'[1]产值及收款计划（2026）'!$B:$B,'[1]产值及收款计划（2026）'!X:X)} -> #NAME? | Y5: {=_xlfn.XLOOKUP($A5&$B5,'[1]产值及收款计划（2026）'!$A:$A&'[1]产值及收款计划（2026）'!$B:$B,'[1]产值及收款计划（2026）'!Y:Y)} -> #NAME? | Z5: {=_xlfn.XLOOKUP($A5&$B5,'[1]产值及收款计划（2026）'!$A:$A&'[1]产值及收款计划（2026）'!$B:$B,'[1]产值及收款计划（2026）'!Z:Z)} -> #NAME? | AA5: {=_xlfn.XLOOKUP($A5&$B5,'[1]产值及收款计划（2026）'!$A:$A&'[1]产值及收款计划（2026）'!$B:$B,'[1]产值及收款计划（2026）'!AA:AA)} -> #NAME? | AB5: {=_xlfn.XLOOKUP($A5&$B5,'[1]产值及收款计划（2026）'!$A:$A&'[1]产值及收款计划（2026）'!$B:$B,'[1]产值及收款计划（2026）'!AB:AB)} -> #NAME? | AC5: {=_xlfn.XLOOKUP($A5&$B5,'[1]产值及收款计划（2026）'!$A:$A&'[1]产值及收款计划（2026）'!$B:$B,'[1]产值及收款计划（2026）'!AC:AC)} -> #NAME? | AD5: {=_xlfn.XLOOKUP($A5&$B5,'[1]产值及收款计划（2026）'!$A:$A&'[1]产值及收款计划（2026）'!$B:$B,'[1]产值及收款计划（2026）'!AD:AD)} -> #NAME? | AE5: {=_xlfn.XLOOKUP($A5&$B5,'[1]产值及收款计划（2026）'!$A:$A&'[1]产值及收款计划（2026）'!$B:$B,'[1]产值及收款计划（2026）'!AE:AE)} -> #NAME? | AF5: {=_xlfn.XLOOKUP($A5&$B5,'[1]产值及收款计划（2026）'!$A:$A&'[1]产值及收款计划（2026）'!$B:$B,'[1]产值及收款计划（2026）'!AF:AF)} -> #NAME? | AG5: {=_xlfn.XLOOKUP($A5&$B5,'[1]产值及收款计划（2026）'!$A:$A&'[1]产值及收款计划（2026）'!$B:$B,'[1]产值及收款计划（2026）'!AG:AG)} -> #NAME? | AH5: {=_xlfn.XLOOKUP($A5&$B5,'[1]产值及收款计划（2026）'!$A:$A&'[1]产值及收款计划（2026）'!$B:$B,'[1]产值及收款计划（2026）'!AH:AH)} -> #NAME? | AI5: {=_xlfn.XLOOKUP($A5&$B5,'[1]产值及收款计划（2026）'!$A:$A&'[1]产值及收款计划（2026）'!$B:$B,'[1]产值及收款计划（2026）'!AI:AI)} -> #NAME? | AJ5: {=_xlfn.XLOOKUP($A5&$B5,'[1]产值及收款计划（2026）'!$A:$A&'[1]产值及收款计划（2026）'!$B:$B,'[1]产值及收款计划（2026）'!AJ:AJ)} -> #NAME? | AK5: {=_xlfn.XLOOKUP($A5&$B5,'[1]产值及收款计划（2026）'!$A:$A&'[1]产值及收款计划（2026）'!$B:$B,'[1]产值及收款计划（2026）'!AK:AK)} -> #NAME? | AL5: {=_xlfn.XLOOKUP($A5&$B5,'[1]产值及收款计划（2026）'!$A:$A&'[1]产值及收款计划（2026）'!$B:$B,'[1]产值及收款计划（2026）'!AL:AL)} -> #NAME? | AM5: {=_xlfn.LET(_xlpm.勾选月份状态数组,TRANSPOSE('PPT(12-15页）-TOP10'!$A$3:$A$14),_xlpm.选择数据区,IF('PPT(12-15页）-TOP10'!$E$3="收款",$BA5:$BL5,$AA5:$AL5),SUM(_xlfn._xlws.FILTER(_xlpm.选择数据区,_xlpm.勾选月份状态数组,"")))} -> #NAME? | AN5: {=_xlfn.LET(_xlpm.勾选月份状态数组,TRANSPOSE('PPT(12-15页）-TOP10'!$A$3:$A$14),_xlpm.选择数据区,IF('PPT(12-15页）-TOP10'!$E$3="收款",$DA5:$DL5,$CA5:$CL5),SUM(_xlfn._xlws.FILTER(_xlpm.选择数据区,_xlpm.勾选月份状态数组,"")))} -> #NAME? | AO5: =SUM(CA5:CC5)+SUM(AD5:AL5) -> #NAME? | AS5: {=_xlfn.XLOOKUP($A5&$B5,'[1]产值及收款计划（2026）'!$A:$A&'[1]产值及收款计划（2026）'!$B:$B,'[1]产值及收款计划（2026）'!AS:AS)} -> #NAME? | AT5: {=_xlfn.XLOOKUP($A5&$B5,'[1]产值及收款计划（2026）'!$A:$A&'[1]产值及收款计划（2026）'!$B:$B,'[1]产值及收款计划（2026）'!AT:AT)} -> #NAME? | AU5: {=_xlfn.XLOOKUP($A5&$B5,'[1]产值及收款计划（2026）'!$A:$A&'[1]产值及收款计划（2026）'!$B:$B,'[1]产值及收款计划（2026）'!AU:AU)} -> #NAME? | AV5: {=_xlfn.XLOOKUP($A5&$B5,'[1]产值及收款计划（2026）'!$A:$A&'[1]产值及收款计划（2026）'!$B:$B,'[1]产值及收款计划（2026）'!AV:AV)} -> #NAME? | AW5: {=_xlfn.XLOOKUP($A5&$B5,'[1]产值及收款计划（2026）'!$A:$A&'[1]产值及收款计划（2026）'!$B:$B,'[1]产值及收款计划（2026）'!AW:AW)} -> #NAME? | AX5: {=_xlfn.XLOOKUP($A5&$B5,'[1]产值及收款计划（2026）'!$A:$A&'[1]产值及收款计划（2026）'!$B:$B,'[1]产值及收款计划（2026）'!AX:AX)} -> #NAME? | AY5: {=_xlfn.XLOOKUP($A5&$B5,'[1]产值及收款计划（2026）'!$A:$A&'[1]产值及收款计划（2026）'!$B:$B,'[1]产值及收款计划（2026）'!AY:AY)} -> #NAME? | AZ5: {=_xlfn.XLOOKUP($A5&$B5,'[1]产值及收款计划（2026）'!$A:$A&'[1]产值及收款计划（2026）'!$B:$B,'[1]产值及收款计划（2026）'!AZ:AZ)} -> #NAME? | BA5: {=_xlfn.XLOOKUP($A5&$B5,'[1]产值及收款计划（2026）'!$A:$A&'[1]产值及收款计划（2026）'!$B:$B,'[1]产值及收款计划（2026）'!BA:BA)} -> #NAME? | BB5: {=_xlfn.XLOOKUP($A5&$B5,'[1]产值及收款计划（2026）'!$A:$A&'[1]产值及收款计划（2026）'!$B:$B,'[1]产值及收款计划（2026）'!BB:BB)} -> #NAME? | BC5: {=_xlfn.XLOOKUP($A5&$B5,'[1]产值及收款计划（2026）'!$A:$A&'[1]产值及收款计划（2026）'!$B:$B,'[1]产值及收款计划（2026）'!BC:BC)} -> #NAME? | BD5: {=_xlfn.XLOOKUP($A5&$B5,'[1]产值及收款计划（2026）'!$A:$A&'[1]产值及收款计划（2026）'!$B:$B,'[1]产值及收款计划（2026）'!BD:BD)} -> #NAME? | BE5: {=_xlfn.XLOOKUP($A5&$B5,'[1]产值及收款计划（2026）'!$A:$A&'[1]产值及收款计划（2026）'!$B:$B,'[1]产值及收款计划（2026）'!BE:BE)} -> #NAME? | BF5: {=_xlfn.XLOOKUP($A5&$B5,'[1]产值及收款计划（2026）'!$A:$A&'[1]产值及收款计划（2026）'!$B:$B,'[1]产值及收款计划（2026）'!BF:BF)} -> #NAME? | BG5: {=_xlfn.XLOOKUP($A5&$B5,'[1]产值及收款计划（2026）'!$A:$A&'[1]产值及收款计划（2026）'!$B:$B,'[1]产值及收款计划（2026）'!BG:BG)} -> #NAME? | BH5: {=_xlfn.XLOOKUP($A5&$B5,'[1]产值及收款计划（2026）'!$A:$A&'[1]产值及收款计划（2026）'!$B:$B,'[1]产值及收款计划（2026）'!BH:BH)} -> #NAME? | BI5: {=_xlfn.XLOOKUP($A5&$B5,'[1]产值及收款计划（2026）'!$A:$A&'[1]产值及收款计划（2026）'!$B:$B,'[1]产值及收款计划（2026）'!BI:BI)} -> #NAME? | BJ5: {=_xlfn.XLOOKUP($A5&$B5,'[1]产值及收款计划（2026）'!$A:$A&'[1]产值及收款计划（2026）'!$B:$B,'[1]产值及收款计划（2026）'!BJ:BJ)} -> #NAME? | BK5: {=_xlfn.XLOOKUP($A5&$B5,'[1]产值及收款计划（2026）'!$A:$A&'[1]产值及收款计划（2026）'!$B:$B,'[1]产值及收款计划（2026）'!BK:BK)} -> #NAME? | BL5: {=_xlfn.XLOOKUP($A5&$B5,'[1]产值及收款计划（2026）'!$A:$A&'[1]产值及收款计划（2026）'!$B:$B,'[1]产值及收款计划（2026）'!BL:BL)} -> #NAME? | BQ5: {=_xlfn.XLOOKUP($A5&$B5,'[1]产值及收款计划（2026）'!$A:$A&'[1]产值及收款计划（2026）'!$B:$B,'[1]产值及收款计划（2026）'!BQ:BQ)} -> #NAME? | BR5: {=_xlfn.XLOOKUP($A5&$B5,'[1]产值及收款计划（2026）'!$A:$A&'[1]产值及收款计划（2026）'!$B:$B,'[1]产值及收款计划（2026）'!BR:BR)} -> #NAME? | BS5: 数字建造中心 | BT5: =SUMIFS($AP:$AP,$B:$B,$BS5,$AO:$AO,BT$4) -> 0 | BU5: =SUMIFS($AP:$AP,$B:$B,$BS5,$AO:$AO,BU$4) -> 0 | BV5: =SUMIFS($AP:$AP,$B:$B,$BS5,$AO:$AO,BV$4) -> 0 | BW5: =SUM(BT5:BV5) -> 0 | CA5: {=_xlfn.XLOOKUP($A5&$B5,'[1]产值及收款计划（2026）'!$A:$A&'[1]产值及收款计划（2026）'!$B:$B,'[1]产值及收款计划（2026）'!CA:CA)} -> #NAME? | CB5: {=_xlfn.XLOOKUP($A5&$B5,'[1]产值及收款计划（2026）'!$A:$A&'[1]产值及收款计划（2026）'!$B:$B,'[1]产值及收款计划（2026）'!CB:CB)} -> #NAME? | CC5: {=_xlfn.XLOOKUP($A5&$B5,'[1]产值及收款计划（2026）'!$A:$A&'[1]产值及收款计划（2026）'!$B:$B,'[1]产值及收款计划（2026）'!CC:CC)} -> #NAME? | CD5: {=_xlfn.XLOOKUP($A5&$B5,'[1]产值及收款计划（2026）'!$A:$A&'[1]产值及收款计划（2026）'!$B:$B,'[1]产值及收款计划（2026）'!CD:CD)} -> #NAME? | CE5: {=_xlfn.XLOOKUP($A5&$B5,'[1]产值及收款计划（2026）'!$A:$A&'[1]产值及收款计划（2026）'!$B:$B,'[1]产值及收款计划（2026）'!CE:CE)} -> #NAME? | CF5: {=_xlfn.XLOOKUP($A5&$B5,'[1]产值及收款计划（2026）'!$A:$A&'[1]产值及收款计划（2026）'!$B:$B,'[1]产值及收款计划（2026）'!CF:CF)} -> #NAME? | CG5: {=_xlfn.XLOOKUP($A5&$B5,'[1]产值及收款计划（2026）'!$A:$A&'[1]产值及收款计划（2026）'!$B:$B,'[1]产值及收款计划（2026）'!CG:CG)} -> #NAME? | CH5: {=_xlfn.XLOOKUP($A5&$B5,'[1]产值及收款计划（2026）'!$A:$A&'[1]产值及收款计划（2026）'!$B:$B,'[1]产值及收款计划（2026）'!CH:CH)} -> #NAME? | CI5: {=_xlfn.XLOOKUP($A5&$B5,'[1]产值及收款计划（2026）'!$A:$A&'[1]产值及收款计划（2026）'!$B:$B,'[1]产值及收款计划（2026）'!CI:CI)} -> #NAME? | CJ5: {=_xlfn.XLOOKUP($A5&$B5,'[1]产值及收款计划（2026）'!$A:$A&'[1]产值及收款计划（2026）'!$B:$B,'[1]产值及收款计划（2026）'!CJ:CJ)} -> #NAME? | CK5: {=_xlfn.XLOOKUP($A5&$B5,'[1]产值及收款计划（2026）'!$A:$A&'[1]产值及收款计划（2026）'!$B:$B,'[1]产值及收款计划（2026）'!CK:CK)} -> #NAME? | CL5: {=_xlfn.XLOOKUP($A5&$B5,'[1]产值及收款计划（2026）'!$A:$A&'[1]产值及收款计划（2026）'!$B:$B,'[1]产值及收款计划（2026）'!CL:CL)} -> #NAME? | DA5: {=_xlfn.XLOOKUP($A5&$B5,'[1]产值及收款计划（2026）'!$A:$A&'[1]产值及收款计划（2026）'!$B:$B,'[1]产值及收款计划（2026）'!DA:DA)} -> #NAME? | DB5: {=_xlfn.XLOOKUP($A5&$B5,'[1]产值及收款计划（2026）'!$A:$A&'[1]产值及收款计划（2026）'!$B:$B,'[1]产值及收款计划（2026）'!DB:DB)} -> #NAME? | DC5: {=_xlfn.XLOOKUP($A5&$B5,'[1]产值及收款计划（2026）'!$A:$A&'[1]产值及收款计划（2026）'!$B:$B,'[1]产值及收款计划（2026）'!DC:DC)} -> #NAME? | DD5: {=_xlfn.XLOOKUP($A5&$B5,'[1]产值及收款计划（2026）'!$A:$A&'[1]产值及收款计划（2026）'!$B:$B,'[1]产值及收款计划（2026）'!DD:DD)} -> #NAME? | DE5: {=_xlfn.XLOOKUP($A5&$B5,'[1]产值及收款计划（2026）'!$A:$A&'[1]产值及收款计划（2026）'!$B:$B,'[1]产值及收款计划（2026）'!DE:DE)} -> #NAME? | DF5: {=_xlfn.XLOOKUP($A5&$B5,'[1]产值及收款计划（2026）'!$A:$A&'[1]产值及收款计划（2026）'!$B:$B,'[1]产值及收款计划（2026）'!DF:DF)} -> #NAME? | DG5: {=_xlfn.XLOOKUP($A5&$B5,'[1]产值及收款计划（2026）'!$A:$A&'[1]产值及收款计划（2026）'!$B:$B,'[1]产值及收款计划（2026）'!DG:DG)} -> #NAME? | DH5: {=_xlfn.XLOOKUP($A5&$B5,'[1]产值及收款计划（2026）'!$A:$A&'[1]产值及收款计划（2026）'!$B:$B,'[1]产值及收款计划（2026）'!DH:DH)} -> #NAME? | DI5: {=_xlfn.XLOOKUP($A5&$B5,'[1]产值及收款计划（2026）'!$A:$A&'[1]产值及收款计划（2026）'!$B:$B,'[1]产值及收款计划（2026）'!DI:DI)} -> #NAME? | DJ5: {=_xlfn.XLOOKUP($A5&$B5,'[1]产值及收款计划（2026）'!$A:$A&'[1]产值及收款计划（2026）'!$B:$B,'[1]产值及收款计划（2026）'!DJ:DJ)} -> #NAME? | DK5: {=_xlfn.XLOOKUP($A5&$B5,'[1]产值及收款计划（2026）'!$A:$A&'[1]产值及收款计划（2026）'!$B:$B,'[1]产值及收款计划（2026）'!DK:DK)} -> #NAME? | DL5: {=_xlfn.XLOOKUP($A5&$B5,'[1]产值及收款计划（2026）'!$A:$A&'[1]产值及收款计划（2026）'!$B:$B,'[1]产值及收款计划（2026）'!DL:DL)} -> #NAME?
A6: =A5+1 -> 2 | B6: 数字建造中心 | C6: {=_xlfn.XLOOKUP($A6&$B6,'[1]产值及收款计划（2026）'!$A:$A&'[1]产值及收款计划（2026）'!$B:$B,'[1]产值及收款计划（2026）'!C:C)} -> #NAME? | D6: {=_xlfn.XLOOKUP($A6&$B6,'[1]产值及收款计划（2026）'!$A:$A&'[1]产值及收款计划（2026）'!$B:$B,'[1]产值及收款计划（2026）'!D:D)} -> #NAME? | E6: {=_xlfn.XLOOKUP($A6&$B6,'[1]产值及收款计划（2026）'!$A:$A&'[1]产值及收款计划（2026）'!$B:$B,'[1]产值及收款计划（2026）'!E:E)} -> #NAME? | F6: {=_xlfn.XLOOKUP($A6&$B6,'[1]产值及收款计划（2026）'!$A:$A&'[1]产值及收款计划（2026）'!$B:$B,'[1]产值及收款计划（2026）'!F:F)} -> #NAME? | G6: {=_xlfn.XLOOKUP($A6&$B6,'[1]产值及收款计划（2026）'!$A:$A&'[1]产值及收款计划（2026）'!$B:$B,'[1]产值及收款计划（2026）'!G:G)} -> #NAME? | H6: {=_xlfn.XLOOKUP($A6&$B6,'[1]产值及收款计划（2026）'!$A:$A&'[1]产值及收款计划（2026）'!$B:$B,'[1]产值及收款计划（2026）'!H:H)} -> #NAME? | I6: {=_xlfn.XLOOKUP($A6&$B6,'[1]产值及收款计划（2026）'!$A:$A&'[1]产值及收款计划（2026）'!$B:$B,'[1]产值及收款计划（2026）'!I:I)} -> #NAME? | J6: {=_xlfn.XLOOKUP($A6&$B6,'[1]产值及收款计划（2026）'!$A:$A&'[1]产值及收款计划（2026）'!$B:$B,'[1]产值及收款计划（2026）'!J:J)} -> #NAME? | K6: {=_xlfn.XLOOKUP($A6&$B6,'[1]产值及收款计划（2026）'!$A:$A&'[1]产值及收款计划（2026）'!$B:$B,'[1]产值及收款计划（2026）'!K:K)} -> #NAME? | L6: {=_xlfn.XLOOKUP($A6&$B6,'[1]产值及收款计划（2026）'!$A:$A&'[1]产值及收款计划（2026）'!$B:$B,'[1]产值及收款计划（2026）'!L:L)} -> #NAME? | M6: {=_xlfn.XLOOKUP($A6&$B6,'[1]产值及收款计划（2026）'!$A:$A&'[1]产值及收款计划（2026）'!$B:$B,'[1]产值及收款计划（2026）'!M:M)} -> #NAME? | N6: {=_xlfn.XLOOKUP($A6&$B6,'[1]产值及收款计划（2026）'!$A:$A&'[1]产值及收款计划（2026）'!$B:$B,'[1]产值及收款计划（2026）'!N:N)} -> #NAME? | O6: {=_xlfn.XLOOKUP($A6&$B6,'[1]产值及收款计划（2026）'!$A:$A&'[1]产值及收款计划（2026）'!$B:$B,'[1]产值及收款计划（2026）'!O:O)} -> #NAME? | P6: {=_xlfn.XLOOKUP($A6&$B6,'[1]产值及收款计划（2026）'!$A:$A&'[1]产值及收款计划（2026）'!$B:$B,'[1]产值及收款计划（2026）'!P:P)} -> #NAME? | Q6: {=_xlfn.XLOOKUP($A6&$B6,'[1]产值及收款计划（2026）'!$A:$A&'[1]产值及收款计划（2026）'!$B:$B,'[1]产值及收款计划（2026）'!Q:Q)} -> #NAME? | R6: {=_xlfn.XLOOKUP($A6&$B6,'[1]产值及收款计划（2026）'!$A:$A&'[1]产值及收款计划（2026）'!$B:$B,'[1]产值及收款计划（2026）'!R:R)} -> #NAME? | S6: {=_xlfn.XLOOKUP($A6&$B6,'[1]产值及收款计划（2026）'!$A:$A&'[1]产值及收款计划（2026）'!$B:$B,'[1]产值及收款计划（2026）'!S:S)} -> #NAME? | T6: {=_xlfn.XLOOKUP($A6&$B6,'[1]产值及收款计划（2026）'!$A:$A&'[1]产值及收款计划（2026）'!$B:$B,'[1]产值及收款计划（2026）'!T:T)} -> #NAME? | U6: {=_xlfn.XLOOKUP($A6&$B6,'[1]产值及收款计划（2026）'!$A:$A&'[1]产值及收款计划（2026）'!$B:$B,'[1]产值及收款计划（2026）'!U:U)} -> #NAME? | V6: {=_xlfn.XLOOKUP($A6&$B6,'[1]产值及收款计划（2026）'!$A:$A&'[1]产值及收款计划（2026）'!$B:$B,'[1]产值及收款计划（2026）'!V:V)} -> #NAME? | W6: {=_xlfn.XLOOKUP($A6&$B6,'[1]产值及收款计划（2026）'!$A:$A&'[1]产值及收款计划（2026）'!$B:$B,'[1]产值及收款计划（2026）'!W:W)} -> #NAME? | X6: {=_xlfn.XLOOKUP($A6&$B6,'[1]产值及收款计划（2026）'!$A:$A&'[1]产值及收款计划（2026）'!$B:$B,'[1]产值及收款计划（2026）'!X:X)} -> #NAME? | Y6: {=_xlfn.XLOOKUP($A6&$B6,'[1]产值及收款计划（2026）'!$A:$A&'[1]产值及收款计划（2026）'!$B:$B,'[1]产值及收款计划（2026）'!Y:Y)} -> #NAME? | Z6: {=_xlfn.XLOOKUP($A6&$B6,'[1]产值及收款计划（2026）'!$A:$A&'[1]产值及收款计划（2026）'!$B:$B,'[1]产值及收款计划（2026）'!Z:Z)} -> #NAME? | AA6: {=_xlfn.XLOOKUP($A6&$B6,'[1]产值及收款计划（2026）'!$A:$A&'[1]产值及收款计划（2026）'!$B:$B,'[1]产值及收款计划（2026）'!AA:AA)} -> #NAME? | AB6: {=_xlfn.XLOOKUP($A6&$B6,'[1]产值及收款计划（2026）'!$A:$A&'[1]产值及收款计划（2026）'!$B:$B,'[1]产值及收款计划（2026）'!AB:AB)} -> #NAME? | AC6: {=_xlfn.XLOOKUP($A6&$B6,'[1]产值及收款计划（2026）'!$A:$A&'[1]产值及收款计划（2026）'!$B:$B,'[1]产值及收款计划（2026）'!AC:AC)} -> #NAME? | AD6: {=_xlfn.XLOOKUP($A6&$B6,'[1]产值及收款计划（2026）'!$A:$A&'[1]产值及收款计划（2026）'!$B:$B,'[1]产值及收款计划（2026）'!AD:AD)} -> #NAME? | AE6: {=_xlfn.XLOOKUP($A6&$B6,'[1]产值及收款计划（2026）'!$A:$A&'[1]产值及收款计划（2026）'!$B:$B,'[1]产值及收款计划（2026）'!AE:AE)} -> #NAME? | AF6: {=_xlfn.XLOOKUP($A6&$B6,'[1]产值及收款计划（2026）'!$A:$A&'[1]产值及收款计划（2026）'!$B:$B,'[1]产值及收款计划（2026）'!AF:AF)} -> #NAME? | AG6: {=_xlfn.XLOOKUP($A6&$B6,'[1]产值及收款计划（2026）'!$A:$A&'[1]产值及收款计划（2026）'!$B:$B,'[1]产值及收款计划（2026）'!AG:AG)} -> #NAME? | AH6: {=_xlfn.XLOOKUP($A6&$B6,'[1]产值及收款计划（2026）'!$A:$A&'[1]产值及收款计划（2026）'!$B:$B,'[1]产值及收款计划（2026）'!AH:AH)} -> #NAME? | AI6: {=_xlfn.XLOOKUP($A6&$B6,'[1]产值及收款计划（2026）'!$A:$A&'[1]产值及收款计划（2026）'!$B:$B,'[1]产值及收款计划（2026）'!AI:AI)} -> #NAME? | AJ6: {=_xlfn.XLOOKUP($A6&$B6,'[1]产值及收款计划（2026）'!$A:$A&'[1]产值及收款计划（2026）'!$B:$B,'[1]产值及收款计划（2026）'!AJ:AJ)} -> #NAME? | AK6: {=_xlfn.XLOOKUP($A6&$B6,'[1]产值及收款计划（2026）'!$A:$A&'[1]产值及收款计划（2026）'!$B:$B,'[1]产值及收款计划（2026）'!AK:AK)} -> #NAME? | AL6: {=_xlfn.XLOOKUP($A6&$B6,'[1]产值及收款计划（2026）'!$A:$A&'[1]产值及收款计划（2026）'!$B:$B,'[1]产值及收款计划（2026）'!AL:AL)} -> #NAME? | AM6: {=_xlfn.LET(_xlpm.勾选月份状态数组,TRANSPOSE('PPT(12-15页）-TOP10'!$A$3:$A$14),_xlpm.选择数据区,IF('PPT(12-15页）-TOP10'!$E$3="收款",$BA6:$BL6,$AA6:$AL6),SUM(_xlfn._xlws.FILTER(_xlpm.选择数据区,_xlpm.勾选月份状态数组,"")))} -> #NAME? | AN6: {=_xlfn.LET(_xlpm.勾选月份状态数组,TRANSPOSE('PPT(12-15页）-TOP10'!$A$3:$A$14),_xlpm.选择数据区,IF('PPT(12-15页）-TOP10'!$E$3="收款",$DA6:$DL6,$CA6:$CL6),SUM(_xlfn._xlws.FILTER(_xlpm.选择数据区,_xlpm.勾选月份状态数组,"")))} -> #NAME? | AO6: =SUM(CA6:CC6)+SUM(AD6:AL6) -> #NAME? | AS6: {=_xlfn.XLOOKUP($A6&$B6,'[1]产值及收款计划（2026）'!$A:$A&'[1]产值及收款计划（2026）'!$B:$B,'[1]产值及收款计划（2026）'!AS:AS)} -> #NAME? | AT6: {=_xlfn.XLOOKUP($A6&$B6,'[1]产值及收款计划（2026）'!$A:$A&'[1]产值及收款计划（2026）'!$B:$B,'[1]产值及收款计划（2026）'!AT:AT)} -> #NAME? | AU6: {=_xlfn.XLOOKUP($A6&$B6,'[1]产值及收款计划（2026）'!$A:$A&'[1]产值及收款计划（2026）'!$B:$B,'[1]产值及收款计划（2026）'!AU:AU)} -> #NAME? | AV6: {=_xlfn.XLOOKUP($A6&$B6,'[1]产值及收款计划（2026）'!$A:$A&'[1]产值及收款计划（2026）'!$B:$B,'[1]产值及收款计划（2026）'!AV:AV)} -> #NAME? | AW6: {=_xlfn.XLOOKUP($A6&$B6,'[1]产值及收款计划（2026）'!$A:$A&'[1]产值及收款计划（2026）'!$B:$B,'[1]产值及收款计划（2026）'!AW:AW)} -> #NAME? | AX6: {=_xlfn.XLOOKUP($A6&$B6,'[1]产值及收款计划（2026）'!$A:$A&'[1]产值及收款计划（2026）'!$B:$B,'[1]产值及收款计划（2026）'!AX:AX)} -> #NAME? | AY6: {=_xlfn.XLOOKUP($A6&$B6,'[1]产值及收款计划（2026）'!$A:$A&'[1]产值及收款计划（2026）'!$B:$B,'[1]产值及收款计划（2026）'!AY:AY)} -> #NAME? | AZ6: {=_xlfn.XLOOKUP($A6&$B6,'[1]产值及收款计划（2026）'!$A:$A&'[1]产值及收款计划（2026）'!$B:$B,'[1]产值及收款计划（2026）'!AZ:AZ)} -> #NAME? | BA6: {=_xlfn.XLOOKUP($A6&$B6,'[1]产值及收款计划（2026）'!$A:$A&'[1]产值及收款计划（2026）'!$B:$B,'[1]产值及收款计划（2026）'!BA:BA)} -> #NAME? | BB6: {=_xlfn.XLOOKUP($A6&$B6,'[1]产值及收款计划（2026）'!$A:$A&'[1]产值及收款计划（2026）'!$B:$B,'[1]产值及收款计划（2026）'!BB:BB)} -> #NAME? | BC6: {=_xlfn.XLOOKUP($A6&$B6,'[1]产值及收款计划（2026）'!$A:$A&'[1]产值及收款计划（2026）'!$B:$B,'[1]产值及收款计划（2026）'!BC:BC)} -> #NAME? | BD6: {=_xlfn.XLOOKUP($A6&$B6,'[1]产值及收款计划（2026）'!$A:$A&'[1]产值及收款计划（2026）'!$B:$B,'[1]产值及收款计划（2026）'!BD:BD)} -> #NAME? | BE6: {=_xlfn.XLOOKUP($A6&$B6,'[1]产值及收款计划（2026）'!$A:$A&'[1]产值及收款计划（2026）'!$B:$B,'[1]产值及收款计划（2026）'!BE:BE)} -> #NAME? | BF6: {=_xlfn.XLOOKUP($A6&$B6,'[1]产值及收款计划（2026）'!$A:$A&'[1]产值及收款计划（2026）'!$B:$B,'[1]产值及收款计划（2026）'!BF:BF)} -> #NAME? | BG6: {=_xlfn.XLOOKUP($A6&$B6,'[1]产值及收款计划（2026）'!$A:$A&'[1]产值及收款计划（2026）'!$B:$B,'[1]产值及收款计划（2026）'!BG:BG)} -> #NAME? | BH6: {=_xlfn.XLOOKUP($A6&$B6,'[1]产值及收款计划（2026）'!$A:$A&'[1]产值及收款计划（2026）'!$B:$B,'[1]产值及收款计划（2026）'!BH:BH)} -> #NAME? | BI6: {=_xlfn.XLOOKUP($A6&$B6,'[1]产值及收款计划（2026）'!$A:$A&'[1]产值及收款计划（2026）'!$B:$B,'[1]产值及收款计划（2026）'!BI:BI)} -> #NAME? | BJ6: {=_xlfn.XLOOKUP($A6&$B6,'[1]产值及收款计划（2026）'!$A:$A&'[1]产值及收款计划（2026）'!$B:$B,'[1]产值及收款计划（2026）'!BJ:BJ)} -> #NAME? | BK6: {=_xlfn.XLOOKUP($A6&$B6,'[1]产值及收款计划（2026）'!$A:$A&'[1]产值及收款计划（2026）'!$B:$B,'[1]产值及收款计划（2026）'!BK:BK)} -> #NAME? | BL6: {=_xlfn.XLOOKUP($A6&$B6,'[1]产值及收款计划（2026）'!$A:$A&'[1]产值及收款计划（2026）'!$B:$B,'[1]产值及收款计划（2026）'!BL:BL)} -> #NAME? | BQ6: {=_xlfn.XLOOKUP($A6&$B6,'[1]产值及收款计划（2026）'!$A:$A&'[1]产值及收款计划（2026）'!$B:$B,'[1]产值及收款计划（2026）'!BQ:BQ)} -> #NAME? | BR6: {=_xlfn.XLOOKUP($A6&$B6,'[1]产值及收款计划（2026）'!$A:$A&'[1]产值及收款计划（2026）'!$B:$B,'[1]产值及收款计划（2026）'!BR:BR)} -> #NAME? | BS6: 智能运管中心 | BT6: =SUMIFS($AP:$AP,$B:$B,$BS6,$AO:$AO,BT$4) -> 0 | BU6: =SUMIFS($AP:$AP,$B:$B,$BS6,$AO:$AO,BU$4) -> 0 | BV6: =SUMIFS($AP:$AP,$B:$B,$BS6,$AO:$AO,BV$4) -> 0 | BW6: =SUM(BT6:BV6) -> 0 | CA6: {=_xlfn.XLOOKUP($A6&$B6,'[1]产值及收款计划（2026）'!$A:$A&'[1]产值及收款计划（2026）'!$B:$B,'[1]产值及收款计划（2026）'!CA:CA)} -> #NAME? | CB6: {=_xlfn.XLOOKUP($A6&$B6,'[1]产值及收款计划（2026）'!$A:$A&'[1]产值及收款计划（2026）'!$B:$B,'[1]产值及收款计划（2026）'!CB:CB)} -> #NAME? | CC6: {=_xlfn.XLOOKUP($A6&$B6,'[1]产值及收款计划（2026）'!$A:$A&'[1]产值及收款计划（2026）'!$B:$B,'[1]产值及收款计划（2026）'!CC:CC)} -> #NAME? | CD6: {=_xlfn.XLOOKUP($A6&$B6,'[1]产值及收款计划（2026）'!$A:$A&'[1]产值及收款计划（2026）'!$B:$B,'[1]产值及收款计划（2026）'!CD:CD)} -> #NAME? | CE6: {=_xlfn.XLOOKUP($A6&$B6,'[1]产值及收款计划（2026）'!$A:$A&'[1]产值及收款计划（2026）'!$B:$B,'[1]产值及收款计划（2026）'!CE:CE)} -> #NAME? | CF6: {=_xlfn.XLOOKUP($A6&$B6,'[1]产值及收款计划（2026）'!$A:$A&'[1]产值及收款计划（2026）'!$B:$B,'[1]产值及收款计划（2026）'!CF:CF)} -> #NAME? | CG6: {=_xlfn.XLOOKUP($A6&$B6,'[1]产值及收款计划（2026）'!$A:$A&'[1]产值及收款计划（2026）'!$B:$B,'[1]产值及收款计划（2026）'!CG:CG)} -> #NAME? | CH6: {=_xlfn.XLOOKUP($A6&$B6,'[1]产值及收款计划（2026）'!$A:$A&'[1]产值及收款计划（2026）'!$B:$B,'[1]产值及收款计划（2026）'!CH:CH)} -> #NAME? | CI6: {=_xlfn.XLOOKUP($A6&$B6,'[1]产值及收款计划（2026）'!$A:$A&'[1]产值及收款计划（2026）'!$B:$B,'[1]产值及收款计划（2026）'!CI:CI)} -> #NAME? | CJ6: {=_xlfn.XLOOKUP($A6&$B6,'[1]产值及收款计划（2026）'!$A:$A&'[1]产值及收款计划（2026）'!$B:$B,'[1]产值及收款计划（2026）'!CJ:CJ)} -> #NAME? | CK6: {=_xlfn.XLOOKUP($A6&$B6,'[1]产值及收款计划（2026）'!$A:$A&'[1]产值及收款计划（2026）'!$B:$B,'[1]产值及收款计划（2026）'!CK:CK)} -> #NAME? | CL6: {=_xlfn.XLOOKUP($A6&$B6,'[1]产值及收款计划（2026）'!$A:$A&'[1]产值及收款计划（2026）'!$B:$B,'[1]产值及收款计划（2026）'!CL:CL)} -> #NAME? | DA6: {=_xlfn.XLOOKUP($A6&$B6,'[1]产值及收款计划（2026）'!$A:$A&'[1]产值及收款计划（2026）'!$B:$B,'[1]产值及收款计划（2026）'!DA:DA)} -> #NAME? | DB6: {=_xlfn.XLOOKUP($A6&$B6,'[1]产值及收款计划（2026）'!$A:$A&'[1]产值及收款计划（2026）'!$B:$B,'[1]产值及收款计划（2026）'!DB:DB)} -> #NAME? | DC6: {=_xlfn.XLOOKUP($A6&$B6,'[1]产值及收款计划（2026）'!$A:$A&'[1]产值及收款计划（2026）'!$B:$B,'[1]产值及收款计划（2026）'!DC:DC)} -> #NAME? | DD6: {=_xlfn.XLOOKUP($A6&$B6,'[1]产值及收款计划（2026）'!$A:$A&'[1]产值及收款计划（2026）'!$B:$B,'[1]产值及收款计划（2026）'!DD:DD)} -> #NAME? | DE6: {=_xlfn.XLOOKUP($A6&$B6,'[1]产值及收款计划（2026）'!$A:$A&'[1]产值及收款计划（2026）'!$B:$B,'[1]产值及收款计划（2026）'!DE:DE)} -> #NAME? | DF6: {=_xlfn.XLOOKUP($A6&$B6,'[1]产值及收款计划（2026）'!$A:$A&'[1]产值及收款计划（2026）'!$B:$B,'[1]产值及收款计划（2026）'!DF:DF)} -> #NAME? | DG6: {=_xlfn.XLOOKUP($A6&$B6,'[1]产值及收款计划（2026）'!$A:$A&'[1]产值及收款计划（2026）'!$B:$B,'[1]产值及收款计划（2026）'!DG:DG)} -> #NAME? | DH6: {=_xlfn.XLOOKUP($A6&$B6,'[1]产值及收款计划（2026）'!$A:$A&'[1]产值及收款计划（2026）'!$B:$B,'[1]产值及收款计划（2026）'!DH:DH)} -> #NAME? | DI6: {=_xlfn.XLOOKUP($A6&$B6,'[1]产值及收款计划（2026）'!$A:$A&'[1]产值及收款计划（2026）'!$B:$B,'[1]产值及收款计划（2026）'!DI:DI)} -> #NAME? | DJ6: {=_xlfn.XLOOKUP($A6&$B6,'[1]产值及收款计划（2026）'!$A:$A&'[1]产值及收款计划（2026）'!$B:$B,'[1]产值及收款计划（2026）'!DJ:DJ)} -> #NAME? | DK6: {=_xlfn.XLOOKUP($A6&$B6,'[1]产值及收款计划（2026）'!$A:$A&'[1]产值及收款计划（2026）'!$B:$B,'[1]产值及收款计划（2026）'!DK:DK)} -> #NAME? | DL6: {=_xlfn.XLOOKUP($A6&$B6,'[1]产值及收款计划（2026）'!$A:$A&'[1]产值及收款计划（2026）'!$B:$B,'[1]产值及收款计划（2026）'!DL:DL)} -> #NAME?
A7: =A6+1 -> 3 | B7: 数字建造中心 | C7: {=_xlfn.XLOOKUP($A7&$B7,'[1]产值及收款计划（2026）'!$A:$A&'[1]产值及收款计划（2026）'!$B:$B,'[1]产值及收款计划（2026）'!C:C)} -> #NAME? | D7: {=_xlfn.XLOOKUP($A7&$B7,'[1]产值及收款计划（2026）'!$A:$A&'[1]产值及收款计划（2026）'!$B:$B,'[1]产值及收款计划（2026）'!D:D)} -> #NAME? | E7: {=_xlfn.XLOOKUP($A7&$B7,'[1]产值及收款计划（2026）'!$A:$A&'[1]产值及收款计划（2026）'!$B:$B,'[1]产值及收款计划（2026）'!E:E)} -> #NAME? | F7: {=_xlfn.XLOOKUP($A7&$B7,'[1]产值及收款计划（2026）'!$A:$A&'[1]产值及收款计划（2026）'!$B:$B,'[1]产值及收款计划（2026）'!F:F)} -> #NAME? | G7: {=_xlfn.XLOOKUP($A7&$B7,'[1]产值及收款计划（2026）'!$A:$A&'[1]产值及收款计划（2026）'!$B:$B,'[1]产值及收款计划（2026）'!G:G)} -> #NAME? | H7: {=_xlfn.XLOOKUP($A7&$B7,'[1]产值及收款计划（2026）'!$A:$A&'[1]产值及收款计划（2026）'!$B:$B,'[1]产值及收款计划（2026）'!H:H)} -> #NAME? | I7: {=_xlfn.XLOOKUP($A7&$B7,'[1]产值及收款计划（2026）'!$A:$A&'[1]产值及收款计划（2026）'!$B:$B,'[1]产值及收款计划（2026）'!I:I)} -> #NAME? | J7: {=_xlfn.XLOOKUP($A7&$B7,'[1]产值及收款计划（2026）'!$A:$A&'[1]产值及收款计划（2026）'!$B:$B,'[1]产值及收款计划（2026）'!J:J)} -> #NAME? | K7: {=_xlfn.XLOOKUP($A7&$B7,'[1]产值及收款计划（2026）'!$A:$A&'[1]产值及收款计划（2026）'!$B:$B,'[1]产值及收款计划（2026）'!K:K)} -> #NAME? | L7: {=_xlfn.XLOOKUP($A7&$B7,'[1]产值及收款计划（2026）'!$A:$A&'[1]产值及收款计划（2026）'!$B:$B,'[1]产值及收款计划（2026）'!L:L)} -> #NAME? | M7: {=_xlfn.XLOOKUP($A7&$B7,'[1]产值及收款计划（2026）'!$A:$A&'[1]产值及收款计划（2026）'!$B:$B,'[1]产值及收款计划（2026）'!M:M)} -> #NAME? | N7: {=_xlfn.XLOOKUP($A7&$B7,'[1]产值及收款计划（2026）'!$A:$A&'[1]产值及收款计划（2026）'!$B:$B,'[1]产值及收款计划（2026）'!N:N)} -> #NAME? | O7: {=_xlfn.XLOOKUP($A7&$B7,'[1]产值及收款计划（2026）'!$A:$A&'[1]产值及收款计划（2026）'!$B:$B,'[1]产值及收款计划（2026）'!O:O)} -> #NAME? | P7: {=_xlfn.XLOOKUP($A7&$B7,'[1]产值及收款计划（2026）'!$A:$A&'[1]产值及收款计划（2026）'!$B:$B,'[1]产值及收款计划（2026）'!P:P)} -> #NAME? | Q7: {=_xlfn.XLOOKUP($A7&$B7,'[1]产值及收款计划（2026）'!$A:$A&'[1]产值及收款计划（2026）'!$B:$B,'[1]产值及收款计划（2026）'!Q:Q)} -> #NAME? | R7: {=_xlfn.XLOOKUP($A7&$B7,'[1]产值及收款计划（2026）'!$A:$A&'[1]产值及收款计划（2026）'!$B:$B,'[1]产值及收款计划（2026）'!R:R)} -> #NAME? | S7: {=_xlfn.XLOOKUP($A7&$B7,'[1]产值及收款计划（2026）'!$A:$A&'[1]产值及收款计划（2026）'!$B:$B,'[1]产值及收款计划（2026）'!S:S)} -> #NAME? | T7: {=_xlfn.XLOOKUP($A7&$B7,'[1]产值及收款计划（2026）'!$A:$A&'[1]产值及收款计划（2026）'!$B:$B,'[1]产值及收款计划（2026）'!T:T)} -> #NAME? | U7: {=_xlfn.XLOOKUP($A7&$B7,'[1]产值及收款计划（2026）'!$A:$A&'[1]产值及收款计划（2026）'!$B:$B,'[1]产值及收款计划（2026）'!U:U)} -> #NAME? | V7: {=_xlfn.XLOOKUP($A7&$B7,'[1]产值及收款计划（2026）'!$A:$A&'[1]产值及收款计划（2026）'!$B:$B,'[1]产值及收款计划（2026）'!V:V)} -> #NAME? | W7: {=_xlfn.XLOOKUP($A7&$B7,'[1]产值及收款计划（2026）'!$A:$A&'[1]产值及收款计划（2026）'!$B:$B,'[1]产值及收款计划（2026）'!W:W)} -> #NAME? | X7: {=_xlfn.XLOOKUP($A7&$B7,'[1]产值及收款计划（2026）'!$A:$A&'[1]产值及收款计划（2026）'!$B:$B,'[1]产值及收款计划（2026）'!X:X)} -> #NAME? | Y7: {=_xlfn.XLOOKUP($A7&$B7,'[1]产值及收款计划（2026）'!$A:$A&'[1]产值及收款计划（2026）'!$B:$B,'[1]产值及收款计划（2026）'!Y:Y)} -> #NAME? | Z7: {=_xlfn.XLOOKUP($A7&$B7,'[1]产值及收款计划（2026）'!$A:$A&'[1]产值及收款计划（2026）'!$B:$B,'[1]产值及收款计划（2026）'!Z:Z)} -> #NAME? | AA7: {=_xlfn.XLOOKUP($A7&$B7,'[1]产值及收款计划（2026）'!$A:$A&'[1]产值及收款计划（2026）'!$B:$B,'[1]产值及收款计划（2026）'!AA:AA)} -> #NAME? | AB7: {=_xlfn.XLOOKUP($A7&$B7,'[1]产值及收款计划（2026）'!$A:$A&'[1]产值及收款计划（2026）'!$B:$B,'[1]产值及收款计划（2026）'!AB:AB)} -> #NAME? | AC7: {=_xlfn.XLOOKUP($A7&$B7,'[1]产值及收款计划（2026）'!$A:$A&'[1]产值及收款计划（2026）'!$B:$B,'[1]产值及收款计划（2026）'!AC:AC)} -> #NAME? | AD7: {=_xlfn.XLOOKUP($A7&$B7,'[1]产值及收款计划（2026）'!$A:$A&'[1]产值及收款计划（2026）'!$B:$B,'[1]产值及收款计划（2026）'!AD:AD)} -> #NAME? | AE7: {=_xlfn.XLOOKUP($A7&$B7,'[1]产值及收款计划（2026）'!$A:$A&'[1]产值及收款计划（2026）'!$B:$B,'[1]产值及收款计划（2026）'!AE:AE)} -> #NAME? | AF7: {=_xlfn.XLOOKUP($A7&$B7,'[1]产值及收款计划（2026）'!$A:$A&'[1]产值及收款计划（2026）'!$B:$B,'[1]产值及收款计划（2026）'!AF:AF)} -> #NAME? | AG7: {=_xlfn.XLOOKUP($A7&$B7,'[1]产值及收款计划（2026）'!$A:$A&'[1]产值及收款计划（2026）'!$B:$B,'[1]产值及收款计划（2026）'!AG:AG)} -> #NAME? | AH7: {=_xlfn.XLOOKUP($A7&$B7,'[1]产值及收款计划（2026）'!$A:$A&'[1]产值及收款计划（2026）'!$B:$B,'[1]产值及收款计划（2026）'!AH:AH)} -> #NAME? | AI7: {=_xlfn.XLOOKUP($A7&$B7,'[1]产值及收款计划（2026）'!$A:$A&'[1]产值及收款计划（2026）'!$B:$B,'[1]产值及收款计划（2026）'!AI:AI)} -> #NAME? | AJ7: {=_xlfn.XLOOKUP($A7&$B7,'[1]产值及收款计划（2026）'!$A:$A&'[1]产值及收款计划（2026）'!$B:$B,'[1]产值及收款计划（2026）'!AJ:AJ)} -> #NAME? | AK7: {=_xlfn.XLOOKUP($A7&$B7,'[1]产值及收款计划（2026）'!$A:$A&'[1]产值及收款计划（2026）'!$B:$B,'[1]产值及收款计划（2026）'!AK:AK)} -> #NAME? | AL7: {=_xlfn.XLOOKUP($A7&$B7,'[1]产值及收款计划（2026）'!$A:$A&'[1]产值及收款计划（2026）'!$B:$B,'[1]产值及收款计划（2026）'!AL:AL)} -> #NAME? | AM7: {=_xlfn.LET(_xlpm.勾选月份状态数组,TRANSPOSE('PPT(12-15页）-TOP10'!$A$3:$A$14),_xlpm.选择数据区,IF('PPT(12-15页）-TOP10'!$E$3="收款",$BA7:$BL7,$AA7:$AL7),SUM(_xlfn._xlws.FILTER(_xlpm.选择数据区,_xlpm.勾选月份状态数组,"")))} -> #NAME? | AN7: {=_xlfn.LET(_xlpm.勾选月份状态数组,TRANSPOSE('PPT(12-15页）-TOP10'!$A$3:$A$14),_xlpm.选择数据区,IF('PPT(12-15页）-TOP10'!$E$3="收款",$DA7:$DL7,$CA7:$CL7),SUM(_xlfn._xlws.FILTER(_xlpm.选择数据区,_xlpm.勾选月份状态数组,"")))} -> #NAME? | AO7: =SUM(CA7:CC7)+SUM(AD7:AL7) -> #NAME? | AS7: {=_xlfn.XLOOKUP($A7&$B7,'[1]产值及收款计划（2026）'!$A:$A&'[1]产值及收款计划（2026）'!$B:$B,'[1]产值及收款计划（2026）'!AS:AS)} -> #NAME? | AT7: {=_xlfn.XLOOKUP($A7&$B7,'[1]产值及收款计划（2026）'!$A:$A&'[1]产值及收款计划（2026）'!$B:$B,'[1]产值及收款计划（2026）'!AT:AT)} -> #NAME? | AU7: {=_xlfn.XLOOKUP($A7&$B7,'[1]产值及收款计划（2026）'!$A:$A&'[1]产值及收款计划（2026）'!$B:$B,'[1]产值及收款计划（2026）'!AU:AU)} -> #NAME? | AV7: {=_xlfn.XLOOKUP($A7&$B7,'[1]产值及收款计划（2026）'!$A:$A&'[1]产值及收款计划（2026）'!$B:$B,'[1]产值及收款计划（2026）'!AV:AV)} -> #NAME? | AW7: {=_xlfn.XLOOKUP($A7&$B7,'[1]产值及收款计划（2026）'!$A:$A&'[1]产值及收款计划（2026）'!$B:$B,'[1]产值及收款计划（2026）'!AW:AW)} -> #NAME? | AX7: {=_xlfn.XLOOKUP($A7&$B7,'[1]产值及收款计划（2026）'!$A:$A&'[1]产值及收款计划（2026）'!$B:$B,'[1]产值及收款计划（2026）'!AX:AX)} -> #NAME? | AY7: {=_xlfn.XLOOKUP($A7&$B7,'[1]产值及收款计划（2026）'!$A:$A&'[1]产值及收款计划（2026）'!$B:$B,'[1]产值及收款计划（2026）'!AY:AY)} -> #NAME? | AZ7: {=_xlfn.XLOOKUP($A7&$B7,'[1]产值及收款计划（2026）'!$A:$A&'[1]产值及收款计划（2026）'!$B:$B,'[1]产值及收款计划（2026）'!AZ:AZ)} -> #NAME? | BA7: {=_xlfn.XLOOKUP($A7&$B7,'[1]产值及收款计划（2026）'!$A:$A&'[1]产值及收款计划（2026）'!$B:$B,'[1]产值及收款计划（2026）'!BA:BA)} -> #NAME? | BB7: {=_xlfn.XLOOKUP($A7&$B7,'[1]产值及收款计划（2026）'!$A:$A&'[1]产值及收款计划（2026）'!$B:$B,'[1]产值及收款计划（2026）'!BB:BB)} -> #NAME? | BC7: {=_xlfn.XLOOKUP($A7&$B7,'[1]产值及收款计划（2026）'!$A:$A&'[1]产值及收款计划（2026）'!$B:$B,'[1]产值及收款计划（2026）'!BC:BC)} -> #NAME? | BD7: {=_xlfn.XLOOKUP($A7&$B7,'[1]产值及收款计划（2026）'!$A:$A&'[1]产值及收款计划（2026）'!$B:$B,'[1]产值及收款计划（2026）'!BD:BD)} -> #NAME? | BE7: {=_xlfn.XLOOKUP($A7&$B7,'[1]产值及收款计划（2026）'!$A:$A&'[1]产值及收款计划（2026）'!$B:$B,'[1]产值及收款计划（2026）'!BE:BE)} -> #NAME? | BF7: {=_xlfn.XLOOKUP($A7&$B7,'[1]产值及收款计划（2026）'!$A:$A&'[1]产值及收款计划（2026）'!$B:$B,'[1]产值及收款计划（2026）'!BF:BF)} -> #NAME? | BG7: {=_xlfn.XLOOKUP($A7&$B7,'[1]产值及收款计划（2026）'!$A:$A&'[1]产值及收款计划（2026）'!$B:$B,'[1]产值及收款计划（2026）'!BG:BG)} -> #NAME? | BH7: {=_xlfn.XLOOKUP($A7&$B7,'[1]产值及收款计划（2026）'!$A:$A&'[1]产值及收款计划（2026）'!$B:$B,'[1]产值及收款计划（2026）'!BH:BH)} -> #NAME? | BI7: {=_xlfn.XLOOKUP($A7&$B7,'[1]产值及收款计划（2026）'!$A:$A&'[1]产值及收款计划（2026）'!$B:$B,'[1]产值及收款计划（2026）'!BI:BI)} -> #NAME? | BJ7: {=_xlfn.XLOOKUP($A7&$B7,'[1]产值及收款计划（2026）'!$A:$A&'[1]产值及收款计划（2026）'!$B:$B,'[1]产值及收款计划（2026）'!BJ:BJ)} -> #NAME? | BK7: {=_xlfn.XLOOKUP($A7&$B7,'[1]产值及收款计划（2026）'!$A:$A&'[1]产值及收款计划（2026）'!$B:$B,'[1]产值及收款计划（2026）'!BK:BK)} -> #NAME? | BL7: {=_xlfn.XLOOKUP($A7&$B7,'[1]产值及收款计划（2026）'!$A:$A&'[1]产值及收款计划（2026）'!$B:$B,'[1]产值及收款计划（2026）'!BL:BL)} -> #NAME? | BQ7: {=_xlfn.XLOOKUP($A7&$B7,'[1]产值及收款计划（2026）'!$A:$A&'[1]产值及收款计划（2026）'!$B:$B,'[1]产值及收款计划（2026）'!BQ:BQ)} -> #NAME? | BR7: {=_xlfn.XLOOKUP($A7&$B7,'[1]产值及收款计划（2026）'!$A:$A&'[1]产值及收款计划（2026）'!$B:$B,'[1]产值及收款计划（2026）'!BR:BR)} -> #NAME? | BS7: 数智管理中心 | BT7: =SUMIFS($AP:$AP,$B:$B,$BS7,$AO:$AO,BT$4) -> 0 | BU7: =SUMIFS($AP:$AP,$B:$B,$BS7,$AO:$AO,BU$4) -> 0 | BV7: =SUMIFS($AP:$AP,$B:$B,$BS7,$AO:$AO,BV$4) -> 0 | BW7: =SUM(BT7:BV7) -> 0 | CA7: {=_xlfn.XLOOKUP($A7&$B7,'[1]产值及收款计划（2026）'!$A:$A&'[1]产值及收款计划（2026）'!$B:$B,'[1]产值及收款计划（2026）'!CA:CA)} -> #NAME? | CB7: {=_xlfn.XLOOKUP($A7&$B7,'[1]产值及收款计划（2026）'!$A:$A&'[1]产值及收款计划（2026）'!$B:$B,'[1]产值及收款计划（2026）'!CB:CB)} -> #NAME? | CC7: {=_xlfn.XLOOKUP($A7&$B7,'[1]产值及收款计划（2026）'!$A:$A&'[1]产值及收款计划（2026）'!$B:$B,'[1]产值及收款计划（2026）'!CC:CC)} -> #NAME? | CD7: {=_xlfn.XLOOKUP($A7&$B7,'[1]产值及收款计划（2026）'!$A:$A&'[1]产值及收款计划（2026）'!$B:$B,'[1]产值及收款计划（2026）'!CD:CD)} -> #NAME? | CE7: {=_xlfn.XLOOKUP($A7&$B7,'[1]产值及收款计划（2026）'!$A:$A&'[1]产值及收款计划（2026）'!$B:$B,'[1]产值及收款计划（2026）'!CE:CE)} -> #NAME? | CF7: {=_xlfn.XLOOKUP($A7&$B7,'[1]产值及收款计划（2026）'!$A:$A&'[1]产值及收款计划（2026）'!$B:$B,'[1]产值及收款计划（2026）'!CF:CF)} -> #NAME? | CG7: {=_xlfn.XLOOKUP($A7&$B7,'[1]产值及收款计划（2026）'!$A:$A&'[1]产值及收款计划（2026）'!$B:$B,'[1]产值及收款计划（2026）'!CG:CG)} -> #NAME? | CH7: {=_xlfn.XLOOKUP($A7&$B7,'[1]产值及收款计划（2026）'!$A:$A&'[1]产值及收款计划（2026）'!$B:$B,'[1]产值及收款计划（2026）'!CH:CH)} -> #NAME? | CI7: {=_xlfn.XLOOKUP($A7&$B7,'[1]产值及收款计划（2026）'!$A:$A&'[1]产值及收款计划（2026）'!$B:$B,'[1]产值及收款计划（2026）'!CI:CI)} -> #NAME? | CJ7: {=_xlfn.XLOOKUP($A7&$B7,'[1]产值及收款计划（2026）'!$A:$A&'[1]产值及收款计划（2026）'!$B:$B,'[1]产值及收款计划（2026）'!CJ:CJ)} -> #NAME? | CK7: {=_xlfn.XLOOKUP($A7&$B7,'[1]产值及收款计划（2026）'!$A:$A&'[1]产值及收款计划（2026）'!$B:$B,'[1]产值及收款计划（2026）'!CK:CK)} -> #NAME? | CL7: {=_xlfn.XLOOKUP($A7&$B7,'[1]产值及收款计划（2026）'!$A:$A&'[1]产值及收款计划（2026）'!$B:$B,'[1]产值及收款计划（2026）'!CL:CL)} -> #NAME? | DA7: {=_xlfn.XLOOKUP($A7&$B7,'[1]产值及收款计划（2026）'!$A:$A&'[1]产值及收款计划（2026）'!$B:$B,'[1]产值及收款计划（2026）'!DA:DA)} -> #NAME? | DB7: {=_xlfn.XLOOKUP($A7&$B7,'[1]产值及收款计划（2026）'!$A:$A&'[1]产值及收款计划（2026）'!$B:$B,'[1]产值及收款计划（2026）'!DB:DB)} -> #NAME? | DC7: {=_xlfn.XLOOKUP($A7&$B7,'[1]产值及收款计划（2026）'!$A:$A&'[1]产值及收款计划（2026）'!$B:$B,'[1]产值及收款计划（2026）'!DC:DC)} -> #NAME? | DD7: {=_xlfn.XLOOKUP($A7&$B7,'[1]产值及收款计划（2026）'!$A:$A&'[1]产值及收款计划（2026）'!$B:$B,'[1]产值及收款计划（2026）'!DD:DD)} -> #NAME? | DE7: {=_xlfn.XLOOKUP($A7&$B7,'[1]产值及收款计划（2026）'!$A:$A&'[1]产值及收款计划（2026）'!$B:$B,'[1]产值及收款计划（2026）'!DE:DE)} -> #NAME? | DF7: {=_xlfn.XLOOKUP($A7&$B7,'[1]产值及收款计划（2026）'!$A:$A&'[1]产值及收款计划（2026）'!$B:$B,'[1]产值及收款计划（2026）'!DF:DF)} -> #NAME? | DG7: {=_xlfn.XLOOKUP($A7&$B7,'[1]产值及收款计划（2026）'!$A:$A&'[1]产值及收款计划（2026）'!$B:$B,'[1]产值及收款计划（2026）'!DG:DG)} -> #NAME? | DH7: {=_xlfn.XLOOKUP($A7&$B7,'[1]产值及收款计划（2026）'!$A:$A&'[1]产值及收款计划（2026）'!$B:$B,'[1]产值及收款计划（2026）'!DH:DH)} -> #NAME? | DI7: {=_xlfn.XLOOKUP($A7&$B7,'[1]产值及收款计划（2026）'!$A:$A&'[1]产值及收款计划（2026）'!$B:$B,'[1]产值及收款计划（2026）'!DI:DI)} -> #NAME? | DJ7: {=_xlfn.XLOOKUP($A7&$B7,'[1]产值及收款计划（2026）'!$A:$A&'[1]产值及收款计划（2026）'!$B:$B,'[1]产值及收款计划（2026）'!DJ:DJ)} -> #NAME? | DK7: {=_xlfn.XLOOKUP($A7&$B7,'[1]产值及收款计划（2026）'!$A:$A&'[1]产值及收款计划（2026）'!$B:$B,'[1]产值及收款计划（2026）'!DK:DK)} -> #NAME? | DL7: {=_xlfn.XLOOKUP($A7&$B7,'[1]产值及收款计划（2026）'!$A:$A&'[1]产值及收款计划（2026）'!$B:$B,'[1]产值及收款计划（2026）'!DL:DL)} -> #NAME?
A8: =A7+1 -> 4 | B8: 数字建造中心 | C8: {=_xlfn.XLOOKUP($A8&$B8,'[1]产值及收款计划（2026）'!$A:$A&'[1]产值及收款计划（2026）'!$B:$B,'[1]产值及收款计划（2026）'!C:C)} -> #NAME? | D8: {=_xlfn.XLOOKUP($A8&$B8,'[1]产值及收款计划（2026）'!$A:$A&'[1]产值及收款计划（2026）'!$B:$B,'[1]产值及收款计划（2026）'!D:D)} -> #NAME? | E8: {=_xlfn.XLOOKUP($A8&$B8,'[1]产值及收款计划（2026）'!$A:$A&'[1]产值及收款计划（2026）'!$B:$B,'[1]产值及收款计划（2026）'!E:E)} -> #NAME? | F8: {=_xlfn.XLOOKUP($A8&$B8,'[1]产值及收款计划（2026）'!$A:$A&'[1]产值及收款计划（2026）'!$B:$B,'[1]产值及收款计划（2026）'!F:F)} -> #NAME? | G8: {=_xlfn.XLOOKUP($A8&$B8,'[1]产值及收款计划（2026）'!$A:$A&'[1]产值及收款计划（2026）'!$B:$B,'[1]产值及收款计划（2026）'!G:G)} -> #NAME? | H8: {=_xlfn.XLOOKUP($A8&$B8,'[1]产值及收款计划（2026）'!$A:$A&'[1]产值及收款计划（2026）'!$B:$B,'[1]产值及收款计划（2026）'!H:H)} -> #NAME? | I8: {=_xlfn.XLOOKUP($A8&$B8,'[1]产值及收款计划（2026）'!$A:$A&'[1]产值及收款计划（2026）'!$B:$B,'[1]产值及收款计划（2026）'!I:I)} -> #NAME? | J8: {=_xlfn.XLOOKUP($A8&$B8,'[1]产值及收款计划（2026）'!$A:$A&'[1]产值及收款计划（2026）'!$B:$B,'[1]产值及收款计划（2026）'!J:J)} -> #NAME? | K8: {=_xlfn.XLOOKUP($A8&$B8,'[1]产值及收款计划（2026）'!$A:$A&'[1]产值及收款计划（2026）'!$B:$B,'[1]产值及收款计划（2026）'!K:K)} -> #NAME? | L8: {=_xlfn.XLOOKUP($A8&$B8,'[1]产值及收款计划（2026）'!$A:$A&'[1]产值及收款计划（2026）'!$B:$B,'[1]产值及收款计划（2026）'!L:L)} -> #NAME? | M8: {=_xlfn.XLOOKUP($A8&$B8,'[1]产值及收款计划（2026）'!$A:$A&'[1]产值及收款计划（2026）'!$B:$B,'[1]产值及收款计划（2026）'!M:M)} -> #NAME? | N8: {=_xlfn.XLOOKUP($A8&$B8,'[1]产值及收款计划（2026）'!$A:$A&'[1]产值及收款计划（2026）'!$B:$B,'[1]产值及收款计划（2026）'!N:N)} -> #NAME? | O8: {=_xlfn.XLOOKUP($A8&$B8,'[1]产值及收款计划（2026）'!$A:$A&'[1]产值及收款计划（2026）'!$B:$B,'[1]产值及收款计划（2026）'!O:O)} -> #NAME? | P8: {=_xlfn.XLOOKUP($A8&$B8,'[1]产值及收款计划（2026）'!$A:$A&'[1]产值及收款计划（2026）'!$B:$B,'[1]产值及收款计划（2026）'!P:P)} -> #NAME? | Q8: {=_xlfn.XLOOKUP($A8&$B8,'[1]产值及收款计划（2026）'!$A:$A&'[1]产值及收款计划（2026）'!$B:$B,'[1]产值及收款计划（2026）'!Q:Q)} -> #NAME? | R8: {=_xlfn.XLOOKUP($A8&$B8,'[1]产值及收款计划（2026）'!$A:$A&'[1]产值及收款计划（2026）'!$B:$B,'[1]产值及收款计划（2026）'!R:R)} -> #NAME? | S8: {=_xlfn.XLOOKUP($A8&$B8,'[1]产值及收款计划（2026）'!$A:$A&'[1]产值及收款计划（2026）'!$B:$B,'[1]产值及收款计划（2026）'!S:S)} -> #NAME? | T8: {=_xlfn.XLOOKUP($A8&$B8,'[1]产值及收款计划（2026）'!$A:$A&'[1]产值及收款计划（2026）'!$B:$B,'[1]产值及收款计划（2026）'!T:T)} -> #NAME? | U8: {=_xlfn.XLOOKUP($A8&$B8,'[1]产值及收款计划（2026）'!$A:$A&'[1]产值及收款计划（2026）'!$B:$B,'[1]产值及收款计划（2026）'!U:U)} -> #NAME? | V8: {=_xlfn.XLOOKUP($A8&$B8,'[1]产值及收款计划（2026）'!$A:$A&'[1]产值及收款计划（2026）'!$B:$B,'[1]产值及收款计划（2026）'!V:V)} -> #NAME? | W8: {=_xlfn.XLOOKUP($A8&$B8,'[1]产值及收款计划（2026）'!$A:$A&'[1]产值及收款计划（2026）'!$B:$B,'[1]产值及收款计划（2026）'!W:W)} -> #NAME? | X8: {=_xlfn.XLOOKUP($A8&$B8,'[1]产值及收款计划（2026）'!$A:$A&'[1]产值及收款计划（2026）'!$B:$B,'[1]产值及收款计划（2026）'!X:X)} -> #NAME? | Y8: {=_xlfn.XLOOKUP($A8&$B8,'[1]产值及收款计划（2026）'!$A:$A&'[1]产值及收款计划（2026）'!$B:$B,'[1]产值及收款计划（2026）'!Y:Y)} -> #NAME? | Z8: {=_xlfn.XLOOKUP($A8&$B8,'[1]产值及收款计划（2026）'!$A:$A&'[1]产值及收款计划（2026）'!$B:$B,'[1]产值及收款计划（2026）'!Z:Z)} -> #NAME? | AA8: {=_xlfn.XLOOKUP($A8&$B8,'[1]产值及收款计划（2026）'!$A:$A&'[1]产值及收款计划（2026）'!$B:$B,'[1]产值及收款计划（2026）'!AA:AA)} -> #NAME? | AB8: {=_xlfn.XLOOKUP($A8&$B8,'[1]产值及收款计划（2026）'!$A:$A&'[1]产值及收款计划（2026）'!$B:$B,'[1]产值及收款计划（2026）'!AB:AB)} -> #NAME? | AC8: {=_xlfn.XLOOKUP($A8&$B8,'[1]产值及收款计划（2026）'!$A:$A&'[1]产值及收款计划（2026）'!$B:$B,'[1]产值及收款计划（2026）'!AC:AC)} -> #NAME? | AD8: {=_xlfn.XLOOKUP($A8&$B8,'[1]产值及收款计划（2026）'!$A:$A&'[1]产值及收款计划（2026）'!$B:$B,'[1]产值及收款计划（2026）'!AD:AD)} -> #NAME? | AE8: {=_xlfn.XLOOKUP($A8&$B8,'[1]产值及收款计划（2026）'!$A:$A&'[1]产值及收款计划（2026）'!$B:$B,'[1]产值及收款计划（2026）'!AE:AE)} -> #NAME? | AF8: {=_xlfn.XLOOKUP($A8&$B8,'[1]产值及收款计划（2026）'!$A:$A&'[1]产值及收款计划（2026）'!$B:$B,'[1]产值及收款计划（2026）'!AF:AF)} -> #NAME? | AG8: {=_xlfn.XLOOKUP($A8&$B8,'[1]产值及收款计划（2026）'!$A:$A&'[1]产值及收款计划（2026）'!$B:$B,'[1]产值及收款计划（2026）'!AG:AG)} -> #NAME? | AH8: {=_xlfn.XLOOKUP($A8&$B8,'[1]产值及收款计划（2026）'!$A:$A&'[1]产值及收款计划（2026）'!$B:$B,'[1]产值及收款计划（2026）'!AH:AH)} -> #NAME? | AI8: {=_xlfn.XLOOKUP($A8&$B8,'[1]产值及收款计划（2026）'!$A:$A&'[1]产值及收款计划（2026）'!$B:$B,'[1]产值及收款计划（2026）'!AI:AI)} -> #NAME? | AJ8: {=_xlfn.XLOOKUP($A8&$B8,'[1]产值及收款计划（2026）'!$A:$A&'[1]产值及收款计划（2026）'!$B:$B,'[1]产值及收款计划（2026）'!AJ:AJ)} -> #NAME? | AK8: {=_xlfn.XLOOKUP($A8&$B8,'[1]产值及收款计划（2026）'!$A:$A&'[1]产值及收款计划（2026）'!$B:$B,'[1]产值及收款计划（2026）'!AK:AK)} -> #NAME? | AL8: {=_xlfn.XLOOKUP($A8&$B8,'[1]产值及收款计划（2026）'!$A:$A&'[1]产值及收款计划（2026）'!$B:$B,'[1]产值及收款计划（2026）'!AL:AL)} -> #NAME? | AM8: {=_xlfn.LET(_xlpm.勾选月份状态数组,TRANSPOSE('PPT(12-15页）-TOP10'!$A$3:$A$14),_xlpm.选择数据区,IF('PPT(12-15页）-TOP10'!$E$3="收款",$BA8:$BL8,$AA8:$AL8),SUM(_xlfn._xlws.FILTER(_xlpm.选择数据区,_xlpm.勾选月份状态数组,"")))} -> #NAME? | AN8: {=_xlfn.LET(_xlpm.勾选月份状态数组,TRANSPOSE('PPT(12-15页）-TOP10'!$A$3:$A$14),_xlpm.选择数据区,IF('PPT(12-15页）-TOP10'!$E$3="收款",$DA8:$DL8,$CA8:$CL8),SUM(_xlfn._xlws.FILTER(_xlpm.选择数据区,_xlpm.勾选月份状态数组,"")))} -> #NAME? | AO8: =SUM(CA8:CC8)+SUM(AD8:AL8) -> #NAME? | AS8: {=_xlfn.XLOOKUP($A8&$B8,'[1]产值及收款计划（2026）'!$A:$A&'[1]产值及收款计划（2026）'!$B:$B,'[1]产值及收款计划（2026）'!AS:AS)} -> #NAME? | AT8: {=_xlfn.XLOOKUP($A8&$B8,'[1]产值及收款计划（2026）'!$A:$A&'[1]产值及收款计划（2026）'!$B:$B,'[1]产值及收款计划（2026）'!AT:AT)} -> #NAME? | AU8: {=_xlfn.XLOOKUP($A8&$B8,'[1]产值及收款计划（2026）'!$A:$A&'[1]产值及收款计划（2026）'!$B:$B,'[1]产值及收款计划（2026）'!AU:AU)} -> #NAME? | AV8: {=_xlfn.XLOOKUP($A8&$B8,'[1]产值及收款计划（2026）'!$A:$A&'[1]产值及收款计划（2026）'!$B:$B,'[1]产值及收款计划（2026）'!AV:AV)} -> #NAME? | AW8: {=_xlfn.XLOOKUP($A8&$B8,'[1]产值及收款计划（2026）'!$A:$A&'[1]产值及收款计划（2026）'!$B:$B,'[1]产值及收款计划（2026）'!AW:AW)} -> #NAME? | AX8: {=_xlfn.XLOOKUP($A8&$B8,'[1]产值及收款计划（2026）'!$A:$A&'[1]产值及收款计划（2026）'!$B:$B,'[1]产值及收款计划（2026）'!AX:AX)} -> #NAME? | AY8: {=_xlfn.XLOOKUP($A8&$B8,'[1]产值及收款计划（2026）'!$A:$A&'[1]产值及收款计划（2026）'!$B:$B,'[1]产值及收款计划（2026）'!AY:AY)} -> #NAME? | AZ8: {=_xlfn.XLOOKUP($A8&$B8,'[1]产值及收款计划（2026）'!$A:$A&'[1]产值及收款计划（2026）'!$B:$B,'[1]产值及收款计划（2026）'!AZ:AZ)} -> #NAME? | BA8: {=_xlfn.XLOOKUP($A8&$B8,'[1]产值及收款计划（2026）'!$A:$A&'[1]产值及收款计划（2026）'!$B:$B,'[1]产值及收款计划（2026）'!BA:BA)} -> #NAME? | BB8: {=_xlfn.XLOOKUP($A8&$B8,'[1]产值及收款计划（2026）'!$A:$A&'[1]产值及收款计划（2026）'!$B:$B,'[1]产值及收款计划（2026）'!BB:BB)} -> #NAME? | BC8: {=_xlfn.XLOOKUP($A8&$B8,'[1]产值及收款计划（2026）'!$A:$A&'[1]产值及收款计划（2026）'!$B:$B,'[1]产值及收款计划（2026）'!BC:BC)} -> #NAME? | BD8: {=_xlfn.XLOOKUP($A8&$B8,'[1]产值及收款计划（2026）'!$A:$A&'[1]产值及收款计划（2026）'!$B:$B,'[1]产值及收款计划（2026）'!BD:BD)} -> #NAME? | BE8: {=_xlfn.XLOOKUP($A8&$B8,'[1]产值及收款计划（2026）'!$A:$A&'[1]产值及收款计划（2026）'!$B:$B,'[1]产值及收款计划（2026）'!BE:BE)} -> #NAME? | BF8: {=_xlfn.XLOOKUP($A8&$B8,'[1]产值及收款计划（2026）'!$A:$A&'[1]产值及收款计划（2026）'!$B:$B,'[1]产值及收款计划（2026）'!BF:BF)} -> #NAME? | BG8: {=_xlfn.XLOOKUP($A8&$B8,'[1]产值及收款计划（2026）'!$A:$A&'[1]产值及收款计划（2026）'!$B:$B,'[1]产值及收款计划（2026）'!BG:BG)} -> #NAME? | BH8: {=_xlfn.XLOOKUP($A8&$B8,'[1]产值及收款计划（2026）'!$A:$A&'[1]产值及收款计划（2026）'!$B:$B,'[1]产值及收款计划（2026）'!BH:BH)} -> #NAME? | BI8: {=_xlfn.XLOOKUP($A8&$B8,'[1]产值及收款计划（2026）'!$A:$A&'[1]产值及收款计划（2026）'!$B:$B,'[1]产值及收款计划（2026）'!BI:BI)} -> #NAME? | BJ8: {=_xlfn.XLOOKUP($A8&$B8,'[1]产值及收款计划（2026）'!$A:$A&'[1]产值及收款计划（2026）'!$B:$B,'[1]产值及收款计划（2026）'!BJ:BJ)} -> #NAME? | BK8: {=_xlfn.XLOOKUP($A8&$B8,'[1]产值及收款计划（2026）'!$A:$A&'[1]产值及收款计划（2026）'!$B:$B,'[1]产值及收款计划（2026）'!BK:BK)} -> #NAME? | BL8: {=_xlfn.XLOOKUP($A8&$B8,'[1]产值及收款计划（2026）'!$A:$A&'[1]产值及收款计划（2026）'!$B:$B,'[1]产值及收款计划（2026）'!BL:BL)} -> #NAME? | BQ8: {=_xlfn.XLOOKUP($A8&$B8,'[1]产值及收款计划（2026）'!$A:$A&'[1]产值及收款计划（2026）'!$B:$B,'[1]产值及收款计划（2026）'!BQ:BQ)} -> #NAME? | BR8: {=_xlfn.XLOOKUP($A8&$B8,'[1]产值及收款计划（2026）'!$A:$A&'[1]产值及收款计划（2026）'!$B:$B,'[1]产值及收款计划（2026）'!BR:BR)} -> #NAME? | BS8: 广东分公司 | BT8: =SUMIFS($AP:$AP,$B:$B,$BS8,$AO:$AO,BT$4) -> 0 | BU8: =SUMIFS($AP:$AP,$B:$B,$BS8,$AO:$AO,BU$4) -> 0 | BV8: =SUMIFS($AP:$AP,$B:$B,$BS8,$AO:$AO,BV$4) -> 0 | BW8: =SUM(BT8:BV8) -> 0 | CA8: {=_xlfn.XLOOKUP($A8&$B8,'[1]产值及收款计划（2026）'!$A:$A&'[1]产值及收款计划（2026）'!$B:$B,'[1]产值及收款计划（2026）'!CA:CA)} -> #NAME? | CB8: {=_xlfn.XLOOKUP($A8&$B8,'[1]产值及收款计划（2026）'!$A:$A&'[1]产值及收款计划（2026）'!$B:$B,'[1]产值及收款计划（2026）'!CB:CB)} -> #NAME? | CC8: {=_xlfn.XLOOKUP($A8&$B8,'[1]产值及收款计划（2026）'!$A:$A&'[1]产值及收款计划（2026）'!$B:$B,'[1]产值及收款计划（2026）'!CC:CC)} -> #NAME? | CD8: {=_xlfn.XLOOKUP($A8&$B8,'[1]产值及收款计划（2026）'!$A:$A&'[1]产值及收款计划（2026）'!$B:$B,'[1]产值及收款计划（2026）'!CD:CD)} -> #NAME? | CE8: {=_xlfn.XLOOKUP($A8&$B8,'[1]产值及收款计划（2026）'!$A:$A&'[1]产值及收款计划（2026）'!$B:$B,'[1]产值及收款计划（2026）'!CE:CE)} -> #NAME? | CF8: {=_xlfn.XLOOKUP($A8&$B8,'[1]产值及收款计划（2026）'!$A:$A&'[1]产值及收款计划（2026）'!$B:$B,'[1]产值及收款计划（2026）'!CF:CF)} -> #NAME? | CG8: {=_xlfn.XLOOKUP($A8&$B8,'[1]产值及收款计划（2026）'!$A:$A&'[1]产值及收款计划（2026）'!$B:$B,'[1]产值及收款计划（2026）'!CG:CG)} -> #NAME? | CH8: {=_xlfn.XLOOKUP($A8&$B8,'[1]产值及收款计划（2026）'!$A:$A&'[1]产值及收款计划（2026）'!$B:$B,'[1]产值及收款计划（2026）'!CH:CH)} -> #NAME? | CI8: {=_xlfn.XLOOKUP($A8&$B8,'[1]产值及收款计划（2026）'!$A:$A&'[1]产值及收款计划（2026）'!$B:$B,'[1]产值及收款计划（2026）'!CI:CI)} -> #NAME? | CJ8: {=_xlfn.XLOOKUP($A8&$B8,'[1]产值及收款计划（2026）'!$A:$A&'[1]产值及收款计划（2026）'!$B:$B,'[1]产值及收款计划（2026）'!CJ:CJ)} -> #NAME? | CK8: {=_xlfn.XLOOKUP($A8&$B8,'[1]产值及收款计划（2026）'!$A:$A&'[1]产值及收款计划（2026）'!$B:$B,'[1]产值及收款计划（2026）'!CK:CK)} -> #NAME? | CL8: {=_xlfn.XLOOKUP($A8&$B8,'[1]产值及收款计划（2026）'!$A:$A&'[1]产值及收款计划（2026）'!$B:$B,'[1]产值及收款计划（2026）'!CL:CL)} -> #NAME? | DA8: {=_xlfn.XLOOKUP($A8&$B8,'[1]产值及收款计划（2026）'!$A:$A&'[1]产值及收款计划（2026）'!$B:$B,'[1]产值及收款计划（2026）'!DA:DA)} -> #NAME? | DB8: {=_xlfn.XLOOKUP($A8&$B8,'[1]产值及收款计划（2026）'!$A:$A&'[1]产值及收款计划（2026）'!$B:$B,'[1]产值及收款计划（2026）'!DB:DB)} -> #NAME? | DC8: {=_xlfn.XLOOKUP($A8&$B8,'[1]产值及收款计划（2026）'!$A:$A&'[1]产值及收款计划（2026）'!$B:$B,'[1]产值及收款计划（2026）'!DC:DC)} -> #NAME? | DD8: {=_xlfn.XLOOKUP($A8&$B8,'[1]产值及收款计划（2026）'!$A:$A&'[1]产值及收款计划（2026）'!$B:$B,'[1]产值及收款计划（2026）'!DD:DD)} -> #NAME? | DE8: {=_xlfn.XLOOKUP($A8&$B8,'[1]产值及收款计划（2026）'!$A:$A&'[1]产值及收款计划（2026）'!$B:$B,'[1]产值及收款计划（2026）'!DE:DE)} -> #NAME? | DF8: {=_xlfn.XLOOKUP($A8&$B8,'[1]产值及收款计划（2026）'!$A:$A&'[1]产值及收款计划（2026）'!$B:$B,'[1]产值及收款计划（2026）'!DF:DF)} -> #NAME? | DG8: {=_xlfn.XLOOKUP($A8&$B8,'[1]产值及收款计划（2026）'!$A:$A&'[1]产值及收款计划（2026）'!$B:$B,'[1]产值及收款计划（2026）'!DG:DG)} -> #NAME? | DH8: {=_xlfn.XLOOKUP($A8&$B8,'[1]产值及收款计划（2026）'!$A:$A&'[1]产值及收款计划（2026）'!$B:$B,'[1]产值及收款计划（2026）'!DH:DH)} -> #NAME? | DI8: {=_xlfn.XLOOKUP($A8&$B8,'[1]产值及收款计划（2026）'!$A:$A&'[1]产值及收款计划（2026）'!$B:$B,'[1]产值及收款计划（2026）'!DI:DI)} -> #NAME? | DJ8: {=_xlfn.XLOOKUP($A8&$B8,'[1]产值及收款计划（2026）'!$A:$A&'[1]产值及收款计划（2026）'!$B:$B,'[1]产值及收款计划（2026）'!DJ:DJ)} -> #NAME? | DK8: {=_xlfn.XLOOKUP($A8&$B8,'[1]产值及收款计划（2026）'!$A:$A&'[1]产值及收款计划（2026）'!$B:$B,'[1]产值及收款计划（2026）'!DK:DK)} -> #NAME? | DL8: {=_xlfn.XLOOKUP($A8&$B8,'[1]产值及收款计划（2026）'!$A:$A&'[1]产值及收款计划（2026）'!$B:$B,'[1]产值及收款计划（2026）'!DL:DL)} -> #NAME?
A9: =A8+1 -> 5 | B9: 数字建造中心 | C9: {=_xlfn.XLOOKUP($A9&$B9,'[1]产值及收款计划（2026）'!$A:$A&'[1]产值及收款计划（2026）'!$B:$B,'[1]产值及收款计划（2026）'!C:C)} -> #NAME? | D9: {=_xlfn.XLOOKUP($A9&$B9,'[1]产值及收款计划（2026）'!$A:$A&'[1]产值及收款计划（2026）'!$B:$B,'[1]产值及收款计划（2026）'!D:D)} -> #NAME? | E9: {=_xlfn.XLOOKUP($A9&$B9,'[1]产值及收款计划（2026）'!$A:$A&'[1]产值及收款计划（2026）'!$B:$B,'[1]产值及收款计划（2026）'!E:E)} -> #NAME? | F9: {=_xlfn.XLOOKUP($A9&$B9,'[1]产值及收款计划（2026）'!$A:$A&'[1]产值及收款计划（2026）'!$B:$B,'[1]产值及收款计划（2026）'!F:F)} -> #NAME? | G9: {=_xlfn.XLOOKUP($A9&$B9,'[1]产值及收款计划（2026）'!$A:$A&'[1]产值及收款计划（2026）'!$B:$B,'[1]产值及收款计划（2026）'!G:G)} -> #NAME? | H9: {=_xlfn.XLOOKUP($A9&$B9,'[1]产值及收款计划（2026）'!$A:$A&'[1]产值及收款计划（2026）'!$B:$B,'[1]产值及收款计划（2026）'!H:H)} -> #NAME? | I9: {=_xlfn.XLOOKUP($A9&$B9,'[1]产值及收款计划（2026）'!$A:$A&'[1]产值及收款计划（2026）'!$B:$B,'[1]产值及收款计划（2026）'!I:I)} -> #NAME? | J9: {=_xlfn.XLOOKUP($A9&$B9,'[1]产值及收款计划（2026）'!$A:$A&'[1]产值及收款计划（2026）'!$B:$B,'[1]产值及收款计划（2026）'!J:J)} -> #NAME? | K9: {=_xlfn.XLOOKUP($A9&$B9,'[1]产值及收款计划（2026）'!$A:$A&'[1]产值及收款计划（2026）'!$B:$B,'[1]产值及收款计划（2026）'!K:K)} -> #NAME? | L9: {=_xlfn.XLOOKUP($A9&$B9,'[1]产值及收款计划（2026）'!$A:$A&'[1]产值及收款计划（2026）'!$B:$B,'[1]产值及收款计划（2026）'!L:L)} -> #NAME? | M9: {=_xlfn.XLOOKUP($A9&$B9,'[1]产值及收款计划（2026）'!$A:$A&'[1]产值及收款计划（2026）'!$B:$B,'[1]产值及收款计划（2026）'!M:M)} -> #NAME? | N9: {=_xlfn.XLOOKUP($A9&$B9,'[1]产值及收款计划（2026）'!$A:$A&'[1]产值及收款计划（2026）'!$B:$B,'[1]产值及收款计划（2026）'!N:N)} -> #NAME? | O9: {=_xlfn.XLOOKUP($A9&$B9,'[1]产值及收款计划（2026）'!$A:$A&'[1]产值及收款计划（2026）'!$B:$B,'[1]产值及收款计划（2026）'!O:O)} -> #NAME? | P9: {=_xlfn.XLOOKUP($A9&$B9,'[1]产值及收款计划（2026）'!$A:$A&'[1]产值及收款计划（2026）'!$B:$B,'[1]产值及收款计划（2026）'!P:P)} -> #NAME? | Q9: {=_xlfn.XLOOKUP($A9&$B9,'[1]产值及收款计划（2026）'!$A:$A&'[1]产值及收款计划（2026）'!$B:$B,'[1]产值及收款计划（2026）'!Q:Q)} -> #NAME? | R9: {=_xlfn.XLOOKUP($A9&$B9,'[1]产值及收款计划（2026）'!$A:$A&'[1]产值及收款计划（2026）'!$B:$B,'[1]产值及收款计划（2026）'!R:R)} -> #NAME? | S9: {=_xlfn.XLOOKUP($A9&$B9,'[1]产值及收款计划（2026）'!$A:$A&'[1]产值及收款计划（2026）'!$B:$B,'[1]产值及收款计划（2026）'!S:S)} -> #NAME? | T9: {=_xlfn.XLOOKUP($A9&$B9,'[1]产值及收款计划（2026）'!$A:$A&'[1]产值及收款计划（2026）'!$B:$B,'[1]产值及收款计划（2026）'!T:T)} -> #NAME? | U9: {=_xlfn.XLOOKUP($A9&$B9,'[1]产值及收款计划（2026）'!$A:$A&'[1]产值及收款计划（2026）'!$B:$B,'[1]产值及收款计划（2026）'!U:U)} -> #NAME? | V9: {=_xlfn.XLOOKUP($A9&$B9,'[1]产值及收款计划（2026）'!$A:$A&'[1]产值及收款计划（2026）'!$B:$B,'[1]产值及收款计划（2026）'!V:V)} -> #NAME? | W9: {=_xlfn.XLOOKUP($A9&$B9,'[1]产值及收款计划（2026）'!$A:$A&'[1]产值及收款计划（2026）'!$B:$B,'[1]产值及收款计划（2026）'!W:W)} -> #NAME? | X9: {=_xlfn.XLOOKUP($A9&$B9,'[1]产值及收款计划（2026）'!$A:$A&'[1]产值及收款计划（2026）'!$B:$B,'[1]产值及收款计划（2026）'!X:X)} -> #NAME? | Y9: {=_xlfn.XLOOKUP($A9&$B9,'[1]产值及收款计划（2026）'!$A:$A&'[1]产值及收款计划（2026）'!$B:$B,'[1]产值及收款计划（2026）'!Y:Y)} -> #NAME? | Z9: {=_xlfn.XLOOKUP($A9&$B9,'[1]产值及收款计划（2026）'!$A:$A&'[1]产值及收款计划（2026）'!$B:$B,'[1]产值及收款计划（2026）'!Z:Z)} -> #NAME? | AA9: {=_xlfn.XLOOKUP($A9&$B9,'[1]产值及收款计划（2026）'!$A:$A&'[1]产值及收款计划（2026）'!$B:$B,'[1]产值及收款计划（2026）'!AA:AA)} -> #NAME? | AB9: {=_xlfn.XLOOKUP($A9&$B9,'[1]产值及收款计划（2026）'!$A:$A&'[1]产值及收款计划（2026）'!$B:$B,'[1]产值及收款计划（2026）'!AB:AB)} -> #NAME? | AC9: {=_xlfn.XLOOKUP($A9&$B9,'[1]产值及收款计划（2026）'!$A:$A&'[1]产值及收款计划（2026）'!$B:$B,'[1]产值及收款计划（2026）'!AC:AC)} -> #NAME? | AD9: {=_xlfn.XLOOKUP($A9&$B9,'[1]产值及收款计划（2026）'!$A:$A&'[1]产值及收款计划（2026）'!$B:$B,'[1]产值及收款计划（2026）'!AD:AD)} -> #NAME? | AE9: {=_xlfn.XLOOKUP($A9&$B9,'[1]产值及收款计划（2026）'!$A:$A&'[1]产值及收款计划（2026）'!$B:$B,'[1]产值及收款计划（2026）'!AE:AE)} -> #NAME? | AF9: {=_xlfn.XLOOKUP($A9&$B9,'[1]产值及收款计划（2026）'!$A:$A&'[1]产值及收款计划（2026）'!$B:$B,'[1]产值及收款计划（2026）'!AF:AF)} -> #NAME? | AG9: {=_xlfn.XLOOKUP($A9&$B9,'[1]产值及收款计划（2026）'!$A:$A&'[1]产值及收款计划（2026）'!$B:$B,'[1]产值及收款计划（2026）'!AG:AG)} -> #NAME? | AH9: {=_xlfn.XLOOKUP($A9&$B9,'[1]产值及收款计划（2026）'!$A:$A&'[1]产值及收款计划（2026）'!$B:$B,'[1]产值及收款计划（2026）'!AH:AH)} -> #NAME? | AI9: {=_xlfn.XLOOKUP($A9&$B9,'[1]产值及收款计划（2026）'!$A:$A&'[1]产值及收款计划（2026）'!$B:$B,'[1]产值及收款计划（2026）'!AI:AI)} -> #NAME? | AJ9: {=_xlfn.XLOOKUP($A9&$B9,'[1]产值及收款计划（2026）'!$A:$A&'[1]产值及收款计划（2026）'!$B:$B,'[1]产值及收款计划（2026）'!AJ:AJ)} -> #NAME? | AK9: {=_xlfn.XLOOKUP($A9&$B9,'[1]产值及收款计划（2026）'!$A:$A&'[1]产值及收款计划（2026）'!$B:$B,'[1]产值及收款计划（2026）'!AK:AK)} -> #NAME? | AL9: {=_xlfn.XLOOKUP($A9&$B9,'[1]产值及收款计划（2026）'!$A:$A&'[1]产值及收款计划（2026）'!$B:$B,'[1]产值及收款计划（2026）'!AL:AL)} -> #NAME? | AM9: {=_xlfn.LET(_xlpm.勾选月份状态数组,TRANSPOSE('PPT(12-15页）-TOP10'!$A$3:$A$14),_xlpm.选择数据区,IF('PPT(12-15页）-TOP10'!$E$3="收款",$BA9:$BL9,$AA9:$AL9),SUM(_xlfn._xlws.FILTER(_xlpm.选择数据区,_xlpm.勾选月份状态数组,"")))} -> #NAME? | AN9: {=_xlfn.LET(_xlpm.勾选月份状态数组,TRANSPOSE('PPT(12-15页）-TOP10'!$A$3:$A$14),_xlpm.选择数据区,IF('PPT(12-15页）-TOP10'!$E$3="收款",$DA9:$DL9,$CA9:$CL9),SUM(_xlfn._xlws.FILTER(_xlpm.选择数据区,_xlpm.勾选月份状态数组,"")))} -> #NAME? | AO9: =SUM(CA9:CC9)+SUM(AD9:AL9) -> #NAME? | AS9: {=_xlfn.XLOOKUP($A9&$B9,'[1]产值及收款计划（2026）'!$A:$A&'[1]产值及收款计划（2026）'!$B:$B,'[1]产值及收款计划（2026）'!AS:AS)} -> #NAME? | AT9: {=_xlfn.XLOOKUP($A9&$B9,'[1]产值及收款计划（2026）'!$A:$A&'[1]产值及收款计划（2026）'!$B:$B,'[1]产值及收款计划（2026）'!AT:AT)} -> #NAME? | AU9: {=_xlfn.XLOOKUP($A9&$B9,'[1]产值及收款计划（2026）'!$A:$A&'[1]产值及收款计划（2026）'!$B:$B,'[1]产值及收款计划（2026）'!AU:AU)} -> #NAME? | AV9: {=_xlfn.XLOOKUP($A9&$B9,'[1]产值及收款计划（2026）'!$A:$A&'[1]产值及收款计划（2026）'!$B:$B,'[1]产值及收款计划（2026）'!AV:AV)} -> #NAME? | AW9: {=_xlfn.XLOOKUP($A9&$B9,'[1]产值及收款计划（2026）'!$A:$A&'[1]产值及收款计划（2026）'!$B:$B,'[1]产值及收款计划（2026）'!AW:AW)} -> #NAME? | AX9: {=_xlfn.XLOOKUP($A9&$B9,'[1]产值及收款计划（2026）'!$A:$A&'[1]产值及收款计划（2026）'!$B:$B,'[1]产值及收款计划（2026）'!AX:AX)} -> #NAME? | AY9: {=_xlfn.XLOOKUP($A9&$B9,'[1]产值及收款计划（2026）'!$A:$A&'[1]产值及收款计划（2026）'!$B:$B,'[1]产值及收款计划（2026）'!AY:AY)} -> #NAME? | AZ9: {=_xlfn.XLOOKUP($A9&$B9,'[1]产值及收款计划（2026）'!$A:$A&'[1]产值及收款计划（2026）'!$B:$B,'[1]产值及收款计划（2026）'!AZ:AZ)} -> #NAME? | BA9: {=_xlfn.XLOOKUP($A9&$B9,'[1]产值及收款计划（2026）'!$A:$A&'[1]产值及收款计划（2026）'!$B:$B,'[1]产值及收款计划（2026）'!BA:BA)} -> #NAME? | BB9: {=_xlfn.XLOOKUP($A9&$B9,'[1]产值及收款计划（2026）'!$A:$A&'[1]产值及收款计划（2026）'!$B:$B,'[1]产值及收款计划（2026）'!BB:BB)} -> #NAME? | BC9: {=_xlfn.XLOOKUP($A9&$B9,'[1]产值及收款计划（2026）'!$A:$A&'[1]产值及收款计划（2026）'!$B:$B,'[1]产值及收款计划（2026）'!BC:BC)} -> #NAME? | BD9: {=_xlfn.XLOOKUP($A9&$B9,'[1]产值及收款计划（2026）'!$A:$A&'[1]产值及收款计划（2026）'!$B:$B,'[1]产值及收款计划（2026）'!BD:BD)} -> #NAME? | BE9: {=_xlfn.XLOOKUP($A9&$B9,'[1]产值及收款计划（2026）'!$A:$A&'[1]产值及收款计划（2026）'!$B:$B,'[1]产值及收款计划（2026）'!BE:BE)} -> #NAME? | BF9: {=_xlfn.XLOOKUP($A9&$B9,'[1]产值及收款计划（2026）'!$A:$A&'[1]产值及收款计划（2026）'!$B:$B,'[1]产值及收款计划（2026）'!BF:BF)} -> #NAME? | BG9: {=_xlfn.XLOOKUP($A9&$B9,'[1]产值及收款计划（2026）'!$A:$A&'[1]产值及收款计划（2026）'!$B:$B,'[1]产值及收款计划（2026）'!BG:BG)} -> #NAME? | BH9: {=_xlfn.XLOOKUP($A9&$B9,'[1]产值及收款计划（2026）'!$A:$A&'[1]产值及收款计划（2026）'!$B:$B,'[1]产值及收款计划（2026）'!BH:BH)} -> #NAME? | BI9: {=_xlfn.XLOOKUP($A9&$B9,'[1]产值及收款计划（2026）'!$A:$A&'[1]产值及收款计划（2026）'!$B:$B,'[1]产值及收款计划（2026）'!BI:BI)} -> #NAME? | BJ9: {=_xlfn.XLOOKUP($A9&$B9,'[1]产值及收款计划（2026）'!$A:$A&'[1]产值及收款计划（2026）'!$B:$B,'[1]产值及收款计划（2026）'!BJ:BJ)} -> #NAME? | BK9: {=_xlfn.XLOOKUP($A9&$B9,'[1]产值及收款计划（2026）'!$A:$A&'[1]产值及收款计划（2026）'!$B:$B,'[1]产值及收款计划（2026）'!BK:BK)} -> #NAME? | BL9: {=_xlfn.XLOOKUP($A9&$B9,'[1]产值及收款计划（2026）'!$A:$A&'[1]产值及收款计划（2026）'!$B:$B,'[1]产值及收款计划（2026）'!BL:BL)} -> #NAME? | BQ9: {=_xlfn.XLOOKUP($A9&$B9,'[1]产值及收款计划（2026）'!$A:$A&'[1]产值及收款计划（2026）'!$B:$B,'[1]产值及收款计划（2026）'!BQ:BQ)} -> #NAME? | BR9: {=_xlfn.XLOOKUP($A9&$B9,'[1]产值及收款计划（2026）'!$A:$A&'[1]产值及收款计划（2026）'!$B:$B,'[1]产值及收款计划（2026）'!BR:BR)} -> #NAME? | BS9: 福建分公司 | BT9: =SUMIFS($AP:$AP,$B:$B,$BS9,$AO:$AO,BT$4) -> 0 | BU9: =SUMIFS($AP:$AP,$B:$B,$BS9,$AO:$AO,BU$4) -> 0 | BV9: =SUMIFS($AP:$AP,$B:$B,$BS9,$AO:$AO,BV$4) -> 0 | BW9: =SUM(BT9:BV9) -> 0 | CA9: {=_xlfn.XLOOKUP($A9&$B9,'[1]产值及收款计划（2026）'!$A:$A&'[1]产值及收款计划（2026）'!$B:$B,'[1]产值及收款计划（2026）'!CA:CA)} -> #NAME? | CB9: {=_xlfn.XLOOKUP($A9&$B9,'[1]产值及收款计划（2026）'!$A:$A&'[1]产值及收款计划（2026）'!$B:$B,'[1]产值及收款计划（2026）'!CB:CB)} -> #NAME? | CC9: {=_xlfn.XLOOKUP($A9&$B9,'[1]产值及收款计划（2026）'!$A:$A&'[1]产值及收款计划（2026）'!$B:$B,'[1]产值及收款计划（2026）'!CC:CC)} -> #NAME? | CD9: {=_xlfn.XLOOKUP($A9&$B9,'[1]产值及收款计划（2026）'!$A:$A&'[1]产值及收款计划（2026）'!$B:$B,'[1]产值及收款计划（2026）'!CD:CD)} -> #NAME? | CE9: {=_xlfn.XLOOKUP($A9&$B9,'[1]产值及收款计划（2026）'!$A:$A&'[1]产值及收款计划（2026）'!$B:$B,'[1]产值及收款计划（2026）'!CE:CE)} -> #NAME? | CF9: {=_xlfn.XLOOKUP($A9&$B9,'[1]产值及收款计划（2026）'!$A:$A&'[1]产值及收款计划（2026）'!$B:$B,'[1]产值及收款计划（2026）'!CF:CF)} -> #NAME? | CG9: {=_xlfn.XLOOKUP($A9&$B9,'[1]产值及收款计划（2026）'!$A:$A&'[1]产值及收款计划（2026）'!$B:$B,'[1]产值及收款计划（2026）'!CG:CG)} -> #NAME? | CH9: {=_xlfn.XLOOKUP($A9&$B9,'[1]产值及收款计划（2026）'!$A:$A&'[1]产值及收款计划（2026）'!$B:$B,'[1]产值及收款计划（2026）'!CH:CH)} -> #NAME? | CI9: {=_xlfn.XLOOKUP($A9&$B9,'[1]产值及收款计划（2026）'!$A:$A&'[1]产值及收款计划（2026）'!$B:$B,'[1]产值及收款计划（2026）'!CI:CI)} -> #NAME? | CJ9: {=_xlfn.XLOOKUP($A9&$B9,'[1]产值及收款计划（2026）'!$A:$A&'[1]产值及收款计划（2026）'!$B:$B,'[1]产值及收款计划（2026）'!CJ:CJ)} -> #NAME? | CK9: {=_xlfn.XLOOKUP($A9&$B9,'[1]产值及收款计划（2026）'!$A:$A&'[1]产值及收款计划（2026）'!$B:$B,'[1]产值及收款计划（2026）'!CK:CK)} -> #NAME? | CL9: {=_xlfn.XLOOKUP($A9&$B9,'[1]产值及收款计划（2026）'!$A:$A&'[1]产值及收款计划（2026）'!$B:$B,'[1]产值及收款计划（2026）'!CL:CL)} -> #NAME? | DA9: {=_xlfn.XLOOKUP($A9&$B9,'[1]产值及收款计划（2026）'!$A:$A&'[1]产值及收款计划（2026）'!$B:$B,'[1]产值及收款计划（2026）'!DA:DA)} -> #NAME? | DB9: {=_xlfn.XLOOKUP($A9&$B9,'[1]产值及收款计划（2026）'!$A:$A&'[1]产值及收款计划（2026）'!$B:$B,'[1]产值及收款计划（2026）'!DB:DB)} -> #NAME? | DC9: {=_xlfn.XLOOKUP($A9&$B9,'[1]产值及收款计划（2026）'!$A:$A&'[1]产值及收款计划（2026）'!$B:$B,'[1]产值及收款计划（2026）'!DC:DC)} -> #NAME? | DD9: {=_xlfn.XLOOKUP($A9&$B9,'[1]产值及收款计划（2026）'!$A:$A&'[1]产值及收款计划（2026）'!$B:$B,'[1]产值及收款计划（2026）'!DD:DD)} -> #NAME? | DE9: {=_xlfn.XLOOKUP($A9&$B9,'[1]产值及收款计划（2026）'!$A:$A&'[1]产值及收款计划（2026）'!$B:$B,'[1]产值及收款计划（2026）'!DE:DE)} -> #NAME? | DF9: {=_xlfn.XLOOKUP($A9&$B9,'[1]产值及收款计划（2026）'!$A:$A&'[1]产值及收款计划（2026）'!$B:$B,'[1]产值及收款计划（2026）'!DF:DF)} -> #NAME? | DG9: {=_xlfn.XLOOKUP($A9&$B9,'[1]产值及收款计划（2026）'!$A:$A&'[1]产值及收款计划（2026）'!$B:$B,'[1]产值及收款计划（2026）'!DG:DG)} -> #NAME? | DH9: {=_xlfn.XLOOKUP($A9&$B9,'[1]产值及收款计划（2026）'!$A:$A&'[1]产值及收款计划（2026）'!$B:$B,'[1]产值及收款计划（2026）'!DH:DH)} -> #NAME? | DI9: {=_xlfn.XLOOKUP($A9&$B9,'[1]产值及收款计划（2026）'!$A:$A&'[1]产值及收款计划（2026）'!$B:$B,'[1]产值及收款计划（2026）'!DI:DI)} -> #NAME? | DJ9: {=_xlfn.XLOOKUP($A9&$B9,'[1]产值及收款计划（2026）'!$A:$A&'[1]产值及收款计划（2026）'!$B:$B,'[1]产值及收款计划（2026）'!DJ:DJ)} -> #NAME? | DK9: {=_xlfn.XLOOKUP($A9&$B9,'[1]产值及收款计划（2026）'!$A:$A&'[1]产值及收款计划（2026）'!$B:$B,'[1]产值及收款计划（2026）'!DK:DK)} -> #NAME? | DL9: {=_xlfn.XLOOKUP($A9&$B9,'[1]产值及收款计划（2026）'!$A:$A&'[1]产值及收款计划（2026）'!$B:$B,'[1]产值及收款计划（2026）'!DL:DL)} -> #NAME?
A10: =A9+1 -> 6 | B10: 数字建造中心 | C10: {=_xlfn.XLOOKUP($A10&$B10,'[1]产值及收款计划（2026）'!$A:$A&'[1]产值及收款计划（2026）'!$B:$B,'[1]产值及收款计划（2026）'!C:C)} -> #NAME? | D10: {=_xlfn.XLOOKUP($A10&$B10,'[1]产值及收款计划（2026）'!$A:$A&'[1]产值及收款计划（2026）'!$B:$B,'[1]产值及收款计划（2026）'!D:D)} -> #NAME? | E10: {=_xlfn.XLOOKUP($A10&$B10,'[1]产值及收款计划（2026）'!$A:$A&'[1]产值及收款计划（2026）'!$B:$B,'[1]产值及收款计划（2026）'!E:E)} -> #NAME? | F10: {=_xlfn.XLOOKUP($A10&$B10,'[1]产值及收款计划（2026）'!$A:$A&'[1]产值及收款计划（2026）'!$B:$B,'[1]产值及收款计划（2026）'!F:F)} -> #NAME? | G10: {=_xlfn.XLOOKUP($A10&$B10,'[1]产值及收款计划（2026）'!$A:$A&'[1]产值及收款计划（2026）'!$B:$B,'[1]产值及收款计划（2026）'!G:G)} -> #NAME? | H10: {=_xlfn.XLOOKUP($A10&$B10,'[1]产值及收款计划（2026）'!$A:$A&'[1]产值及收款计划（2026）'!$B:$B,'[1]产值及收款计划（2026）'!H:H)} -> #NAME? | I10: {=_xlfn.XLOOKUP($A10&$B10,'[1]产值及收款计划（2026）'!$A:$A&'[1]产值及收款计划（2026）'!$B:$B,'[1]产值及收款计划（2026）'!I:I)} -> #NAME? | J10: {=_xlfn.XLOOKUP($A10&$B10,'[1]产值及收款计划（2026）'!$A:$A&'[1]产值及收款计划（2026）'!$B:$B,'[1]产值及收款计划（2026）'!J:J)} -> #NAME? | K10: {=_xlfn.XLOOKUP($A10&$B10,'[1]产值及收款计划（2026）'!$A:$A&'[1]产值及收款计划（2026）'!$B:$B,'[1]产值及收款计划（2026）'!K:K)} -> #NAME? | L10: {=_xlfn.XLOOKUP($A10&$B10,'[1]产值及收款计划（2026）'!$A:$A&'[1]产值及收款计划（2026）'!$B:$B,'[1]产值及收款计划（2026）'!L:L)} -> #NAME? | M10: {=_xlfn.XLOOKUP($A10&$B10,'[1]产值及收款计划（2026）'!$A:$A&'[1]产值及收款计划（2026）'!$B:$B,'[1]产值及收款计划（2026）'!M:M)} -> #NAME? | N10: {=_xlfn.XLOOKUP($A10&$B10,'[1]产值及收款计划（2026）'!$A:$A&'[1]产值及收款计划（2026）'!$B:$B,'[1]产值及收款计划（2026）'!N:N)} -> #NAME? | O10: {=_xlfn.XLOOKUP($A10&$B10,'[1]产值及收款计划（2026）'!$A:$A&'[1]产值及收款计划（2026）'!$B:$B,'[1]产值及收款计划（2026）'!O:O)} -> #NAME? | P10: {=_xlfn.XLOOKUP($A10&$B10,'[1]产值及收款计划（2026）'!$A:$A&'[1]产值及收款计划（2026）'!$B:$B,'[1]产值及收款计划（2026）'!P:P)} -> #NAME? | Q10: {=_xlfn.XLOOKUP($A10&$B10,'[1]产值及收款计划（2026）'!$A:$A&'[1]产值及收款计划（2026）'!$B:$B,'[1]产值及收款计划（2026）'!Q:Q)} -> #NAME? | R10: {=_xlfn.XLOOKUP($A10&$B10,'[1]产值及收款计划（2026）'!$A:$A&'[1]产值及收款计划（2026）'!$B:$B,'[1]产值及收款计划（2026）'!R:R)} -> #NAME? | S10: {=_xlfn.XLOOKUP($A10&$B10,'[1]产值及收款计划（2026）'!$A:$A&'[1]产值及收款计划（2026）'!$B:$B,'[1]产值及收款计划（2026）'!S:S)} -> #NAME? | T10: {=_xlfn.XLOOKUP($A10&$B10,'[1]产值及收款计划（2026）'!$A:$A&'[1]产值及收款计划（2026）'!$B:$B,'[1]产值及收款计划（2026）'!T:T)} -> #NAME? | U10: {=_xlfn.XLOOKUP($A10&$B10,'[1]产值及收款计划（2026）'!$A:$A&'[1]产值及收款计划（2026）'!$B:$B,'[1]产值及收款计划（2026）'!U:U)} -> #NAME? | V10: {=_xlfn.XLOOKUP($A10&$B10,'[1]产值及收款计划（2026）'!$A:$A&'[1]产值及收款计划（2026）'!$B:$B,'[1]产值及收款计划（2026）'!V:V)} -> #NAME? | W10: {=_xlfn.XLOOKUP($A10&$B10,'[1]产值及收款计划（2026）'!$A:$A&'[1]产值及收款计划（2026）'!$B:$B,'[1]产值及收款计划（2026）'!W:W)} -> #NAME? | X10: {=_xlfn.XLOOKUP($A10&$B10,'[1]产值及收款计划（2026）'!$A:$A&'[1]产值及收款计划（2026）'!$B:$B,'[1]产值及收款计划（2026）'!X:X)} -> #NAME? | Y10: {=_xlfn.XLOOKUP($A10&$B10,'[1]产值及收款计划（2026）'!$A:$A&'[1]产值及收款计划（2026）'!$B:$B,'[1]产值及收款计划（2026）'!Y:Y)} -> #NAME? | Z10: {=_xlfn.XLOOKUP($A10&$B10,'[1]产值及收款计划（2026）'!$A:$A&'[1]产值及收款计划（2026）'!$B:$B,'[1]产值及收款计划（2026）'!Z:Z)} -> #NAME? | AA10: {=_xlfn.XLOOKUP($A10&$B10,'[1]产值及收款计划（2026）'!$A:$A&'[1]产值及收款计划（2026）'!$B:$B,'[1]产值及收款计划（2026）'!AA:AA)} -> #NAME? | AB10: {=_xlfn.XLOOKUP($A10&$B10,'[1]产值及收款计划（2026）'!$A:$A&'[1]产值及收款计划（2026）'!$B:$B,'[1]产值及收款计划（2026）'!AB:AB)} -> #NAME? | AC10: {=_xlfn.XLOOKUP($A10&$B10,'[1]产值及收款计划（2026）'!$A:$A&'[1]产值及收款计划（2026）'!$B:$B,'[1]产值及收款计划（2026）'!AC:AC)} -> #NAME? | AD10: {=_xlfn.XLOOKUP($A10&$B10,'[1]产值及收款计划（2026）'!$A:$A&'[1]产值及收款计划（2026）'!$B:$B,'[1]产值及收款计划（2026）'!AD:AD)} -> #NAME? | AE10: {=_xlfn.XLOOKUP($A10&$B10,'[1]产值及收款计划（2026）'!$A:$A&'[1]产值及收款计划（2026）'!$B:$B,'[1]产值及收款计划（2026）'!AE:AE)} -> #NAME? | AF10: {=_xlfn.XLOOKUP($A10&$B10,'[1]产值及收款计划（2026）'!$A:$A&'[1]产值及收款计划（2026）'!$B:$B,'[1]产值及收款计划（2026）'!AF:AF)} -> #NAME? | AG10: {=_xlfn.XLOOKUP($A10&$B10,'[1]产值及收款计划（2026）'!$A:$A&'[1]产值及收款计划（2026）'!$B:$B,'[1]产值及收款计划（2026）'!AG:AG)} -> #NAME? | AH10: {=_xlfn.XLOOKUP($A10&$B10,'[1]产值及收款计划（2026）'!$A:$A&'[1]产值及收款计划（2026）'!$B:$B,'[1]产值及收款计划（2026）'!AH:AH)} -> #NAME? | AI10: {=_xlfn.XLOOKUP($A10&$B10,'[1]产值及收款计划（2026）'!$A:$A&'[1]产值及收款计划（2026）'!$B:$B,'[1]产值及收款计划（2026）'!AI:AI)} -> #NAME? | AJ10: {=_xlfn.XLOOKUP($A10&$B10,'[1]产值及收款计划（2026）'!$A:$A&'[1]产值及收款计划（2026）'!$B:$B,'[1]产值及收款计划（2026）'!AJ:AJ)} -> #NAME? | AK10: {=_xlfn.XLOOKUP($A10&$B10,'[1]产值及收款计划（2026）'!$A:$A&'[1]产值及收款计划（2026）'!$B:$B,'[1]产值及收款计划（2026）'!AK:AK)} -> #NAME? | AL10: {=_xlfn.XLOOKUP($A10&$B10,'[1]产值及收款计划（2026）'!$A:$A&'[1]产值及收款计划（2026）'!$B:$B,'[1]产值及收款计划（2026）'!AL:AL)} -> #NAME? | AM10: {=_xlfn.LET(_xlpm.勾选月份状态数组,TRANSPOSE('PPT(12-15页）-TOP10'!$A$3:$A$14),_xlpm.选择数据区,IF('PPT(12-15页）-TOP10'!$E$3="收款",$BA10:$BL10,$AA10:$AL10),SUM(_xlfn._xlws.FILTER(_xlpm.选择数据区,_xlpm.勾选月份状态数组,"")))} -> #NAME? | AN10: {=_xlfn.LET(_xlpm.勾选月份状态数组,TRANSPOSE('PPT(12-15页）-TOP10'!$A$3:$A$14),_xlpm.选择数据区,IF('PPT(12-15页）-TOP10'!$E$3="收款",$DA10:$DL10,$CA10:$CL10),SUM(_xlfn._xlws.FILTER(_xlpm.选择数据区,_xlpm.勾选月份状态数组,"")))} -> #NAME? | AO10: =SUM(CA10:CC10)+SUM(AD10:AL10) -> 0 | AS10: {=_xlfn.XLOOKUP($A10&$B10,'[1]产值及收款计划（2026）'!$A:$A&'[1]产值及收款计划（2026）'!$B:$B,'[1]产值及收款计划（2026）'!AS:AS)} -> #NAME? | AT10: {=_xlfn.XLOOKUP($A10&$B10,'[1]产值及收款计划（2026）'!$A:$A&'[1]产值及收款计划（2026）'!$B:$B,'[1]产值及收款计划（2026）'!AT:AT)} -> #NAME? | AU10: {=_xlfn.XLOOKUP($A10&$B10,'[1]产值及收款计划（2026）'!$A:$A&'[1]产值及收款计划（2026）'!$B:$B,'[1]产值及收款计划（2026）'!AU:AU)} -> #NAME? | AV10: {=_xlfn.XLOOKUP($A10&$B10,'[1]产值及收款计划（2026）'!$A:$A&'[1]产值及收款计划（2026）'!$B:$B,'[1]产值及收款计划（2026）'!AV:AV)} -> #NAME? | AW10: {=_xlfn.XLOOKUP($A10&$B10,'[1]产值及收款计划（2026）'!$A:$A&'[1]产值及收款计划（2026）'!$B:$B,'[1]产值及收款计划（2026）'!AW:AW)} -> #NAME? | AX10: {=_xlfn.XLOOKUP($A10&$B10,'[1]产值及收款计划（2026）'!$A:$A&'[1]产值及收款计划（2026）'!$B:$B,'[1]产值及收款计划（2026）'!AX:AX)} -> #NAME? | AY10: {=_xlfn.XLOOKUP($A10&$B10,'[1]产值及收款计划（2026）'!$A:$A&'[1]产值及收款计划（2026）'!$B:$B,'[1]产值及收款计划（2026）'!AY:AY)} -> #NAME? | AZ10: {=_xlfn.XLOOKUP($A10&$B10,'[1]产值及收款计划（2026）'!$A:$A&'[1]产值及收款计划（2026）'!$B:$B,'[1]产值及收款计划（2026）'!AZ:AZ)} -> #NAME? | BA10: {=_xlfn.XLOOKUP($A10&$B10,'[1]产值及收款计划（2026）'!$A:$A&'[1]产值及收款计划（2026）'!$B:$B,'[1]产值及收款计划（2026）'!BA:BA)} -> #NAME? | BB10: {=_xlfn.XLOOKUP($A10&$B10,'[1]产值及收款计划（2026）'!$A:$A&'[1]产值及收款计划（2026）'!$B:$B,'[1]产值及收款计划（2026）'!BB:BB)} -> #NAME? | BC10: {=_xlfn.XLOOKUP($A10&$B10,'[1]产值及收款计划（2026）'!$A:$A&'[1]产值及收款计划（2026）'!$B:$B,'[1]产值及收款计划（2026）'!BC:BC)} -> #NAME? | BD10: {=_xlfn.XLOOKUP($A10&$B10,'[1]产值及收款计划（2026）'!$A:$A&'[1]产值及收款计划（2026）'!$B:$B,'[1]产值及收款计划（2026）'!BD:BD)} -> #NAME? | BE10: {=_xlfn.XLOOKUP($A10&$B10,'[1]产值及收款计划（2026）'!$A:$A&'[1]产值及收款计划（2026）'!$B:$B,'[1]产值及收款计划（2026）'!BE:BE)} -> #NAME? | BF10: {=_xlfn.XLOOKUP($A10&$B10,'[1]产值及收款计划（2026）'!$A:$A&'[1]产值及收款计划（2026）'!$B:$B,'[1]产值及收款计划（2026）'!BF:BF)} -> #NAME? | BG10: {=_xlfn.XLOOKUP($A10&$B10,'[1]产值及收款计划（2026）'!$A:$A&'[1]产值及收款计划（2026）'!$B:$B,'[1]产值及收款计划（2026）'!BG:BG)} -> #NAME? | BH10: {=_xlfn.XLOOKUP($A10&$B10,'[1]产值及收款计划（2026）'!$A:$A&'[1]产值及收款计划（2026）'!$B:$B,'[1]产值及收款计划（2026）'!BH:BH)} -> #NAME? | BI10: {=_xlfn.XLOOKUP($A10&$B10,'[1]产值及收款计划（2026）'!$A:$A&'[1]产值及收款计划（2026）'!$B:$B,'[1]产值及收款计划（2026）'!BI:BI)} -> #NAME? | BJ10: {=_xlfn.XLOOKUP($A10&$B10,'[1]产值及收款计划（2026）'!$A:$A&'[1]产值及收款计划（2026）'!$B:$B,'[1]产值及收款计划（2026）'!BJ:BJ)} -> #NAME? | BK10: {=_xlfn.XLOOKUP($A10&$B10,'[1]产值及收款计划（2026）'!$A:$A&'[1]产值及收款计划（2026）'!$B:$B,'[1]产值及收款计划（2026）'!BK:BK)} -> #NAME? | BL10: {=_xlfn.XLOOKUP($A10&$B10,'[1]产值及收款计划（2026）'!$A:$A&'[1]产值及收款计划（2026）'!$B:$B,'[1]产值及收款计划（2026）'!BL:BL)} -> #NAME? | BQ10: {=_xlfn.XLOOKUP($A10&$B10,'[1]产值及收款计划（2026）'!$A:$A&'[1]产值及收款计划（2026）'!$B:$B,'[1]产值及收款计划（2026）'!BQ:BQ)} -> #NAME? | BR10: {=_xlfn.XLOOKUP($A10&$B10,'[1]产值及收款计划（2026）'!$A:$A&'[1]产值及收款计划（2026）'!$B:$B,'[1]产值及收款计划（2026）'!BR:BR)} -> #NAME? | BT10: =SUM(BT5:BT9) -> 0 | BU10: =SUM(BU5:BU9) -> 0 | BV10: =SUM(BV5:BV9) -> 0 | BW10: =SUM(BW5:BW9) -> 0 | CA10: {=_xlfn.XLOOKUP($A10&$B10,'[1]产值及收款计划（2026）'!$A:$A&'[1]产值及收款计划（2026）'!$B:$B,'[1]产值及收款计划（2026）'!CA:CA)} -> #NAME? | CB10: {=_xlfn.XLOOKUP($A10&$B10,'[1]产值及收款计划（2026）'!$A:$A&'[1]产值及收款计划（2026）'!$B:$B,'[1]产值及收款计划（2026）'!CB:CB)} -> #NAME? | CC10: {=_xlfn.XLOOKUP($A10&$B10,'[1]产值及收款计划（2026）'!$A:$A&'[1]产值及收款计划（2026）'!$B:$B,'[1]产值及收款计划（2026）'!CC:CC)} -> #NAME? | CD10: {=_xlfn.XLOOKUP($A10&$B10,'[1]产值及收款计划（2026）'!$A:$A&'[1]产值及收款计划（2026）'!$B:$B,'[1]产值及收款计划（2026）'!CD:CD)} -> #NAME? | CE10: {=_xlfn.XLOOKUP($A10&$B10,'[1]产值及收款计划（2026）'!$A:$A&'[1]产值及收款计划（2026）'!$B:$B,'[1]产值及收款计划（2026）'!CE:CE)} -> #NAME? | CF10: {=_xlfn.XLOOKUP($A10&$B10,'[1]产值及收款计划（2026）'!$A:$A&'[1]产值及收款计划（2026）'!$B:$B,'[1]产值及收款计划（2026）'!CF:CF)} -> #NAME? | CG10: {=_xlfn.XLOOKUP($A10&$B10,'[1]产值及收款计划（2026）'!$A:$A&'[1]产值及收款计划（2026）'!$B:$B,'[1]产值及收款计划（2026）'!CG:CG)} -> #NAME? | CH10: {=_xlfn.XLOOKUP($A10&$B10,'[1]产值及收款计划（2026）'!$A:$A&'[1]产值及收款计划（2026）'!$B:$B,'[1]产值及收款计划（2026）'!CH:CH)} -> #NAME? | CI10: {=_xlfn.XLOOKUP($A10&$B10,'[1]产值及收款计划（2026）'!$A:$A&'[1]产值及收款计划（2026）'!$B:$B,'[1]产值及收款计划（2026）'!CI:CI)} -> #NAME? | CJ10: {=_xlfn.XLOOKUP($A10&$B10,'[1]产值及收款计划（2026）'!$A:$A&'[1]产值及收款计划（2026）'!$B:$B,'[1]产值及收款计划（2026）'!CJ:CJ)} -> #NAME? | CK10: {=_xlfn.XLOOKUP($A10&$B10,'[1]产值及收款计划（2026）'!$A:$A&'[1]产值及收款计划（2026）'!$B:$B,'[1]产值及收款计划（2026）'!CK:CK)} -> #NAME? | CL10: {=_xlfn.XLOOKUP($A10&$B10,'[1]产值及收款计划（2026）'!$A:$A&'[1]产值及收款计划（2026）'!$B:$B,'[1]产值及收款计划（2026）'!CL:CL)} -> #NAME? | DA10: {=_xlfn.XLOOKUP($A10&$B10,'[1]产值及收款计划（2026）'!$A:$A&'[1]产值及收款计划（2026）'!$B:$B,'[1]产值及收款计划（2026）'!DA:DA)} -> #NAME? | DB10: {=_xlfn.XLOOKUP($A10&$B10,'[1]产值及收款计划（2026）'!$A:$A&'[1]产值及收款计划（2026）'!$B:$B,'[1]产值及收款计划（2026）'!DB:DB)} -> #NAME? | DC10: {=_xlfn.XLOOKUP($A10&$B10,'[1]产值及收款计划（2026）'!$A:$A&'[1]产值及收款计划（2026）'!$B:$B,'[1]产值及收款计划（2026）'!DC:DC)} -> #NAME? | DD10: {=_xlfn.XLOOKUP($A10&$B10,'[1]产值及收款计划（2026）'!$A:$A&'[1]产值及收款计划（2026）'!$B:$B,'[1]产值及收款计划（2026）'!DD:DD)} -> #NAME? | DE10: {=_xlfn.XLOOKUP($A10&$B10,'[1]产值及收款计划（2026）'!$A:$A&'[1]产值及收款计划（2026）'!$B:$B,'[1]产值及收款计划（2026）'!DE:DE)} -> #NAME? | DF10: {=_xlfn.XLOOKUP($A10&$B10,'[1]产值及收款计划（2026）'!$A:$A&'[1]产值及收款计划（2026）'!$B:$B,'[1]产值及收款计划（2026）'!DF:DF)} -> #NAME? | DG10: {=_xlfn.XLOOKUP($A10&$B10,'[1]产值及收款计划（2026）'!$A:$A&'[1]产值及收款计划（2026）'!$B:$B,'[1]产值及收款计划（2026）'!DG:DG)} -> #NAME? | DH10: {=_xlfn.XLOOKUP($A10&$B10,'[1]产值及收款计划（2026）'!$A:$A&'[1]产值及收款计划（2026）'!$B:$B,'[1]产值及收款计划（2026）'!DH:DH)} -> #NAME? | DI10: {=_xlfn.XLOOKUP($A10&$B10,'[1]产值及收款计划（2026）'!$A:$A&'[1]产值及收款计划（2026）'!$B:$B,'[1]产值及收款计划（2026）'!DI:DI)} -> #NAME? | DJ10: {=_xlfn.XLOOKUP($A10&$B10,'[1]产值及收款计划（2026）'!$A:$A&'[1]产值及收款计划（2026）'!$B:$B,'[1]产值及收款计划（2026）'!DJ:DJ)} -> #NAME? | DK10: {=_xlfn.XLOOKUP($A10&$B10,'[1]产值及收款计划（2026）'!$A:$A&'[1]产值及收款计划（2026）'!$B:$B,'[1]产值及收款计划（2026）'!DK:DK)} -> #NAME? | DL10: {=_xlfn.XLOOKUP($A10&$B10,'[1]产值及收款计划（2026）'!$A:$A&'[1]产值及收款计划（2026）'!$B:$B,'[1]产值及收款计划（2026）'!DL:DL)} -> #NAME?
A11: =A10+1 -> 7 | B11: 数字建造中心 | C11: {=_xlfn.XLOOKUP($A11&$B11,'[1]产值及收款计划（2026）'!$A:$A&'[1]产值及收款计划（2026）'!$B:$B,'[1]产值及收款计划（2026）'!C:C)} -> ZHT2022091400074 | D11: {=_xlfn.XLOOKUP($A11&$B11,'[1]产值及收款计划（2026）'!$A:$A&'[1]产值及收款计划（2026）'!$B:$B,'[1]产值及收款计划（2026）'!D:D)} -> 上海市域铁路机场联络线1标一分部 中铁二十四局集团有限公司智慧工地项目 | E11: {=_xlfn.XLOOKUP($A11&$B11,'[1]产值及收款计划（2026）'!$A:$A&'[1]产值及收款计划（2026）'!$B:$B,'[1]产值及收款计划（2026）'!E:E)} -> 15.6584 | F11: {=_xlfn.XLOOKUP($A11&$B11,'[1]产值及收款计划（2026）'!$A:$A&'[1]产值及收款计划（2026）'!$B:$B,'[1]产值及收款计划（2026）'!F:F)} -> 15.6584 | G11: {=_xlfn.XLOOKUP($A11&$B11,'[1]产值及收款计划（2026）'!$A:$A&'[1]产值及收款计划（2026）'!$B:$B,'[1]产值及收款计划（2026）'!G:G)} -> 0 | H11: {=_xlfn.XLOOKUP($A11&$B11,'[1]产值及收款计划（2026）'!$A:$A&'[1]产值及收款计划（2026）'!$B:$B,'[1]产值及收款计划（2026）'!H:H)} -> 5.6584 | I11: {=_xlfn.XLOOKUP($A11&$B11,'[1]产值及收款计划（2026）'!$A:$A&'[1]产值及收款计划（2026）'!$B:$B,'[1]产值及收款计划（2026）'!I:I)} -> 0.36136515 | J11: {=_xlfn.XLOOKUP($A11&$B11,'[1]产值及收款计划（2026）'!$A:$A&'[1]产值及收款计划（2026）'!$B:$B,'[1]产值及收款计划（2026）'!J:J)} -> 0.10692707 | K11: {=_xlfn.XLOOKUP($A11&$B11,'[1]产值及收款计划（2026）'!$A:$A&'[1]产值及收款计划（2026）'!$B:$B,'[1]产值及收款计划（2026）'!K:K)} -> 0 | L11: {=_xlfn.XLOOKUP($A11&$B11,'[1]产值及收款计划（2026）'!$A:$A&'[1]产值及收款计划（2026）'!$B:$B,'[1]产值及收款计划（2026）'!L:L)} -> 0 | M11: {=_xlfn.XLOOKUP($A11&$B11,'[1]产值及收款计划（2026）'!$A:$A&'[1]产值及收款计划（2026）'!$B:$B,'[1]产值及收款计划（2026）'!M:M)} -> 主导 | N11: {=_xlfn.XLOOKUP($A11&$B11,'[1]产值及收款计划（2026）'!$A:$A&'[1]产值及收款计划（2026）'!$B:$B,'[1]产值及收款计划（2026）'!N:N)} -> 史菁霞团队 | O11: {=_xlfn.XLOOKUP($A11&$B11,'[1]产值及收款计划（2026）'!$A:$A&'[1]产值及收款计划（2026）'!$B:$B,'[1]产值及收款计划（2026）'!O:O)} -> 谢复欣 | P11: {=_xlfn.XLOOKUP($A11&$B11,'[1]产值及收款计划（2026）'!$A:$A&'[1]产值及收款计划（2026）'!$B:$B,'[1]产值及收款计划（2026）'!P:P)} -> 过往已完结 | Q11: {=_xlfn.XLOOKUP($A11&$B11,'[1]产值及收款计划（2026）'!$A:$A&'[1]产值及收款计划（2026）'!$B:$B,'[1]产值及收款计划（2026）'!Q:Q)} -> 0 | R11: {=_xlfn.XLOOKUP($A11&$B11,'[1]产值及收款计划（2026）'!$A:$A&'[1]产值及收款计划（2026）'!$B:$B,'[1]产值及收款计划（2026）'!R:R)} -> 0 | S11: {=_xlfn.XLOOKUP($A11&$B11,'[1]产值及收款计划（2026）'!$A:$A&'[1]产值及收款计划（2026）'!$B:$B,'[1]产值及收款计划（2026）'!S:S)} -> 0 | T11: {=_xlfn.XLOOKUP($A11&$B11,'[1]产值及收款计划（2026）'!$A:$A&'[1]产值及收款计划（2026）'!$B:$B,'[1]产值及收款计划（2026）'!T:T)} -> 15.6584 | U11: {=_xlfn.XLOOKUP($A11&$B11,'[1]产值及收款计划（2026）'!$A:$A&'[1]产值及收款计划（2026）'!$B:$B,'[1]产值及收款计划（2026）'!U:U)} -> 0 | V11: {=_xlfn.XLOOKUP($A11&$B11,'[1]产值及收款计划（2026）'!$A:$A&'[1]产值及收款计划（2026）'!$B:$B,'[1]产值及收款计划（2026）'!V:V)} -> 0 | W11: {=_xlfn.XLOOKUP($A11&$B11,'[1]产值及收款计划（2026）'!$A:$A&'[1]产值及收款计划（2026）'!$B:$B,'[1]产值及收款计划（2026）'!W:W)} -> 0 | X11: {=_xlfn.XLOOKUP($A11&$B11,'[1]产值及收款计划（2026）'!$A:$A&'[1]产值及收款计划（2026）'!$B:$B,'[1]产值及收款计划（2026）'!X:X)} -> 0 | Y11: {=_xlfn.XLOOKUP($A11&$B11,'[1]产值及收款计划（2026）'!$A:$A&'[1]产值及收款计划（2026）'!$B:$B,'[1]产值及收款计划（2026）'!Y:Y)} -> 0 | Z11: {=_xlfn.XLOOKUP($A11&$B11,'[1]产值及收款计划（2026）'!$A:$A&'[1]产值及收款计划（2026）'!$B:$B,'[1]产值及收款计划（2026）'!Z:Z)} -> 0 | AA11: {=_xlfn.XLOOKUP($A11&$B11,'[1]产值及收款计划（2026）'!$A:$A&'[1]产值及收款计划（2026）'!$B:$B,'[1]产值及收款计划（2026）'!AA:AA)} -> 0 | AB11: {=_xlfn.XLOOKUP($A11&$B11,'[1]产值及收款计划（2026）'!$A:$A&'[1]产值及收款计划（2026）'!$B:$B,'[1]产值及收款计划（2026）'!AB:AB)} -> 0 | AC11: {=_xlfn.XLOOKUP($A11&$B11,'[1]产值及收款计划（2026）'!$A:$A&'[1]产值及收款计划（2026）'!$B:$B,'[1]产值及收款计划（2026）'!AC:AC)} -> 0 | AD11: {=_xlfn.XLOOKUP($A11&$B11,'[1]产值及收款计划（2026）'!$A:$A&'[1]产值及收款计划（2026）'!$B:$B,'[1]产值及收款计划（2026）'!AD:AD)} -> 0 | AE11: {=_xlfn.XLOOKUP($A11&$B11,'[1]产值及收款计划（2026）'!$A:$A&'[1]产值及收款计划（2026）'!$B:$B,'[1]产值及收款计划（2026）'!AE:AE)} -> 0 | AF11: {=_xlfn.XLOOKUP($A11&$B11,'[1]产值及收款计划（2026）'!$A:$A&'[1]产值及收款计划（2026）'!$B:$B,'[1]产值及收款计划（2026）'!AF:AF)} -> 0 | AG11: {=_xlfn.XLOOKUP($A11&$B11,'[1]产值及收款计划（2026）'!$A:$A&'[1]产值及收款计划（2026）'!$B:$B,'[1]产值及收款计划（2026）'!AG:AG)} -> 0 | AH11: {=_xlfn.XLOOKUP($A11&$B11,'[1]产值及收款计划（2026）'!$A:$A&'[1]产值及收款计划（2026）'!$B:$B,'[1]产值及收款计划（2026）'!AH:AH)} -> 0 | AI11: {=_xlfn.XLOOKUP($A11&$B11,'[1]产值及收款计划（2026）'!$A:$A&'[1]产值及收款计划（2026）'!$B:$B,'[1]产值及收款计划（2026）'!AI:AI)} -> 0 | AJ11: {=_xlfn.XLOOKUP($A11&$B11,'[1]产值及收款计划（2026）'!$A:$A&'[1]产值及收款计划（2026）'!$B:$B,'[1]产值及收款计划（2026）'!AJ:AJ)} -> 0 | AK11: {=_xlfn.XLOOKUP($A11&$B11,'[1]产值及收款计划（2026）'!$A:$A&'[1]产值及收款计划（2026）'!$B:$B,'[1]产值及收款计划（2026）'!AK:AK)} -> 0 | AL11: {=_xlfn.XLOOKUP($A11&$B11,'[1]产值及收款计划（2026）'!$A:$A&'[1]产值及收款计划（2026）'!$B:$B,'[1]产值及收款计划（2026）'!AL:AL)} -> 0 | AM11: {=_xlfn.LET(_xlpm.勾选月份状态数组,TRANSPOSE('PPT(12-15页）-TOP10'!$A$3:$A$14),_xlpm.选择数据区,IF('PPT(12-15页）-TOP10'!$E$3="收款",$BA11:$BL11,$AA11:$AL11),SUM(_xlfn._xlws.FILTER(_xlpm.选择数据区,_xlpm.勾选月份状态数组,"")))} -> #NAME? | AN11: {=_xlfn.LET(_xlpm.勾选月份状态数组,TRANSPOSE('PPT(12-15页）-TOP10'!$A$3:$A$14),_xlpm.选择数据区,IF('PPT(12-15页）-TOP10'!$E$3="收款",$DA11:$DL11,$CA11:$CL11),SUM(_xlfn._xlws.FILTER(_xlpm.选择数据区,_xlpm.勾选月份状态数组,"")))} -> #NAME? | AO11: =SUM(CA11:CC11)+SUM(AD11:AL11) -> 0 | AS11: {=_xlfn.XLOOKUP($A11&$B11,'[1]产值及收款计划（2026）'!$A:$A&'[1]产值及收款计划（2026）'!$B:$B,'[1]产值及收款计划（2026）'!AS:AS)} -> 0 | AT11: {=_xlfn.XLOOKUP($A11&$B11,'[1]产值及收款计划（2026）'!$A:$A&'[1]产值及收款计划（2026）'!$B:$B,'[1]产值及收款计划（2026）'!AT:AT)} -> 0 | AU11: {=_xlfn.XLOOKUP($A11&$B11,'[1]产值及收款计划（2026）'!$A:$A&'[1]产值及收款计划（2026）'!$B:$B,'[1]产值及收款计划（2026）'!AU:AU)} -> 0 | AV11: {=_xlfn.XLOOKUP($A11&$B11,'[1]产值及收款计划（2026）'!$A:$A&'[1]产值及收款计划（2026）'!$B:$B,'[1]产值及收款计划（2026）'!AV:AV)} -> 0 | AW11: {=_xlfn.XLOOKUP($A11&$B11,'[1]产值及收款计划（2026）'!$A:$A&'[1]产值及收款计划（2026）'!$B:$B,'[1]产值及收款计划（2026）'!AW:AW)} -> 0 | AX11: {=_xlfn.XLOOKUP($A11&$B11,'[1]产值及收款计划（2026）'!$A:$A&'[1]产值及收款计划（2026）'!$B:$B,'[1]产值及收款计划（2026）'!AX:AX)} -> 4.420148 | AY11: {=_xlfn.XLOOKUP($A11&$B11,'[1]产值及收款计划（2026）'!$A:$A&'[1]产值及收款计划（2026）'!$B:$B,'[1]产值及收款计划（2026）'!AY:AY)} -> 11.238252 | AZ11: {=_xlfn.XLOOKUP($A11&$B11,'[1]产值及收款计划（2026）'!$A:$A&'[1]产值及收款计划（2026）'!$B:$B,'[1]产值及收款计划（2026）'!AZ:AZ)} -> 11.238252 | BA11: {=_xlfn.XLOOKUP($A11&$B11,'[1]产值及收款计划（2026）'!$A:$A&'[1]产值及收款计划（2026）'!$B:$B,'[1]产值及收款计划（2026）'!BA:BA)} -> 0 | BB11: {=_xlfn.XLOOKUP($A11&$B11,'[1]产值及收款计划（2026）'!$A:$A&'[1]产值及收款计划（2026）'!$B:$B,'[1]产值及收款计划（2026）'!BB:BB)} -> 0 | BC11: {=_xlfn.XLOOKUP($A11&$B11,'[1]产值及收款计划（2026）'!$A:$A&'[1]产值及收款计划（2026）'!$B:$B,'[1]产值及收款计划（2026）'!BC:BC)} -> 0 | BD11: {=_xlfn.XLOOKUP($A11&$B11,'[1]产值及收款计划（2026）'!$A:$A&'[1]产值及收款计划（2026）'!$B:$B,'[1]产值及收款计划（2026）'!BD:BD)} -> 0 | BE11: {=_xlfn.XLOOKUP($A11&$B11,'[1]产值及收款计划（2026）'!$A:$A&'[1]产值及收款计划（2026）'!$B:$B,'[1]产值及收款计划（2026）'!BE:BE)} -> 0 | BF11: {=_xlfn.XLOOKUP($A11&$B11,'[1]产值及收款计划（2026）'!$A:$A&'[1]产值及收款计划（2026）'!$B:$B,'[1]产值及收款计划（2026）'!BF:BF)} -> 0 | BG11: {=_xlfn.XLOOKUP($A11&$B11,'[1]产值及收款计划（2026）'!$A:$A&'[1]产值及收款计划（2026）'!$B:$B,'[1]产值及收款计划（2026）'!BG:BG)} -> 0 | BH11: {=_xlfn.XLOOKUP($A11&$B11,'[1]产值及收款计划（2026）'!$A:$A&'[1]产值及收款计划（2026）'!$B:$B,'[1]产值及收款计划（2026）'!BH:BH)} -> 0 | BI11: {=_xlfn.XLOOKUP($A11&$B11,'[1]产值及收款计划（2026）'!$A:$A&'[1]产值及收款计划（2026）'!$B:$B,'[1]产值及收款计划（2026）'!BI:BI)} -> 0 | BJ11: {=_xlfn.XLOOKUP($A11&$B11,'[1]产值及收款计划（2026）'!$A:$A&'[1]产值及收款计划（2026）'!$B:$B,'[1]产值及收款计划（2026）'!BJ:BJ)} -> 0 | BK11: {=_xlfn.XLOOKUP($A11&$B11,'[1]产值及收款计划（2026）'!$A:$A&'[1]产值及收款计划（2026）'!$B:$B,'[1]产值及收款计划（2026）'!BK:BK)} -> 0 | BL11: {=_xlfn.XLOOKUP($A11&$B11,'[1]产值及收款计划（2026）'!$A:$A&'[1]产值及收款计划（2026）'!$B:$B,'[1]产值及收款计划（2026）'!BL:BL)} -> 0 | BQ11: {=_xlfn.XLOOKUP($A11&$B11,'[1]产值及收款计划（2026）'!$A:$A&'[1]产值及收款计划（2026）'!$B:$B,'[1]产值及收款计划（2026）'!BQ:BQ)} -> 0 | BR11: {=_xlfn.XLOOKUP($A11&$B11,'[1]产值及收款计划（2026）'!$A:$A&'[1]产值及收款计划（2026）'!$B:$B,'[1]产值及收款计划（2026）'!BR:BR)} -> 0 | CA11: {=_xlfn.XLOOKUP($A11&$B11,'[1]产值及收款计划（2026）'!$A:$A&'[1]产值及收款计划（2026）'!$B:$B,'[1]产值及收款计划（2026）'!CA:CA)} -> 0 | CB11: {=_xlfn.XLOOKUP($A11&$B11,'[1]产值及收款计划（2026）'!$A:$A&'[1]产值及收款计划（2026）'!$B:$B,'[1]产值及收款计划（2026）'!CB:CB)} -> 0 | CC11: {=_xlfn.XLOOKUP($A11&$B11,'[1]产值及收款计划（2026）'!$A:$A&'[1]产值及收款计划（2026）'!$B:$B,'[1]产值及收款计划（2026）'!CC:CC)} -> 0 | CD11: {=_xlfn.XLOOKUP($A11&$B11,'[1]产值及收款计划（2026）'!$A:$A&'[1]产值及收款计划（2026）'!$B:$B,'[1]产值及收款计划（2026）'!CD:CD)} -> 0 | CE11: {=_xlfn.XLOOKUP($A11&$B11,'[1]产值及收款计划（2026）'!$A:$A&'[1]产值及收款计划（2026）'!$B:$B,'[1]产值及收款计划（2026）'!CE:CE)} -> 0 | CF11: {=_xlfn.XLOOKUP($A11&$B11,'[1]产值及收款计划（2026）'!$A:$A&'[1]产值及收款计划（2026）'!$B:$B,'[1]产值及收款计划（2026）'!CF:CF)} -> 0 | CG11: {=_xlfn.XLOOKUP($A11&$B11,'[1]产值及收款计划（2026）'!$A:$A&'[1]产值及收款计划（2026）'!$B:$B,'[1]产值及收款计划（2026）'!CG:CG)} -> 0 | CH11: {=_xlfn.XLOOKUP($A11&$B11,'[1]产值及收款计划（2026）'!$A:$A&'[1]产值及收款计划（2026）'!$B:$B,'[1]产值及收款计划（2026）'!CH:CH)} -> 0 | CI11: {=_xlfn.XLOOKUP($A11&$B11,'[1]产值及收款计划（2026）'!$A:$A&'[1]产值及收款计划（2026）'!$B:$B,'[1]产值及收款计划（2026）'!CI:CI)} -> 0 | CJ11: {=_xlfn.XLOOKUP($A11&$B11,'[1]产值及收款计划（2026）'!$A:$A&'[1]产值及收款计划（2026）'!$B:$B,'[1]产值及收款计划（2026）'!CJ:CJ)} -> 0 | CK11: {=_xlfn.XLOOKUP($A11&$B11,'[1]产值及收款计划（2026）'!$A:$A&'[1]产值及收款计划（2026）'!$B:$B,'[1]产值及收款计划（2026）'!CK:CK)} -> 0 | CL11: {=_xlfn.XLOOKUP($A11&$B11,'[1]产值及收款计划（2026）'!$A:$A&'[1]产值及收款计划（2026）'!$B:$B,'[1]产值及收款计划（2026）'!CL:CL)} -> 0 | DA11: {=_xlfn.XLOOKUP($A11&$B11,'[1]产值及收款计划（2026）'!$A:$A&'[1]产值及收款计划（2026）'!$B:$B,'[1]产值及收款计划（2026）'!DA:DA)} -> 0 | DB11: {=_xlfn.XLOOKUP($A11&$B11,'[1]产值及收款计划（2026）'!$A:$A&'[1]产值及收款计划（2026）'!$B:$B,'[1]产值及收款计划（2026）'!DB:DB)} -> 4.420148 | DC11: {=_xlfn.XLOOKUP($A11&$B11,'[1]产值及收款计划（2026）'!$A:$A&'[1]产值及收款计划（2026）'!$B:$B,'[1]产值及收款计划（2026）'!DC:DC)} -> 0 | DD11: {=_xlfn.XLOOKUP($A11&$B11,'[1]产值及收款计划（2026）'!$A:$A&'[1]产值及收款计划（2026）'!$B:$B,'[1]产值及收款计划（2026）'!DD:DD)} -> 0 | DE11: {=_xlfn.XLOOKUP($A11&$B11,'[1]产值及收款计划（2026）'!$A:$A&'[1]产值及收款计划（2026）'!$B:$B,'[1]产值及收款计划（2026）'!DE:DE)} -> 0 | DF11: {=_xlfn.XLOOKUP($A11&$B11,'[1]产值及收款计划（2026）'!$A:$A&'[1]产值及收款计划（2026）'!$B:$B,'[1]产值及收款计划（2026）'!DF:DF)} -> 0 | DG11: {=_xlfn.XLOOKUP($A11&$B11,'[1]产值及收款计划（2026）'!$A:$A&'[1]产值及收款计划（2026）'!$B:$B,'[1]产值及收款计划（2026）'!DG:DG)} -> 0 | DH11: {=_xlfn.XLOOKUP($A11&$B11,'[1]产值及收款计划（2026）'!$A:$A&'[1]产值及收款计划（2026）'!$B:$B,'[1]产值及收款计划（2026）'!DH:DH)} -> 0 | DI11: {=_xlfn.XLOOKUP($A11&$B11,'[1]产值及收款计划（2026）'!$A:$A&'[1]产值及收款计划（2026）'!$B:$B,'[1]产值及收款计划（2026）'!DI:DI)} -> 0 | DJ11: {=_xlfn.XLOOKUP($A11&$B11,'[1]产值及收款计划（2026）'!$A:$A&'[1]产值及收款计划（2026）'!$B:$B,'[1]产值及收款计划（2026）'!DJ:DJ)} -> 0 | DK11: {=_xlfn.XLOOKUP($A11&$B11,'[1]产值及收款计划（2026）'!$A:$A&'[1]产值及收款计划（2026）'!$B:$B,'[1]产值及收款计划（2026）'!DK:DK)} -> 0 | DL11: {=_xlfn.XLOOKUP($A11&$B11,'[1]产值及收款计划（2026）'!$A:$A&'[1]产值及收款计划（2026）'!$B:$B,'[1]产值及收款计划（2026）'!DL:DL)} -> 0
A12: =A11+1 -> 8 | B12: 数字建造中心 | C12: {=_xlfn.XLOOKUP($A12&$B12,'[1]产值及收款计划（2026）'!$A:$A&'[1]产值及收款计划（2026）'!$B:$B,'[1]产值及收款计划（2026）'!C:C)} -> ZHT2021070800080 | D12: {=_xlfn.XLOOKUP($A12&$B12,'[1]产值及收款计划（2026）'!$A:$A&'[1]产值及收款计划（2026）'!$B:$B,'[1]产值及收款计划（2026）'!D:D)} -> 南湖区老（旧）住宅区改造提升专项工程（二期）第二批次设计采购施工总承包(EPC)项目施工阶段的BIM应用技术 | E12: {=_xlfn.XLOOKUP($A12&$B12,'[1]产值及收款计划（2026）'!$A:$A&'[1]产值及收款计划（2026）'!$B:$B,'[1]产值及收款计划（2026）'!E:E)} -> 255.8 | F12: {=_xlfn.XLOOKUP($A12&$B12,'[1]产值及收款计划（2026）'!$A:$A&'[1]产值及收款计划（2026）'!$B:$B,'[1]产值及收款计划（2026）'!F:F)} -> 255.8 | G12: {=_xlfn.XLOOKUP($A12&$B12,'[1]产值及收款计划（2026）'!$A:$A&'[1]产值及收款计划（2026）'!$B:$B,'[1]产值及收款计划（2026）'!G:G)} -> 0 | H12: {=_xlfn.XLOOKUP($A12&$B12,'[1]产值及收款计划（2026）'!$A:$A&'[1]产值及收款计划（2026）'!$B:$B,'[1]产值及收款计划（2026）'!H:H)} -> 215.48 | I12: {=_xlfn.XLOOKUP($A12&$B12,'[1]产值及收款计划（2026）'!$A:$A&'[1]产值及收款计划（2026）'!$B:$B,'[1]产值及收款计划（2026）'!I:I)} -> 0.84237686 | J12: {=_xlfn.XLOOKUP($A12&$B12,'[1]产值及收款计划（2026）'!$A:$A&'[1]产值及收款计划（2026）'!$B:$B,'[1]产值及收款计划（2026）'!J:J)} -> 0.06 | K12: {=_xlfn.XLOOKUP($A12&$B12,'[1]产值及收款计划（2026）'!$A:$A&'[1]产值及收款计划（2026）'!$B:$B,'[1]产值及收款计划（2026）'!K:K)} -> 0 | L12: {=_xlfn.XLOOKUP($A12&$B12,'[1]产值及收款计划（2026）'!$A:$A&'[1]产值及收款计划（2026）'!$B:$B,'[1]产值及收款计划（2026）'!L:L)} -> 0 | M12: {=_xlfn.XLOOKUP($A12&$B12,'[1]产值及收款计划（2026）'!$A:$A&'[1]产值及收款计划（2026）'!$B:$B,'[1]产值及收款计划（2026）'!M:M)} -> 主导 | N12: {=_xlfn.XLOOKUP($A12&$B12,'[1]产值及收款计划（2026）'!$A:$A&'[1]产值及收款计划（2026）'!$B:$B,'[1]产值及收款计划（2026）'!N:N)} -> 孔祥平团队 | O12: {=_xlfn.XLOOKUP($A12&$B12,'[1]产值及收款计划（2026）'!$A:$A&'[1]产值及收款计划（2026）'!$B:$B,'[1]产值及收款计划（2026）'!O:O)} -> 卜宝翔 | P12: {=_xlfn.XLOOKUP($A12&$B12,'[1]产值及收款计划（2026）'!$A:$A&'[1]产值及收款计划（2026）'!$B:$B,'[1]产值及收款计划（2026）'!P:P)} -> 过往已完结 | Q12: {=_xlfn.XLOOKUP($A12&$B12,'[1]产值及收款计划（2026）'!$A:$A&'[1]产值及收款计划（2026）'!$B:$B,'[1]产值及收款计划（2026）'!Q:Q)} -> 0 | R12: {=_xlfn.XLOOKUP($A12&$B12,'[1]产值及收款计划（2026）'!$A:$A&'[1]产值及收款计划（2026）'!$B:$B,'[1]产值及收款计划（2026）'!R:R)} -> 0 | S12: {=_xlfn.XLOOKUP($A12&$B12,'[1]产值及收款计划（2026）'!$A:$A&'[1]产值及收款计划（2026）'!$B:$B,'[1]产值及收款计划（2026）'!S:S)} -> 0 | T12: {=_xlfn.XLOOKUP($A12&$B12,'[1]产值及收款计划（2026）'!$A:$A&'[1]产值及收款计划（2026）'!$B:$B,'[1]产值及收款计划（2026）'!T:T)} -> 255.8 | U12: {=_xlfn.XLOOKUP($A12&$B12,'[1]产值及收款计划（2026）'!$A:$A&'[1]产值及收款计划（2026）'!$B:$B,'[1]产值及收款计划（2026）'!U:U)} -> 0 | V12: {=_xlfn.XLOOKUP($A12&$B12,'[1]产值及收款计划（2026）'!$A:$A&'[1]产值及收款计划（2026）'!$B:$B,'[1]产值及收款计划（2026）'!V:V)} -> 0 | W12: {=_xlfn.XLOOKUP($A12&$B12,'[1]产值及收款计划（2026）'!$A:$A&'[1]产值及收款计划（2026）'!$B:$B,'[1]产值及收款计划（2026）'!W:W)} -> 0 | X12: {=_xlfn.XLOOKUP($A12&$B12,'[1]产值及收款计划（2026）'!$A:$A&'[1]产值及收款计划（2026）'!$B:$B,'[1]产值及收款计划（2026）'!X:X)} -> 0 | Y12: {=_xlfn.XLOOKUP($A12&$B12,'[1]产值及收款计划（2026）'!$A:$A&'[1]产值及收款计划（2026）'!$B:$B,'[1]产值及收款计划（2026）'!Y:Y)} -> 0 | Z12: {=_xlfn.XLOOKUP($A12&$B12,'[1]产值及收款计划（2026）'!$A:$A&'[1]产值及收款计划（2026）'!$B:$B,'[1]产值及收款计划（2026）'!Z:Z)} -> 0 | AA12: {=_xlfn.XLOOKUP($A12&$B12,'[1]产值及收款计划（2026）'!$A:$A&'[1]产值及收款计划（2026）'!$B:$B,'[1]产值及收款计划（2026）'!AA:AA)} -> 0 | AB12: {=_xlfn.XLOOKUP($A12&$B12,'[1]产值及收款计划（2026）'!$A:$A&'[1]产值及收款计划（2026）'!$B:$B,'[1]产值及收款计划（2026）'!AB:AB)} -> 0 | AC12: {=_xlfn.XLOOKUP($A12&$B12,'[1]产值及收款计划（2026）'!$A:$A&'[1]产值及收款计划（2026）'!$B:$B,'[1]产值及收款计划（2026）'!AC:AC)} -> 0 | AD12: {=_xlfn.XLOOKUP($A12&$B12,'[1]产值及收款计划（2026）'!$A:$A&'[1]产值及收款计划（2026）'!$B:$B,'[1]产值及收款计划（2026）'!AD:AD)} -> 0 | AE12: {=_xlfn.XLOOKUP($A12&$B12,'[1]产值及收款计划（2026）'!$A:$A&'[1]产值及收款计划（2026）'!$B:$B,'[1]产值及收款计划（2026）'!AE:AE)} -> 0 | AF12: {=_xlfn.XLOOKUP($A12&$B12,'[1]产值及收款计划（2026）'!$A:$A&'[1]产值及收款计划（2026）'!$B:$B,'[1]产值及收款计划（2026）'!AF:AF)} -> 0 | AG12: {=_xlfn.XLOOKUP($A12&$B12,'[1]产值及收款计划（2026）'!$A:$A&'[1]产值及收款计划（2026）'!$B:$B,'[1]产值及收款计划（2026）'!AG:AG)} -> 0 | AH12: {=_xlfn.XLOOKUP($A12&$B12,'[1]产值及收款计划（2026）'!$A:$A&'[1]产值及收款计划（2026）'!$B:$B,'[1]产值及收款计划（2026）'!AH:AH)} -> 0 | AI12: {=_xlfn.XLOOKUP($A12&$B12,'[1]产值及收款计划（2026）'!$A:$A&'[1]产值及收款计划（2026）'!$B:$B,'[1]产值及收款计划（2026）'!AI:AI)} -> 0 | AJ12: {=_xlfn.XLOOKUP($A12&$B12,'[1]产值及收款计划（2026）'!$A:$A&'[1]产值及收款计划（2026）'!$B:$B,'[1]产值及收款计划（2026）'!AJ:AJ)} -> 0 | AK12: {=_xlfn.XLOOKUP($A12&$B12,'[1]产值及收款计划（2026）'!$A:$A&'[1]产值及收款计划（2026）'!$B:$B,'[1]产值及收款计划（2026）'!AK:AK)} -> 0 | AL12: {=_xlfn.XLOOKUP($A12&$B12,'[1]产值及收款计划（2026）'!$A:$A&'[1]产值及收款计划（2026）'!$B:$B,'[1]产值及收款计划（2026）'!AL:AL)} -> 0 | AM12: {=_xlfn.LET(_xlpm.勾选月份状态数组,TRANSPOSE('PPT(12-15页）-TOP10'!$A$3:$A$14),_xlpm.选择数据区,IF('PPT(12-15页）-TOP10'!$E$3="收款",$BA12:$BL12,$AA12:$AL12),SUM(_xlfn._xlws.FILTER(_xlpm.选择数据区,_xlpm.勾选月份状态数组,"")))} -> #NAME? | AN12: {=_xlfn.LET(_xlpm.勾选月份状态数组,TRANSPOSE('PPT(12-15页）-TOP10'!$A$3:$A$14),_xlpm.选择数据区,IF('PPT(12-15页）-TOP10'!$E$3="收款",$DA12:$DL12,$CA12:$CL12),SUM(_xlfn._xlws.FILTER(_xlpm.选择数据区,_xlpm.勾选月份状态数组,"")))} -> #NAME? | AO12: =SUM(CA12:CC12)+SUM(AD12:AL12) -> 0 | AS12: {=_xlfn.XLOOKUP($A12&$B12,'[1]产值及收款计划（2026）'!$A:$A&'[1]产值及收款计划（2026）'!$B:$B,'[1]产值及收款计划（2026）'!AS:AS)} -> 0 | AT12: {=_xlfn.XLOOKUP($A12&$B12,'[1]产值及收款计划（2026）'!$A:$A&'[1]产值及收款计划（2026）'!$B:$B,'[1]产值及收款计划（2026）'!AT:AT)} -> 0 | AU12: {=_xlfn.XLOOKUP($A12&$B12,'[1]产值及收款计划（2026）'!$A:$A&'[1]产值及收款计划（2026）'!$B:$B,'[1]产值及收款计划（2026）'!AU:AU)} -> 0 | AV12: {=_xlfn.XLOOKUP($A12&$B12,'[1]产值及收款计划（2026）'!$A:$A&'[1]产值及收款计划（2026）'!$B:$B,'[1]产值及收款计划（2026）'!AV:AV)} -> 0 | AW12: {=_xlfn.XLOOKUP($A12&$B12,'[1]产值及收款计划（2026）'!$A:$A&'[1]产值及收款计划（2026）'!$B:$B,'[1]产值及收款计划（2026）'!AW:AW)} -> 153.48 | AX12: {=_xlfn.XLOOKUP($A12&$B12,'[1]产值及收款计划（2026）'!$A:$A&'[1]产值及收款计划（2026）'!$B:$B,'[1]产值及收款计划（2026）'!AX:AX)} -> 0 | AY12: {=_xlfn.XLOOKUP($A12&$B12,'[1]产值及收款计划（2026）'!$A:$A&'[1]产值及收款计划（2026）'!$B:$B,'[1]产值及收款计划（2026）'!AY:AY)} -> 102.32 | AZ12: {=_xlfn.XLOOKUP($A12&$B12,'[1]产值及收款计划（2026）'!$A:$A&'[1]产值及收款计划（2026）'!$B:$B,'[1]产值及收款计划（2026）'!AZ:AZ)} -> 102.32 | BA12: {=_xlfn.XLOOKUP($A12&$B12,'[1]产值及收款计划（2026）'!$A:$A&'[1]产值及收款计划（2026）'!$B:$B,'[1]产值及收款计划（2026）'!BA:BA)} -> 0 | BB12: {=_xlfn.XLOOKUP($A12&$B12,'[1]产值及收款计划（2026）'!$A:$A&'[1]产值及收款计划（2026）'!$B:$B,'[1]产值及收款计划（2026）'!BB:BB)} -> 0 | BC12: {=_xlfn.XLOOKUP($A12&$B12,'[1]产值及收款计划（2026）'!$A:$A&'[1]产值及收款计划（2026）'!$B:$B,'[1]产值及收款计划（2026）'!BC:BC)} -> 0 | BD12: {=_xlfn.XLOOKUP($A12&$B12,'[1]产值及收款计划（2026）'!$A:$A&'[1]产值及收款计划（2026）'!$B:$B,'[1]产值及收款计划（2026）'!BD:BD)} -> 0 | BE12: {=_xlfn.XLOOKUP($A12&$B12,'[1]产值及收款计划（2026）'!$A:$A&'[1]产值及收款计划（2026）'!$B:$B,'[1]产值及收款计划（2026）'!BE:BE)} -> 0 | BF12: {=_xlfn.XLOOKUP($A12&$B12,'[1]产值及收款计划（2026）'!$A:$A&'[1]产值及收款计划（2026）'!$B:$B,'[1]产值及收款计划（2026）'!BF:BF)} -> 0 | BG12: {=_xlfn.XLOOKUP($A12&$B12,'[1]产值及收款计划（2026）'!$A:$A&'[1]产值及收款计划（2026）'!$B:$B,'[1]产值及收款计划（2026）'!BG:BG)} -> 0 | BH12: {=_xlfn.XLOOKUP($A12&$B12,'[1]产值及收款计划（2026）'!$A:$A&'[1]产值及收款计划（2026）'!$B:$B,'[1]产值及收款计划（2026）'!BH:BH)} -> 0 | BI12: {=_xlfn.XLOOKUP($A12&$B12,'[1]产值及收款计划（2026）'!$A:$A&'[1]产值及收款计划（2026）'!$B:$B,'[1]产值及收款计划（2026）'!BI:BI)} -> 0 | BJ12: {=_xlfn.XLOOKUP($A12&$B12,'[1]产值及收款计划（2026）'!$A:$A&'[1]产值及收款计划（2026）'!$B:$B,'[1]产值及收款计划（2026）'!BJ:BJ)} -> 0 | BK12: {=_xlfn.XLOOKUP($A12&$B12,'[1]产值及收款计划（2026）'!$A:$A&'[1]产值及收款计划（2026）'!$B:$B,'[1]产值及收款计划（2026）'!BK:BK)} -> 0 | BL12: {=_xlfn.XLOOKUP($A12&$B12,'[1]产值及收款计划（2026）'!$A:$A&'[1]产值及收款计划（2026）'!$B:$B,'[1]产值及收款计划（2026）'!BL:BL)} -> 0 | BQ12: {=_xlfn.XLOOKUP($A12&$B12,'[1]产值及收款计划（2026）'!$A:$A&'[1]产值及收款计划（2026）'!$B:$B,'[1]产值及收款计划（2026）'!BQ:BQ)} -> 0 | BR12: {=_xlfn.XLOOKUP($A12&$B12,'[1]产值及收款计划（2026）'!$A:$A&'[1]产值及收款计划（2026）'!$B:$B,'[1]产值及收款计划（2026）'!BR:BR)} -> 0 | CA12: {=_xlfn.XLOOKUP($A12&$B12,'[1]产值及收款计划（2026）'!$A:$A&'[1]产值及收款计划（2026）'!$B:$B,'[1]产值及收款计划（2026）'!CA:CA)} -> 0 | CB12: {=_xlfn.XLOOKUP($A12&$B12,'[1]产值及收款计划（2026）'!$A:$A&'[1]产值及收款计划（2026）'!$B:$B,'[1]产值及收款计划（2026）'!CB:CB)} -> 0 | CC12: {=_xlfn.XLOOKUP($A12&$B12,'[1]产值及收款计划（2026）'!$A:$A&'[1]产值及收款计划（2026）'!$B:$B,'[1]产值及收款计划（2026）'!CC:CC)} -> 0 | CD12: {=_xlfn.XLOOKUP($A12&$B12,'[1]产值及收款计划（2026）'!$A:$A&'[1]产值及收款计划（2026）'!$B:$B,'[1]产值及收款计划（2026）'!CD:CD)} -> 0 | CE12: {=_xlfn.XLOOKUP($A12&$B12,'[1]产值及收款计划（2026）'!$A:$A&'[1]产值及收款计划（2026）'!$B:$B,'[1]产值及收款计划（2026）'!CE:CE)} -> 0 | CF12: {=_xlfn.XLOOKUP($A12&$B12,'[1]产值及收款计划（2026）'!$A:$A&'[1]产值及收款计划（2026）'!$B:$B,'[1]产值及收款计划（2026）'!CF:CF)} -> 0 | CG12: {=_xlfn.XLOOKUP($A12&$B12,'[1]产值及收款计划（2026）'!$A:$A&'[1]产值及收款计划（2026）'!$B:$B,'[1]产值及收款计划（2026）'!CG:CG)} -> 0 | CH12: {=_xlfn.XLOOKUP($A12&$B12,'[1]产值及收款计划（2026）'!$A:$A&'[1]产值及收款计划（2026）'!$B:$B,'[1]产值及收款计划（2026）'!CH:CH)} -> 0 | CI12: {=_xlfn.XLOOKUP($A12&$B12,'[1]产值及收款计划（2026）'!$A:$A&'[1]产值及收款计划（2026）'!$B:$B,'[1]产值及收款计划（2026）'!CI:CI)} -> 0 | CJ12: {=_xlfn.XLOOKUP($A12&$B12,'[1]产值及收款计划（2026）'!$A:$A&'[1]产值及收款计划（2026）'!$B:$B,'[1]产值及收款计划（2026）'!CJ:CJ)} -> 0 | CK12: {=_xlfn.XLOOKUP($A12&$B12,'[1]产值及收款计划（2026）'!$A:$A&'[1]产值及收款计划（2026）'!$B:$B,'[1]产值及收款计划（2026）'!CK:CK)} -> 0 | CL12: {=_xlfn.XLOOKUP($A12&$B12,'[1]产值及收款计划（2026）'!$A:$A&'[1]产值及收款计划（2026）'!$B:$B,'[1]产值及收款计划（2026）'!CL:CL)} -> 0 | DA12: {=_xlfn.XLOOKUP($A12&$B12,'[1]产值及收款计划（2026）'!$A:$A&'[1]产值及收款计划（2026）'!$B:$B,'[1]产值及收款计划（2026）'!DA:DA)} -> 0 | DB12: {=_xlfn.XLOOKUP($A12&$B12,'[1]产值及收款计划（2026）'!$A:$A&'[1]产值及收款计划（2026）'!$B:$B,'[1]产值及收款计划（2026）'!DB:DB)} -> 0 | DC12: {=_xlfn.XLOOKUP($A12&$B12,'[1]产值及收款计划（2026）'!$A:$A&'[1]产值及收款计划（2026）'!$B:$B,'[1]产值及收款计划（2026）'!DC:DC)} -> 0 | DD12: {=_xlfn.XLOOKUP($A12&$B12,'[1]产值及收款计划（2026）'!$A:$A&'[1]产值及收款计划（2026）'!$B:$B,'[1]产值及收款计划（2026）'!DD:DD)} -> 0 | DE12: {=_xlfn.XLOOKUP($A12&$B12,'[1]产值及收款计划（2026）'!$A:$A&'[1]产值及收款计划（2026）'!$B:$B,'[1]产值及收款计划（2026）'!DE:DE)} -> 0 | DF12: {=_xlfn.XLOOKUP($A12&$B12,'[1]产值及收款计划（2026）'!$A:$A&'[1]产值及收款计划（2026）'!$B:$B,'[1]产值及收款计划（2026）'!DF:DF)} -> 0 | DG12: {=_xlfn.XLOOKUP($A12&$B12,'[1]产值及收款计划（2026）'!$A:$A&'[1]产值及收款计划（2026）'!$B:$B,'[1]产值及收款计划（2026）'!DG:DG)} -> 0 | DH12: {=_xlfn.XLOOKUP($A12&$B12,'[1]产值及收款计划（2026）'!$A:$A&'[1]产值及收款计划（2026）'!$B:$B,'[1]产值及收款计划（2026）'!DH:DH)} -> 0 | DI12: {=_xlfn.XLOOKUP($A12&$B12,'[1]产值及收款计划（2026）'!$A:$A&'[1]产值及收款计划（2026）'!$B:$B,'[1]产值及收款计划（2026）'!DI:DI)} -> 0 | DJ12: {=_xlfn.XLOOKUP($A12&$B12,'[1]产值及收款计划（2026）'!$A:$A&'[1]产值及收款计划（2026）'!$B:$B,'[1]产值及收款计划（2026）'!DJ:DJ)} -> 0 | DK12: {=_xlfn.XLOOKUP($A12&$B12,'[1]产值及收款计划（2026）'!$A:$A&'[1]产值及收款计划（2026）'!$B:$B,'[1]产值及收款计划（2026）'!DK:DK)} -> 0 | DL12: {=_xlfn.XLOOKUP($A12&$B12,'[1]产值及收款计划（2026）'!$A:$A&'[1]产值及收款计划（2026）'!$B:$B,'[1]产值及收款计划（2026）'!DL:DL)} -> 0
A13: =A12+1 -> 9 | B13: 数字建造中心 | C13: {=_xlfn.XLOOKUP($A13&$B13,'[1]产值及收款计划（2026）'!$A:$A&'[1]产值及收款计划（2026）'!$B:$B,'[1]产值及收款计划（2026）'!C:C)} -> ZHT2021120100139 | D13: {=_xlfn.XLOOKUP($A13&$B13,'[1]产值及收款计划（2026）'!$A:$A&'[1]产值及收款计划（2026）'!$B:$B,'[1]产值及收款计划（2026）'!D:D)} -> 虹桥商务区核心区民防工程BIM运管平台开发技术服务 | E13: {=_xlfn.XLOOKUP($A13&$B13,'[1]产值及收款计划（2026）'!$A:$A&'[1]产值及收款计划（2026）'!$B:$B,'[1]产值及收款计划（2026）'!E:E)} -> 146.04 | F13: {=_xlfn.XLOOKUP($A13&$B13,'[1]产值及收款计划（2026）'!$A:$A&'[1]产值及收款计划（2026）'!$B:$B,'[1]产值及收款计划（2026）'!F:F)} -> 146.04 | G13: {=_xlfn.XLOOKUP($A13&$B13,'[1]产值及收款计划（2026）'!$A:$A&'[1]产值及收款计划（2026）'!$B:$B,'[1]产值及收款计划（2026）'!G:G)} -> 0 | H13: {=_xlfn.XLOOKUP($A13&$B13,'[1]产值及收款计划（2026）'!$A:$A&'[1]产值及收款计划（2026）'!$B:$B,'[1]产值及收款计划（2026）'!H:H)} -> 71.04 | I13: {=_xlfn.XLOOKUP($A13&$B13,'[1]产值及收款计划（2026）'!$A:$A&'[1]产值及收款计划（2026）'!$B:$B,'[1]产值及收款计划（2026）'!I:I)} -> 0.48644207 | J13: {=_xlfn.XLOOKUP($A13&$B13,'[1]产值及收款计划（2026）'!$A:$A&'[1]产值及收款计划（2026）'!$B:$B,'[1]产值及收款计划（2026）'!J:J)} -> 0.06 | K13: {=_xlfn.XLOOKUP($A13&$B13,'[1]产值及收款计划（2026）'!$A:$A&'[1]产值及收款计划（2026）'!$B:$B,'[1]产值及收款计划（2026）'!K:K)} -> 0 | L13: {=_xlfn.XLOOKUP($A13&$B13,'[1]产值及收款计划（2026）'!$A:$A&'[1]产值及收款计划（2026）'!$B:$B,'[1]产值及收款计划（2026）'!L:L)} -> 0 | M13: {=_xlfn.XLOOKUP($A13&$B13,'[1]产值及收款计划（2026）'!$A:$A&'[1]产值及收款计划（2026）'!$B:$B,'[1]产值及收款计划（2026）'!M:M)} -> 主导 | N13: {=_xlfn.XLOOKUP($A13&$B13,'[1]产值及收款计划（2026）'!$A:$A&'[1]产值及收款计划（2026）'!$B:$B,'[1]产值及收款计划（2026）'!N:N)} -> 孔祥平团队 | O13: {=_xlfn.XLOOKUP($A13&$B13,'[1]产值及收款计划（2026）'!$A:$A&'[1]产值及收款计划（2026）'!$B:$B,'[1]产值及收款计划（2026）'!O:O)} -> 孔祥平 | P13: {=_xlfn.XLOOKUP($A13&$B13,'[1]产值及收款计划（2026）'!$A:$A&'[1]产值及收款计划（2026）'!$B:$B,'[1]产值及收款计划（2026）'!P:P)} -> 过往已完结 | Q13: {=_xlfn.XLOOKUP($A13&$B13,'[1]产值及收款计划（2026）'!$A:$A&'[1]产值及收款计划（2026）'!$B:$B,'[1]产值及收款计划（2026）'!Q:Q)} -> 0 | R13: {=_xlfn.XLOOKUP($A13&$B13,'[1]产值及收款计划（2026）'!$A:$A&'[1]产值及收款计划（2026）'!$B:$B,'[1]产值及收款计划（2026）'!R:R)} -> 0 | S13: {=_xlfn.XLOOKUP($A13&$B13,'[1]产值及收款计划（2026）'!$A:$A&'[1]产值及收款计划（2026）'!$B:$B,'[1]产值及收款计划（2026）'!S:S)} -> 0 | T13: {=_xlfn.XLOOKUP($A13&$B13,'[1]产值及收款计划（2026）'!$A:$A&'[1]产值及收款计划（2026）'!$B:$B,'[1]产值及收款计划（2026）'!T:T)} -> 146.04 | U13: {=_xlfn.XLOOKUP($A13&$B13,'[1]产值及收款计划（2026）'!$A:$A&'[1]产值及收款计划（2026）'!$B:$B,'[1]产值及收款计划（2026）'!U:U)} -> 0 | V13: {=_xlfn.XLOOKUP($A13&$B13,'[1]产值及收款计划（2026）'!$A:$A&'[1]产值及收款计划（2026）'!$B:$B,'[1]产值及收款计划（2026）'!V:V)} -> 0 | W13: {=_xlfn.XLOOKUP($A13&$B13,'[1]产值及收款计划（2026）'!$A:$A&'[1]产值及收款计划（2026）'!$B:$B,'[1]产值及收款计划（2026）'!W:W)} -> 0 | X13: {=_xlfn.XLOOKUP($A13&$B13,'[1]产值及收款计划（2026）'!$A:$A&'[1]产值及收款计划（2026）'!$B:$B,'[1]产值及收款计划（2026）'!X:X)} -> 0 | Y13: {=_xlfn.XLOOKUP($A13&$B13,'[1]产值及收款计划（2026）'!$A:$A&'[1]产值及收款计划（2026）'!$B:$B,'[1]产值及收款计划（2026）'!Y:Y)} -> 0 | Z13: {=_xlfn.XLOOKUP($A13&$B13,'[1]产值及收款计划（2026）'!$A:$A&'[1]产值及收款计划（2026）'!$B:$B,'[1]产值及收款计划（2026）'!Z:Z)} -> 0 | AA13: {=_xlfn.XLOOKUP($A13&$B13,'[1]产值及收款计划（2026）'!$A:$A&'[1]产值及收款计划（2026）'!$B:$B,'[1]产值及收款计划（2026）'!AA:AA)} -> 0 | AB13: {=_xlfn.XLOOKUP($A13&$B13,'[1]产值及收款计划（2026）'!$A:$A&'[1]产值及收款计划（2026）'!$B:$B,'[1]产值及收款计划（2026）'!AB:AB)} -> 0 | AC13: {=_xlfn.XLOOKUP($A13&$B13,'[1]产值及收款计划（2026）'!$A:$A&'[1]产值及收款计划（2026）'!$B:$B,'[1]产值及收款计划（2026）'!AC:AC)} -> 0 | AD13: {=_xlfn.XLOOKUP($A13&$B13,'[1]产值及收款计划（2026）'!$A:$A&'[1]产值及收款计划（2026）'!$B:$B,'[1]产值及收款计划（2026）'!AD:AD)} -> 0 | AE13: {=_xlfn.XLOOKUP($A13&$B13,'[1]产值及收款计划（2026）'!$A:$A&'[1]产值及收款计划（2026）'!$B:$B,'[1]产值及收款计划（2026）'!AE:AE)} -> 0 | AF13: {=_xlfn.XLOOKUP($A13&$B13,'[1]产值及收款计划（2026）'!$A:$A&'[1]产值及收款计划（2026）'!$B:$B,'[1]产值及收款计划（2026）'!AF:AF)} -> 0 | AG13: {=_xlfn.XLOOKUP($A13&$B13,'[1]产值及收款计划（2026）'!$A:$A&'[1]产值及收款计划（2026）'!$B:$B,'[1]产值及收款计划（2026）'!AG:AG)} -> 0 | AH13: {=_xlfn.XLOOKUP($A13&$B13,'[1]产值及收款计划（2026）'!$A:$A&'[1]产值及收款计划（2026）'!$B:$B,'[1]产值及收款计划（2026）'!AH:AH)} -> 0 | AI13: {=_xlfn.XLOOKUP($A13&$B13,'[1]产值及收款计划（2026）'!$A:$A&'[1]产值及收款计划（2026）'!$B:$B,'[1]产值及收款计划（2026）'!AI:AI)} -> 0 | AJ13: {=_xlfn.XLOOKUP($A13&$B13,'[1]产值及收款计划（2026）'!$A:$A&'[1]产值及收款计划（2026）'!$B:$B,'[1]产值及收款计划（2026）'!AJ:AJ)} -> 0 | AK13: {=_xlfn.XLOOKUP($A13&$B13,'[1]产值及收款计划（2026）'!$A:$A&'[1]产值及收款计划（2026）'!$B:$B,'[1]产值及收款计划（2026）'!AK:AK)} -> 0 | AL13: {=_xlfn.XLOOKUP($A13&$B13,'[1]产值及收款计划（2026）'!$A:$A&'[1]产值及收款计划（2026）'!$B:$B,'[1]产值及收款计划（2026）'!AL:AL)} -> 0 | AM13: {=_xlfn.LET(_xlpm.勾选月份状态数组,TRANSPOSE('PPT(12-15页）-TOP10'!$A$3:$A$14),_xlpm.选择数据区,IF('PPT(12-15页）-TOP10'!$E$3="收款",$BA13:$BL13,$AA13:$AL13),SUM(_xlfn._xlws.FILTER(_xlpm.选择数据区,_xlpm.勾选月份状态数组,"")))} -> #NAME? | AN13: {=_xlfn.LET(_xlpm.勾选月份状态数组,TRANSPOSE('PPT(12-15页）-TOP10'!$A$3:$A$14),_xlpm.选择数据区,IF('PPT(12-15页）-TOP10'!$E$3="收款",$DA13:$DL13,$CA13:$CL13),SUM(_xlfn._xlws.FILTER(_xlpm.选择数据区,_xlpm.勾选月份状态数组,"")))} -> #NAME? | AO13: =SUM(CA13:CC13)+SUM(AD13:AL13) -> 0 | AS13: {=_xlfn.XLOOKUP($A13&$B13,'[1]产值及收款计划（2026）'!$A:$A&'[1]产值及收款计划（2026）'!$B:$B,'[1]产值及收款计划（2026）'!AS:AS)} -> 0 | AT13: {=_xlfn.XLOOKUP($A13&$B13,'[1]产值及收款计划（2026）'!$A:$A&'[1]产值及收款计划（2026）'!$B:$B,'[1]产值及收款计划（2026）'!AT:AT)} -> 0 | AU13: {=_xlfn.XLOOKUP($A13&$B13,'[1]产值及收款计划（2026）'!$A:$A&'[1]产值及收款计划（2026）'!$B:$B,'[1]产值及收款计划（2026）'!AU:AU)} -> 0 | AV13: {=_xlfn.XLOOKUP($A13&$B13,'[1]产值及收款计划（2026）'!$A:$A&'[1]产值及收款计划（2026）'!$B:$B,'[1]产值及收款计划（2026）'!AV:AV)} -> 0 | AW13: {=_xlfn.XLOOKUP($A13&$B13,'[1]产值及收款计划（2026）'!$A:$A&'[1]产值及收款计划（2026）'!$B:$B,'[1]产值及收款计划（2026）'!AW:AW)} -> 0 | AX13: {=_xlfn.XLOOKUP($A13&$B13,'[1]产值及收款计划（2026）'!$A:$A&'[1]产值及收款计划（2026）'!$B:$B,'[1]产值及收款计划（2026）'!AX:AX)} -> 0 | AY13: {=_xlfn.XLOOKUP($A13&$B13,'[1]产值及收款计划（2026）'!$A:$A&'[1]产值及收款计划（2026）'!$B:$B,'[1]产值及收款计划（2026）'!AY:AY)} -> 146.04 | AZ13: {=_xlfn.XLOOKUP($A13&$B13,'[1]产值及收款计划（2026）'!$A:$A&'[1]产值及收款计划（2026）'!$B:$B,'[1]产值及收款计划（2026）'!AZ:AZ)} -> 146.04 | BA13: {=_xlfn.XLOOKUP($A13&$B13,'[1]产值及收款计划（2026）'!$A:$A&'[1]产值及收款计划（2026）'!$B:$B,'[1]产值及收款计划（2026）'!BA:BA)} -> 0 | BB13: {=_xlfn.XLOOKUP($A13&$B13,'[1]产值及收款计划（2026）'!$A:$A&'[1]产值及收款计划（2026）'!$B:$B,'[1]产值及收款计划（2026）'!BB:BB)} -> 110 | BC13: {=_xlfn.XLOOKUP($A13&$B13,'[1]产值及收款计划（2026）'!$A:$A&'[1]产值及收款计划（2026）'!$B:$B,'[1]产值及收款计划（2026）'!BC:BC)} -> 0 | BD13: {=_xlfn.XLOOKUP($A13&$B13,'[1]产值及收款计划（2026）'!$A:$A&'[1]产值及收款计划（2026）'!$B:$B,'[1]产值及收款计划（2026）'!BD:BD)} -> 0 | BE13: {=_xlfn.XLOOKUP($A13&$B13,'[1]产值及收款计划（2026）'!$A:$A&'[1]产值及收款计划（2026）'!$B:$B,'[1]产值及收款计划（2026）'!BE:BE)} -> 0 | BF13: {=_xlfn.XLOOKUP($A13&$B13,'[1]产值及收款计划（2026）'!$A:$A&'[1]产值及收款计划（2026）'!$B:$B,'[1]产值及收款计划（2026）'!BF:BF)} -> 0 | BG13: {=_xlfn.XLOOKUP($A13&$B13,'[1]产值及收款计划（2026）'!$A:$A&'[1]产值及收款计划（2026）'!$B:$B,'[1]产值及收款计划（2026）'!BG:BG)} -> 0 | BH13: {=_xlfn.XLOOKUP($A13&$B13,'[1]产值及收款计划（2026）'!$A:$A&'[1]产值及收款计划（2026）'!$B:$B,'[1]产值及收款计划（2026）'!BH:BH)} -> 0 | BI13: {=_xlfn.XLOOKUP($A13&$B13,'[1]产值及收款计划（2026）'!$A:$A&'[1]产值及收款计划（2026）'!$B:$B,'[1]产值及收款计划（2026）'!BI:BI)} -> 0 | BJ13: {=_xlfn.XLOOKUP($A13&$B13,'[1]产值及收款计划（2026）'!$A:$A&'[1]产值及收款计划（2026）'!$B:$B,'[1]产值及收款计划（2026）'!BJ:BJ)} -> 0 | BK13: {=_xlfn.XLOOKUP($A13&$B13,'[1]产值及收款计划（2026）'!$A:$A&'[1]产值及收款计划（2026）'!$B:$B,'[1]产值及收款计划（2026）'!BK:BK)} -> 0 | BL13: {=_xlfn.XLOOKUP($A13&$B13,'[1]产值及收款计划（2026）'!$A:$A&'[1]产值及收款计划（2026）'!$B:$B,'[1]产值及收款计划（2026）'!BL:BL)} -> 0 | BQ13: {=_xlfn.XLOOKUP($A13&$B13,'[1]产值及收款计划（2026）'!$A:$A&'[1]产值及收款计划（2026）'!$B:$B,'[1]产值及收款计划（2026）'!BQ:BQ)} -> 0 | BR13: {=_xlfn.XLOOKUP($A13&$B13,'[1]产值及收款计划（2026）'!$A:$A&'[1]产值及收款计划（2026）'!$B:$B,'[1]产值及收款计划（2026）'!BR:BR)} -> 0 | CA13: {=_xlfn.XLOOKUP($A13&$B13,'[1]产值及收款计划（2026）'!$A:$A&'[1]产值及收款计划（2026）'!$B:$B,'[1]产值及收款计划（2026）'!CA:CA)} -> 0 | CB13: {=_xlfn.XLOOKUP($A13&$B13,'[1]产值及收款计划（2026）'!$A:$A&'[1]产值及收款计划（2026）'!$B:$B,'[1]产值及收款计划（2026）'!CB:CB)} -> 0 | CC13: {=_xlfn.XLOOKUP($A13&$B13,'[1]产值及收款计划（2026）'!$A:$A&'[1]产值及收款计划（2026）'!$B:$B,'[1]产值及收款计划（2026）'!CC:CC)} -> 0 | CD13: {=_xlfn.XLOOKUP($A13&$B13,'[1]产值及收款计划（2026）'!$A:$A&'[1]产值及收款计划（2026）'!$B:$B,'[1]产值及收款计划（2026）'!CD:CD)} -> 0 | CE13: {=_xlfn.XLOOKUP($A13&$B13,'[1]产值及收款计划（2026）'!$A:$A&'[1]产值及收款计划（2026）'!$B:$B,'[1]产值及收款计划（2026）'!CE:CE)} -> 0 | CF13: {=_xlfn.XLOOKUP($A13&$B13,'[1]产值及收款计划（2026）'!$A:$A&'[1]产值及收款计划（2026）'!$B:$B,'[1]产值及收款计划（2026）'!CF:CF)} -> 0 | CG13: {=_xlfn.XLOOKUP($A13&$B13,'[1]产值及收款计划（2026）'!$A:$A&'[1]产值及收款计划（2026）'!$B:$B,'[1]产值及收款计划（2026）'!CG:CG)} -> 0 | CH13: {=_xlfn.XLOOKUP($A13&$B13,'[1]产值及收款计划（2026）'!$A:$A&'[1]产值及收款计划（2026）'!$B:$B,'[1]产值及收款计划（2026）'!CH:CH)} -> 0 | CI13: {=_xlfn.XLOOKUP($A13&$B13,'[1]产值及收款计划（2026）'!$A:$A&'[1]产值及收款计划（2026）'!$B:$B,'[1]产值及收款计划（2026）'!CI:CI)} -> 0 | CJ13: {=_xlfn.XLOOKUP($A13&$B13,'[1]产值及收款计划（2026）'!$A:$A&'[1]产值及收款计划（2026）'!$B:$B,'[1]产值及收款计划（2026）'!CJ:CJ)} -> 0 | CK13: {=_xlfn.XLOOKUP($A13&$B13,'[1]产值及收款计划（2026）'!$A:$A&'[1]产值及收款计划（2026）'!$B:$B,'[1]产值及收款计划（2026）'!CK:CK)} -> 0 | CL13: {=_xlfn.XLOOKUP($A13&$B13,'[1]产值及收款计划（2026）'!$A:$A&'[1]产值及收款计划（2026）'!$B:$B,'[1]产值及收款计划（2026）'!CL:CL)} -> 0 | DA13: {=_xlfn.XLOOKUP($A13&$B13,'[1]产值及收款计划（2026）'!$A:$A&'[1]产值及收款计划（2026）'!$B:$B,'[1]产值及收款计划（2026）'!DA:DA)} -> 0 | DB13: {=_xlfn.XLOOKUP($A13&$B13,'[1]产值及收款计划（2026）'!$A:$A&'[1]产值及收款计划（2026）'!$B:$B,'[1]产值及收款计划（2026）'!DB:DB)} -> 0 | DC13: {=_xlfn.XLOOKUP($A13&$B13,'[1]产值及收款计划（2026）'!$A:$A&'[1]产值及收款计划（2026）'!$B:$B,'[1]产值及收款计划（2026）'!DC:DC)} -> 0 | DD13: {=_xlfn.XLOOKUP($A13&$B13,'[1]产值及收款计划（2026）'!$A:$A&'[1]产值及收款计划（2026）'!$B:$B,'[1]产值及收款计划（2026）'!DD:DD)} -> 0 | DE13: {=_xlfn.XLOOKUP($A13&$B13,'[1]产值及收款计划（2026）'!$A:$A&'[1]产值及收款计划（2026）'!$B:$B,'[1]产值及收款计划（2026）'!DE:DE)} -> 0 | DF13: {=_xlfn.XLOOKUP($A13&$B13,'[1]产值及收款计划（2026）'!$A:$A&'[1]产值及收款计划（2026）'!$B:$B,'[1]产值及收款计划（2026）'!DF:DF)} -> 0 | DG13: {=_xlfn.XLOOKUP($A13&$B13,'[1]产值及收款计划（2026）'!$A:$A&'[1]产值及收款计划（2026）'!$B:$B,'[1]产值及收款计划（2026）'!DG:DG)} -> 0 | DH13: {=_xlfn.XLOOKUP($A13&$B13,'[1]产值及收款计划（2026）'!$A:$A&'[1]产值及收款计划（2026）'!$B:$B,'[1]产值及收款计划（2026）'!DH:DH)} -> 0 | DI13: {=_xlfn.XLOOKUP($A13&$B13,'[1]产值及收款计划（2026）'!$A:$A&'[1]产值及收款计划（2026）'!$B:$B,'[1]产值及收款计划（2026）'!DI:DI)} -> 0 | DJ13: {=_xlfn.XLOOKUP($A13&$B13,'[1]产值及收款计划（2026）'!$A:$A&'[1]产值及收款计划（2026）'!$B:$B,'[1]产值及收款计划（2026）'!DJ:DJ)} -> 0 | DK13: {=_xlfn.XLOOKUP($A13&$B13,'[1]产值及收款计划（2026）'!$A:$A&'[1]产值及收款计划（2026）'!$B:$B,'[1]产值及收款计划（2026）'!DK:DK)} -> 0 | DL13: {=_xlfn.XLOOKUP($A13&$B13,'[1]产值及收款计划（2026）'!$A:$A&'[1]产值及收款计划（2026）'!$B:$B,'[1]产值及收款计划（2026）'!DL:DL)} -> 0
A14: =A13+1 -> 10 | B14: 数字建造中心 | C14: {=_xlfn.XLOOKUP($A14&$B14,'[1]产值及收款计划（2026）'!$A:$A&'[1]产值及收款计划（2026）'!$B:$B,'[1]产值及收款计划（2026）'!C:C)} -> ZHT2021120100140 | D14: {=_xlfn.XLOOKUP($A14&$B14,'[1]产值及收款计划（2026）'!$A:$A&'[1]产值及收款计划（2026）'!$B:$B,'[1]产值及收款计划（2026）'!D:D)} -> 虹桥商务区核心区民防工程弱电智能化改造硬件采购 | E14: {=_xlfn.XLOOKUP($A14&$B14,'[1]产值及收款计划（2026）'!$A:$A&'[1]产值及收款计划（2026）'!$B:$B,'[1]产值及收款计划（2026）'!E:E)} -> 74.12854 | F14: {=_xlfn.XLOOKUP($A14&$B14,'[1]产值及收款计划（2026）'!$A:$A&'[1]产值及收款计划（2026）'!$B:$B,'[1]产值及收款计划（2026）'!F:F)} -> 74.12854 | G14: {=_xlfn.XLOOKUP($A14&$B14,'[1]产值及收款计划（2026）'!$A:$A&'[1]产值及收款计划（2026）'!$B:$B,'[1]产值及收款计划（2026）'!G:G)} -> 0 | H14: {=_xlfn.XLOOKUP($A14&$B14,'[1]产值及收款计划（2026）'!$A:$A&'[1]产值及收款计划（2026）'!$B:$B,'[1]产值及收款计划（2026）'!H:H)} -> 14.31164 | I14: {=_xlfn.XLOOKUP($A14&$B14,'[1]产值及收款计划（2026）'!$A:$A&'[1]产值及收款计划（2026）'!$B:$B,'[1]产值及收款计划（2026）'!I:I)} -> 0.19306518 | J14: {=_xlfn.XLOOKUP($A14&$B14,'[1]产值及收款计划（2026）'!$A:$A&'[1]产值及收款计划（2026）'!$B:$B,'[1]产值及收款计划（2026）'!J:J)} -> 0.13 | K14: {=_xlfn.XLOOKUP($A14&$B14,'[1]产值及收款计划（2026）'!$A:$A&'[1]产值及收款计划（2026）'!$B:$B,'[1]产值及收款计划（2026）'!K:K)} -> 0 | L14: {=_xlfn.XLOOKUP($A14&$B14,'[1]产值及收款计划（2026）'!$A:$A&'[1]产值及收款计划（2026）'!$B:$B,'[1]产值及收款计划（2026）'!L:L)} -> 0 | M14: {=_xlfn.XLOOKUP($A14&$B14,'[1]产值及收款计划（2026）'!$A:$A&'[1]产值及收款计划（2026）'!$B:$B,'[1]产值及收款计划（2026）'!M:M)} -> 主导 | N14: {=_xlfn.XLOOKUP($A14&$B14,'[1]产值及收款计划（2026）'!$A:$A&'[1]产值及收款计划（2026）'!$B:$B,'[1]产值及收款计划（2026）'!N:N)} -> 孔祥平团队 | O14: {=_xlfn.XLOOKUP($A14&$B14,'[1]产值及收款计划（2026）'!$A:$A&'[1]产值及收款计划（2026）'!$B:$B,'[1]产值及收款计划（2026）'!O:O)} -> 孔祥平 | P14: {=_xlfn.XLOOKUP($A14&$B14,'[1]产值及收款计划（2026）'!$A:$A&'[1]产值及收款计划（2026）'!$B:$B,'[1]产值及收款计划（2026）'!P:P)} -> 过往已完结 | Q14: {=_xlfn.XLOOKUP($A14&$B14,'[1]产值及收款计划（2026）'!$A:$A&'[1]产值及收款计划（2026）'!$B:$B,'[1]产值及收款计划（2026）'!Q:Q)} -> 0 | R14: {=_xlfn.XLOOKUP($A14&$B14,'[1]产值及收款计划（2026）'!$A:$A&'[1]产值及收款计划（2026）'!$B:$B,'[1]产值及收款计划（2026）'!R:R)} -> 0 | S14: {=_xlfn.XLOOKUP($A14&$B14,'[1]产值及收款计划（2026）'!$A:$A&'[1]产值及收款计划（2026）'!$B:$B,'[1]产值及收款计划（2026）'!S:S)} -> 0 | T14: {=_xlfn.XLOOKUP($A14&$B14,'[1]产值及收款计划（2026）'!$A:$A&'[1]产值及收款计划（2026）'!$B:$B,'[1]产值及收款计划（2026）'!T:T)} -> 74.12854 | U14: {=_xlfn.XLOOKUP($A14&$B14,'[1]产值及收款计划（2026）'!$A:$A&'[1]产值及收款计划（2026）'!$B:$B,'[1]产值及收款计划（2026）'!U:U)} -> 0 | V14: {=_xlfn.XLOOKUP($A14&$B14,'[1]产值及收款计划（2026）'!$A:$A&'[1]产值及收款计划（2026）'!$B:$B,'[1]产值及收款计划（2026）'!V:V)} -> 0 | W14: {=_xlfn.XLOOKUP($A14&$B14,'[1]产值及收款计划（2026）'!$A:$A&'[1]产值及收款计划（2026）'!$B:$B,'[1]产值及收款计划（2026）'!W:W)} -> 0 | X14: {=_xlfn.XLOOKUP($A14&$B14,'[1]产值及收款计划（2026）'!$A:$A&'[1]产值及收款计划（2026）'!$B:$B,'[1]产值及收款计划（2026）'!X:X)} -> 0 | Y14: {=_xlfn.XLOOKUP($A14&$B14,'[1]产值及收款计划（2026）'!$A:$A&'[1]产值及收款计划（2026）'!$B:$B,'[1]产值及收款计划（2026）'!Y:Y)} -> 0 | Z14: {=_xlfn.XLOOKUP($A14&$B14,'[1]产值及收款计划（2026）'!$A:$A&'[1]产值及收款计划（2026）'!$B:$B,'[1]产值及收款计划（2026）'!Z:Z)} -> 0 | AA14: {=_xlfn.XLOOKUP($A14&$B14,'[1]产值及收款计划（2026）'!$A:$A&'[1]产值及收款计划（2026）'!$B:$B,'[1]产值及收款计划（2026）'!AA:AA)} -> 0 | AB14: {=_xlfn.XLOOKUP($A14&$B14,'[1]产值及收款计划（2026）'!$A:$A&'[1]产值及收款计划（2026）'!$B:$B,'[1]产值及收款计划（2026）'!AB:AB)} -> 0 | AC14: {=_xlfn.XLOOKUP($A14&$B14,'[1]产值及收款计划（2026）'!$A:$A&'[1]产值及收款计划（2026）'!$B:$B,'[1]产值及收款计划（2026）'!AC:AC)} -> 0 | AD14: {=_xlfn.XLOOKUP($A14&$B14,'[1]产值及收款计划（2026）'!$A:$A&'[1]产值及收款计划（2026）'!$B:$B,'[1]产值及收款计划（2026）'!AD:AD)} -> 0 | AE14: {=_xlfn.XLOOKUP($A14&$B14,'[1]产值及收款计划（2026）'!$A:$A&'[1]产值及收款计划（2026）'!$B:$B,'[1]产值及收款计划（2026）'!AE:AE)} -> 0 | AF14: {=_xlfn.XLOOKUP($A14&$B14,'[1]产值及收款计划（2026）'!$A:$A&'[1]产值及收款计划（2026）'!$B:$B,'[1]产值及收款计划（2026）'!AF:AF)} -> 0 | AG14: {=_xlfn.XLOOKUP($A14&$B14,'[1]产值及收款计划（2026）'!$A:$A&'[1]产值及收款计划（2026）'!$B:$B,'[1]产值及收款计划（2026）'!AG:AG)} -> 0 | AH14: {=_xlfn.XLOOKUP($A14&$B14,'[1]产值及收款计划（2026）'!$A:$A&'[1]产值及收款计划（2026）'!$B:$B,'[1]产值及收款计划（2026）'!AH:AH)} -> 0 | AI14: {=_xlfn.XLOOKUP($A14&$B14,'[1]产值及收款计划（2026）'!$A:$A&'[1]产值及收款计划（2026）'!$B:$B,'[1]产值及收款计划（2026）'!AI:AI)} -> 0 | AJ14: {=_xlfn.XLOOKUP($A14&$B14,'[1]产值及收款计划（2026）'!$A:$A&'[1]产值及收款计划（2026）'!$B:$B,'[1]产值及收款计划（2026）'!AJ:AJ)} -> 0 | AK14: {=_xlfn.XLOOKUP($A14&$B14,'[1]产值及收款计划（2026）'!$A:$A&'[1]产值及收款计划（2026）'!$B:$B,'[1]产值及收款计划（2026）'!AK:AK)} -> 0 | AL14: {=_xlfn.XLOOKUP($A14&$B14,'[1]产值及收款计划（2026）'!$A:$A&'[1]产值及收款计划（2026）'!$B:$B,'[1]产值及收款计划（2026）'!AL:AL)} -> 0 | AM14: {=_xlfn.LET(_xlpm.勾选月份状态数组,TRANSPOSE('PPT(12-15页）-TOP10'!$A$3:$A$14),_xlpm.选择数据区,IF('PPT(12-15页）-TOP10'!$E$3="收款",$BA14:$BL14,$AA14:$AL14),SUM(_xlfn._xlws.FILTER(_xlpm.选择数据区,_xlpm.勾选月份状态数组,"")))} -> #NAME? | AN14: {=_xlfn.LET(_xlpm.勾选月份状态数组,TRANSPOSE('PPT(12-15页）-TOP10'!$A$3:$A$14),_xlpm.选择数据区,IF('PPT(12-15页）-TOP10'!$E$3="收款",$DA14:$DL14,$CA14:$CL14),SUM(_xlfn._xlws.FILTER(_xlpm.选择数据区,_xlpm.勾选月份状态数组,"")))} -> #NAME? | AO14: =SUM(CA14:CC14)+SUM(AD14:AL14) -> 0 | AS14: {=_xlfn.XLOOKUP($A14&$B14,'[1]产值及收款计划（2026）'!$A:$A&'[1]产值及收款计划（2026）'!$B:$B,'[1]产值及收款计划（2026）'!AS:AS)} -> 0 | AT14: {=_xlfn.XLOOKUP($A14&$B14,'[1]产值及收款计划（2026）'!$A:$A&'[1]产值及收款计划（2026）'!$B:$B,'[1]产值及收款计划（2026）'!AT:AT)} -> 0 | AU14: {=_xlfn.XLOOKUP($A14&$B14,'[1]产值及收款计划（2026）'!$A:$A&'[1]产值及收款计划（2026）'!$B:$B,'[1]产值及收款计划（2026）'!AU:AU)} -> 0 | AV14: {=_xlfn.XLOOKUP($A14&$B14,'[1]产值及收款计划（2026）'!$A:$A&'[1]产值及收款计划（2026）'!$B:$B,'[1]产值及收款计划（2026）'!AV:AV)} -> 0 | AW14: {=_xlfn.XLOOKUP($A14&$B14,'[1]产值及收款计划（2026）'!$A:$A&'[1]产值及收款计划（2026）'!$B:$B,'[1]产值及收款计划（2026）'!AW:AW)} -> 37 | AX14: {=_xlfn.XLOOKUP($A14&$B14,'[1]产值及收款计划（2026）'!$A:$A&'[1]产值及收款计划（2026）'!$B:$B,'[1]产值及收款计划（2026）'!AX:AX)} -> 0 | AY14: {=_xlfn.XLOOKUP($A14&$B14,'[1]产值及收款计划（2026）'!$A:$A&'[1]产值及收款计划（2026）'!$B:$B,'[1]产值及收款计划（2026）'!AY:AY)} -> 37.12854 | AZ14: {=_xlfn.XLOOKUP($A14&$B14,'[1]产值及收款计划（2026）'!$A:$A&'[1]产值及收款计划（2026）'!$B:$B,'[1]产值及收款计划（2026）'!AZ:AZ)} -> 37.12854 | BA14: {=_xlfn.XLOOKUP($A14&$B14,'[1]产值及收款计划（2026）'!$A:$A&'[1]产值及收款计划（2026）'!$B:$B,'[1]产值及收款计划（2026）'!BA:BA)} -> 0 | BB14: {=_xlfn.XLOOKUP($A14&$B14,'[1]产值及收款计划（2026）'!$A:$A&'[1]产值及收款计划（2026）'!$B:$B,'[1]产值及收款计划（2026）'!BB:BB)} -> 37 | BC14: {=_xlfn.XLOOKUP($A14&$B14,'[1]产值及收款计划（2026）'!$A:$A&'[1]产值及收款计划（2026）'!$B:$B,'[1]产值及收款计划（2026）'!BC:BC)} -> 0 | BD14: {=_xlfn.XLOOKUP($A14&$B14,'[1]产值及收款计划（2026）'!$A:$A&'[1]产值及收款计划（2026）'!$B:$B,'[1]产值及收款计划（2026）'!BD:BD)} -> 0 | BE14: {=_xlfn.XLOOKUP($A14&$B14,'[1]产值及收款计划（2026）'!$A:$A&'[1]产值及收款计划（2026）'!$B:$B,'[1]产值及收款计划（2026）'!BE:BE)} -> 0 | BF14: {=_xlfn.XLOOKUP($A14&$B14,'[1]产值及收款计划（2026）'!$A:$A&'[1]产值及收款计划（2026）'!$B:$B,'[1]产值及收款计划（2026）'!BF:BF)} -> 0 | BG14: {=_xlfn.XLOOKUP($A14&$B14,'[1]产值及收款计划（2026）'!$A:$A&'[1]产值及收款计划（2026）'!$B:$B,'[1]产值及收款计划（2026）'!BG:BG)} -> 0 | BH14: {=_xlfn.XLOOKUP($A14&$B14,'[1]产值及收款计划（2026）'!$A:$A&'[1]产值及收款计划（2026）'!$B:$B,'[1]产值及收款计划（2026）'!BH:BH)} -> 0 | BI14: {=_xlfn.XLOOKUP($A14&$B14,'[1]产值及收款计划（2026）'!$A:$A&'[1]产值及收款计划（2026）'!$B:$B,'[1]产值及收款计划（2026）'!BI:BI)} -> 0 | BJ14: {=_xlfn.XLOOKUP($A14&$B14,'[1]产值及收款计划（2026）'!$A:$A&'[1]产值及收款计划（2026）'!$B:$B,'[1]产值及收款计划（2026）'!BJ:BJ)} -> 0 | BK14: {=_xlfn.XLOOKUP($A14&$B14,'[1]产值及收款计划（2026）'!$A:$A&'[1]产值及收款计划（2026）'!$B:$B,'[1]产值及收款计划（2026）'!BK:BK)} -> 0 | BL14: {=_xlfn.XLOOKUP($A14&$B14,'[1]产值及收款计划（2026）'!$A:$A&'[1]产值及收款计划（2026）'!$B:$B,'[1]产值及收款计划（2026）'!BL:BL)} -> 0 | BQ14: {=_xlfn.XLOOKUP($A14&$B14,'[1]产值及收款计划（2026）'!$A:$A&'[1]产值及收款计划（2026）'!$B:$B,'[1]产值及收款计划（2026）'!BQ:BQ)} -> 0 | BR14: {=_xlfn.XLOOKUP($A14&$B14,'[1]产值及收款计划（2026）'!$A:$A&'[1]产值及收款计划（2026）'!$B:$B,'[1]产值及收款计划（2026）'!BR:BR)} -> 0 | CA14: {=_xlfn.XLOOKUP($A14&$B14,'[1]产值及收款计划（2026）'!$A:$A&'[1]产值及收款计划（2026）'!$B:$B,'[1]产值及收款计划（2026）'!CA:CA)} -> 0 | CB14: {=_xlfn.XLOOKUP($A14&$B14,'[1]产值及收款计划（2026）'!$A:$A&'[1]产值及收款计划（2026）'!$B:$B,'[1]产值及收款计划（2026）'!CB:CB)} -> 0 | CC14: {=_xlfn.XLOOKUP($A14&$B14,'[1]产值及收款计划（2026）'!$A:$A&'[1]产值及收款计划（2026）'!$B:$B,'[1]产值及收款计划（2026）'!CC:CC)} -> 0 | CD14: {=_xlfn.XLOOKUP($A14&$B14,'[1]产值及收款计划（2026）'!$A:$A&'[1]产值及收款计划（2026）'!$B:$B,'[1]产值及收款计划（2026）'!CD:CD)} -> 0 | CE14: {=_xlfn.XLOOKUP($A14&$B14,'[1]产值及收款计划（2026）'!$A:$A&'[1]产值及收款计划（2026）'!$B:$B,'[1]产值及收款计划（2026）'!CE:CE)} -> 0 | CF14: {=_xlfn.XLOOKUP($A14&$B14,'[1]产值及收款计划（2026）'!$A:$A&'[1]产值及收款计划（2026）'!$B:$B,'[1]产值及收款计划（2026）'!CF:CF)} -> 0 | CG14: {=_xlfn.XLOOKUP($A14&$B14,'[1]产值及收款计划（2026）'!$A:$A&'[1]产值及收款计划（2026）'!$B:$B,'[1]产值及收款计划（2026）'!CG:CG)} -> 0 | CH14: {=_xlfn.XLOOKUP($A14&$B14,'[1]产值及收款计划（2026）'!$A:$A&'[1]产值及收款计划（2026）'!$B:$B,'[1]产值及收款计划（2026）'!CH:CH)} -> 0 | CI14: {=_xlfn.XLOOKUP($A14&$B14,'[1]产值及收款计划（2026）'!$A:$A&'[1]产值及收款计划（2026）'!$B:$B,'[1]产值及收款计划（2026）'!CI:CI)} -> 0 | CJ14: {=_xlfn.XLOOKUP($A14&$B14,'[1]产值及收款计划（2026）'!$A:$A&'[1]产值及收款计划（2026）'!$B:$B,'[1]产值及收款计划（2026）'!CJ:CJ)} -> 0 | CK14: {=_xlfn.XLOOKUP($A14&$B14,'[1]产值及收款计划（2026）'!$A:$A&'[1]产值及收款计划（2026）'!$B:$B,'[1]产值及收款计划（2026）'!CK:CK)} -> 0 | CL14: {=_xlfn.XLOOKUP($A14&$B14,'[1]产值及收款计划（2026）'!$A:$A&'[1]产值及收款计划（2026）'!$B:$B,'[1]产值及收款计划（2026）'!CL:CL)} -> 0 | DA14: {=_xlfn.XLOOKUP($A14&$B14,'[1]产值及收款计划（2026）'!$A:$A&'[1]产值及收款计划（2026）'!$B:$B,'[1]产值及收款计划（2026）'!DA:DA)} -> 0 | DB14: {=_xlfn.XLOOKUP($A14&$B14,'[1]产值及收款计划（2026）'!$A:$A&'[1]产值及收款计划（2026）'!$B:$B,'[1]产值及收款计划（2026）'!DB:DB)} -> 0 | DC14: {=_xlfn.XLOOKUP($A14&$B14,'[1]产值及收款计划（2026）'!$A:$A&'[1]产值及收款计划（2026）'!$B:$B,'[1]产值及收款计划（2026）'!DC:DC)} -> 0 | DD14: {=_xlfn.XLOOKUP($A14&$B14,'[1]产值及收款计划（2026）'!$A:$A&'[1]产值及收款计划（2026）'!$B:$B,'[1]产值及收款计划（2026）'!DD:DD)} -> 0 | DE14: {=_xlfn.XLOOKUP($A14&$B14,'[1]产值及收款计划（2026）'!$A:$A&'[1]产值及收款计划（2026）'!$B:$B,'[1]产值及收款计划（2026）'!DE:DE)} -> 0 | DF14: {=_xlfn.XLOOKUP($A14&$B14,'[1]产值及收款计划（2026）'!$A:$A&'[1]产值及收款计划（2026）'!$B:$B,'[1]产值及收款计划（2026）'!DF:DF)} -> 0 | DG14: {=_xlfn.XLOOKUP($A14&$B14,'[1]产值及收款计划（2026）'!$A:$A&'[1]产值及收款计划（2026）'!$B:$B,'[1]产值及收款计划（2026）'!DG:DG)} -> 0 | DH14: {=_xlfn.XLOOKUP($A14&$B14,'[1]产值及收款计划（2026）'!$A:$A&'[1]产值及收款计划（2026）'!$B:$B,'[1]产值及收款计划（2026）'!DH:DH)} -> 0 | DI14: {=_xlfn.XLOOKUP($A14&$B14,'[1]产值及收款计划（2026）'!$A:$A&'[1]产值及收款计划（2026）'!$B:$B,'[1]产值及收款计划（2026）'!DI:DI)} -> 0 | DJ14: {=_xlfn.XLOOKUP($A14&$B14,'[1]产值及收款计划（2026）'!$A:$A&'[1]产值及收款计划（2026）'!$B:$B,'[1]产值及收款计划（2026）'!DJ:DJ)} -> 0 | DK14: {=_xlfn.XLOOKUP($A14&$B14,'[1]产值及收款计划（2026）'!$A:$A&'[1]产值及收款计划（2026）'!$B:$B,'[1]产值及收款计划（2026）'!DK:DK)} -> 0 | DL14: {=_xlfn.XLOOKUP($A14&$B14,'[1]产值及收款计划（2026）'!$A:$A&'[1]产值及收款计划（2026）'!$B:$B,'[1]产值及收款计划（2026）'!DL:DL)} -> 0
A15: =A14+1 -> 11 | B15: 数字建造中心 | C15: {=_xlfn.XLOOKUP($A15&$B15,'[1]产值及收款计划（2026）'!$A:$A&'[1]产值及收款计划（2026）'!$B:$B,'[1]产值及收款计划（2026）'!C:C)} -> ZHT2021020200008 | D15: {=_xlfn.XLOOKUP($A15&$B15,'[1]产值及收款计划（2026）'!$A:$A&'[1]产值及收款计划（2026）'!$B:$B,'[1]产值及收款计划（2026）'!D:D)} -> 南湖区老（旧）住宅区改造提升专项工程（二期）方案设计、初步设计项目BIM技术应用 | E15: {=_xlfn.XLOOKUP($A15&$B15,'[1]产值及收款计划（2026）'!$A:$A&'[1]产值及收款计划（2026）'!$B:$B,'[1]产值及收款计划（2026）'!E:E)} -> 138.4 | F15: {=_xlfn.XLOOKUP($A15&$B15,'[1]产值及收款计划（2026）'!$A:$A&'[1]产值及收款计划（2026）'!$B:$B,'[1]产值及收款计划（2026）'!F:F)} -> 138.4 | G15: {=_xlfn.XLOOKUP($A15&$B15,'[1]产值及收款计划（2026）'!$A:$A&'[1]产值及收款计划（2026）'!$B:$B,'[1]产值及收款计划（2026）'!G:G)} -> 0 | H15: {=_xlfn.XLOOKUP($A15&$B15,'[1]产值及收款计划（2026）'!$A:$A&'[1]产值及收款计划（2026）'!$B:$B,'[1]产值及收款计划（2026）'!H:H)} -> 72.26 | I15: {=_xlfn.XLOOKUP($A15&$B15,'[1]产值及收款计划（2026）'!$A:$A&'[1]产值及收款计划（2026）'!$B:$B,'[1]产值及收款计划（2026）'!I:I)} -> 0.52210983 | J15: {=_xlfn.XLOOKUP($A15&$B15,'[1]产值及收款计划（2026）'!$A:$A&'[1]产值及收款计划（2026）'!$B:$B,'[1]产值及收款计划（2026）'!J:J)} -> 0.06 | K15: {=_xlfn.XLOOKUP($A15&$B15,'[1]产值及收款计划（2026）'!$A:$A&'[1]产值及收款计划（2026）'!$B:$B,'[1]产值及收款计划（2026）'!K:K)} -> 0 | L15: {=_xlfn.XLOOKUP($A15&$B15,'[1]产值及收款计划（2026）'!$A:$A&'[1]产值及收款计划（2026）'!$B:$B,'[1]产值及收款计划（2026）'!L:L)} -> 0 | M15: {=_xlfn.XLOOKUP($A15&$B15,'[1]产值及收款计划（2026）'!$A:$A&'[1]产值及收款计划（2026）'!$B:$B,'[1]产值及收款计划（2026）'!M:M)} -> 主导 | N15: {=_xlfn.XLOOKUP($A15&$B15,'[1]产值及收款计划（2026）'!$A:$A&'[1]产值及收款计划（2026）'!$B:$B,'[1]产值及收款计划（2026）'!N:N)} -> 孔祥平团队 | O15: {=_xlfn.XLOOKUP($A15&$B15,'[1]产值及收款计划（2026）'!$A:$A&'[1]产值及收款计划（2026）'!$B:$B,'[1]产值及收款计划（2026）'!O:O)} -> 卜宝翔 | P15: {=_xlfn.XLOOKUP($A15&$B15,'[1]产值及收款计划（2026）'!$A:$A&'[1]产值及收款计划（2026）'!$B:$B,'[1]产值及收款计划（2026）'!P:P)} -> 过往已完结 | Q15: {=_xlfn.XLOOKUP($A15&$B15,'[1]产值及收款计划（2026）'!$A:$A&'[1]产值及收款计划（2026）'!$B:$B,'[1]产值及收款计划（2026）'!Q:Q)} -> 0 | R15: {=_xlfn.XLOOKUP($A15&$B15,'[1]产值及收款计划（2026）'!$A:$A&'[1]产值及收款计划（2026）'!$B:$B,'[1]产值及收款计划（2026）'!R:R)} -> 0 | S15: {=_xlfn.XLOOKUP($A15&$B15,'[1]产值及收款计划（2026）'!$A:$A&'[1]产值及收款计划（2026）'!$B:$B,'[1]产值及收款计划（2026）'!S:S)} -> 0 | T15: {=_xlfn.XLOOKUP($A15&$B15,'[1]产值及收款计划（2026）'!$A:$A&'[1]产值及收款计划（2026）'!$B:$B,'[1]产值及收款计划（2026）'!T:T)} -> 138.4 | U15: {=_xlfn.XLOOKUP($A15&$B15,'[1]产值及收款计划（2026）'!$A:$A&'[1]产值及收款计划（2026）'!$B:$B,'[1]产值及收款计划（2026）'!U:U)} -> 0 | V15: {=_xlfn.XLOOKUP($A15&$B15,'[1]产值及收款计划（2026）'!$A:$A&'[1]产值及收款计划（2026）'!$B:$B,'[1]产值及收款计划（2026）'!V:V)} -> 0 | W15: {=_xlfn.XLOOKUP($A15&$B15,'[1]产值及收款计划（2026）'!$A:$A&'[1]产值及收款计划（2026）'!$B:$B,'[1]产值及收款计划（2026）'!W:W)} -> 0 | X15: {=_xlfn.XLOOKUP($A15&$B15,'[1]产值及收款计划（2026）'!$A:$A&'[1]产值及收款计划（2026）'!$B:$B,'[1]产值及收款计划（2026）'!X:X)} -> 0 | Y15: {=_xlfn.XLOOKUP($A15&$B15,'[1]产值及收款计划（2026）'!$A:$A&'[1]产值及收款计划（2026）'!$B:$B,'[1]产值及收款计划（2026）'!Y:Y)} -> 0 | Z15: {=_xlfn.XLOOKUP($A15&$B15,'[1]产值及收款计划（2026）'!$A:$A&'[1]产值及收款计划（2026）'!$B:$B,'[1]产值及收款计划（2026）'!Z:Z)} -> 0 | AA15: {=_xlfn.XLOOKUP($A15&$B15,'[1]产值及收款计划（2026）'!$A:$A&'[1]产值及收款计划（2026）'!$B:$B,'[1]产值及收款计划（2026）'!AA:AA)} -> 0 | AB15: {=_xlfn.XLOOKUP($A15&$B15,'[1]产值及收款计划（2026）'!$A:$A&'[1]产值及收款计划（2026）'!$B:$B,'[1]产值及收款计划（2026）'!AB:AB)} -> 0 | AC15: {=_xlfn.XLOOKUP($A15&$B15,'[1]产值及收款计划（2026）'!$A:$A&'[1]产值及收款计划（2026）'!$B:$B,'[1]产值及收款计划（2026）'!AC:AC)} -> 0 | AD15: {=_xlfn.XLOOKUP($A15&$B15,'[1]产值及收款计划（2026）'!$A:$A&'[1]产值及收款计划（2026）'!$B:$B,'[1]产值及收款计划（2026）'!AD:AD)} -> 0 | AE15: {=_xlfn.XLOOKUP($A15&$B15,'[1]产值及收款计划（2026）'!$A:$A&'[1]产值及收款计划（2026）'!$B:$B,'[1]产值及收款计划（2026）'!AE:AE)} -> 0 | AF15: {=_xlfn.XLOOKUP($A15&$B15,'[1]产值及收款计划（2026）'!$A:$A&'[1]产值及收款计划（2026）'!$B:$B,'[1]产值及收款计划（2026）'!AF:AF)} -> 0 | AG15: {=_xlfn.XLOOKUP($A15&$B15,'[1]产值及收款计划（2026）'!$A:$A&'[1]产值及收款计划（2026）'!$B:$B,'[1]产值及收款计划（2026）'!AG:AG)} -> 0 | AH15: {=_xlfn.XLOOKUP($A15&$B15,'[1]产值及收款计划（2026）'!$A:$A&'[1]产值及收款计划（2026）'!$B:$B,'[1]产值及收款计划（2026）'!AH:AH)} -> 0 | AI15: {=_xlfn.XLOOKUP($A15&$B15,'[1]产值及收款计划（2026）'!$A:$A&'[1]产值及收款计划（2026）'!$B:$B,'[1]产值及收款计划（2026）'!AI:AI)} -> 0 | AJ15: {=_xlfn.XLOOKUP($A15&$B15,'[1]产值及收款计划（2026）'!$A:$A&'[1]产值及收款计划（2026）'!$B:$B,'[1]产值及收款计划（2026）'!AJ:AJ)} -> 0 | AK15: {=_xlfn.XLOOKUP($A15&$B15,'[1]产值及收款计划（2026）'!$A:$A&'[1]产值及收款计划（2026）'!$B:$B,'[1]产值及收款计划（2026）'!AK:AK)} -> 0 | AL15: {=_xlfn.XLOOKUP($A15&$B15,'[1]产值及收款计划（2026）'!$A:$A&'[1]产值及收款计划（2026）'!$B:$B,'[1]产值及收款计划（2026）'!AL:AL)} -> 0 | AM15: {=_xlfn.LET(_xlpm.勾选月份状态数组,TRANSPOSE('PPT(12-15页）-TOP10'!$A$3:$A$14),_xlpm.选择数据区,IF('PPT(12-15页）-TOP10'!$E$3="收款",$BA15:$BL15,$AA15:$AL15),SUM(_xlfn._xlws.FILTER(_xlpm.选择数据区,_xlpm.勾选月份状态数组,"")))} -> #NAME? | AN15: {=_xlfn.LET(_xlpm.勾选月份状态数组,TRANSPOSE('PPT(12-15页）-TOP10'!$A$3:$A$14),_xlpm.选择数据区,IF('PPT(12-15页）-TOP10'!$E$3="收款",$DA15:$DL15,$CA15:$CL15),SUM(_xlfn._xlws.FILTER(_xlpm.选择数据区,_xlpm.勾选月份状态数组,"")))} -> #NAME? | AO15: =SUM(CA15:CC15)+SUM(AD15:AL15) -> 0 | AS15: {=_xlfn.XLOOKUP($A15&$B15,'[1]产值及收款计划（2026）'!$A:$A&'[1]产值及收款计划（2026）'!$B:$B,'[1]产值及收款计划（2026）'!AS:AS)} -> 0 | AT15: {=_xlfn.XLOOKUP($A15&$B15,'[1]产值及收款计划（2026）'!$A:$A&'[1]产值及收款计划（2026）'!$B:$B,'[1]产值及收款计划（2026）'!AT:AT)} -> 0 | AU15: {=_xlfn.XLOOKUP($A15&$B15,'[1]产值及收款计划（2026）'!$A:$A&'[1]产值及收款计划（2026）'!$B:$B,'[1]产值及收款计划（2026）'!AU:AU)} -> 0 | AV15: {=_xlfn.XLOOKUP($A15&$B15,'[1]产值及收款计划（2026）'!$A:$A&'[1]产值及收款计划（2026）'!$B:$B,'[1]产值及收款计划（2026）'!AV:AV)} -> 0 | AW15: {=_xlfn.XLOOKUP($A15&$B15,'[1]产值及收款计划（2026）'!$A:$A&'[1]产值及收款计划（2026）'!$B:$B,'[1]产值及收款计划（2026）'!AW:AW)} -> 131.48 | AX15: {=_xlfn.XLOOKUP($A15&$B15,'[1]产值及收款计划（2026）'!$A:$A&'[1]产值及收款计划（2026）'!$B:$B,'[1]产值及收款计划（2026）'!AX:AX)} -> 0 | AY15: {=_xlfn.XLOOKUP($A15&$B15,'[1]产值及收款计划（2026）'!$A:$A&'[1]产值及收款计划（2026）'!$B:$B,'[1]产值及收款计划（2026）'!AY:AY)} -> 6.92 | AZ15: {=_xlfn.XLOOKUP($A15&$B15,'[1]产值及收款计划（2026）'!$A:$A&'[1]产值及收款计划（2026）'!$B:$B,'[1]产值及收款计划（2026）'!AZ:AZ)} -> 6.92 | BA15: {=_xlfn.XLOOKUP($A15&$B15,'[1]产值及收款计划（2026）'!$A:$A&'[1]产值及收款计划（2026）'!$B:$B,'[1]产值及收款计划（2026）'!BA:BA)} -> 0 | BB15: {=_xlfn.XLOOKUP($A15&$B15,'[1]产值及收款计划（2026）'!$A:$A&'[1]产值及收款计划（2026）'!$B:$B,'[1]产值及收款计划（2026）'!BB:BB)} -> 0 | BC15: {=_xlfn.XLOOKUP($A15&$B15,'[1]产值及收款计划（2026）'!$A:$A&'[1]产值及收款计划（2026）'!$B:$B,'[1]产值及收款计划（2026）'!BC:BC)} -> 0 | BD15: {=_xlfn.XLOOKUP($A15&$B15,'[1]产值及收款计划（2026）'!$A:$A&'[1]产值及收款计划（2026）'!$B:$B,'[1]产值及收款计划（2026）'!BD:BD)} -> 0 | BE15: {=_xlfn.XLOOKUP($A15&$B15,'[1]产值及收款计划（2026）'!$A:$A&'[1]产值及收款计划（2026）'!$B:$B,'[1]产值及收款计划（2026）'!BE:BE)} -> 0 | BF15: {=_xlfn.XLOOKUP($A15&$B15,'[1]产值及收款计划（2026）'!$A:$A&'[1]产值及收款计划（2026）'!$B:$B,'[1]产值及收款计划（2026）'!BF:BF)} -> 0 | BG15: {=_xlfn.XLOOKUP($A15&$B15,'[1]产值及收款计划（2026）'!$A:$A&'[1]产值及收款计划（2026）'!$B:$B,'[1]产值及收款计划（2026）'!BG:BG)} -> 0 | BH15: {=_xlfn.XLOOKUP($A15&$B15,'[1]产值及收款计划（2026）'!$A:$A&'[1]产值及收款计划（2026）'!$B:$B,'[1]产值及收款计划（2026）'!BH:BH)} -> 0 | BI15: {=_xlfn.XLOOKUP($A15&$B15,'[1]产值及收款计划（2026）'!$A:$A&'[1]产值及收款计划（2026）'!$B:$B,'[1]产值及收款计划（2026）'!BI:BI)} -> 0 | BJ15: {=_xlfn.XLOOKUP($A15&$B15,'[1]产值及收款计划（2026）'!$A:$A&'[1]产值及收款计划（2026）'!$B:$B,'[1]产值及收款计划（2026）'!BJ:BJ)} -> 0 | BK15: {=_xlfn.XLOOKUP($A15&$B15,'[1]产值及收款计划（2026）'!$A:$A&'[1]产值及收款计划（2026）'!$B:$B,'[1]产值及收款计划（2026）'!BK:BK)} -> 0 | BL15: {=_xlfn.XLOOKUP($A15&$B15,'[1]产值及收款计划（2026）'!$A:$A&'[1]产值及收款计划（2026）'!$B:$B,'[1]产值及收款计划（2026）'!BL:BL)} -> 0 | BQ15: {=_xlfn.XLOOKUP($A15&$B15,'[1]产值及收款计划（2026）'!$A:$A&'[1]产值及收款计划（2026）'!$B:$B,'[1]产值及收款计划（2026）'!BQ:BQ)} -> 0 | BR15: {=_xlfn.XLOOKUP($A15&$B15,'[1]产值及收款计划（2026）'!$A:$A&'[1]产值及收款计划（2026）'!$B:$B,'[1]产值及收款计划（2026）'!BR:BR)} -> 0 | CA15: {=_xlfn.XLOOKUP($A15&$B15,'[1]产值及收款计划（2026）'!$A:$A&'[1]产值及收款计划（2026）'!$B:$B,'[1]产值及收款计划（2026）'!CA:CA)} -> 0 | CB15: {=_xlfn.XLOOKUP($A15&$B15,'[1]产值及收款计划（2026）'!$A:$A&'[1]产值及收款计划（2026）'!$B:$B,'[1]产值及收款计划（2026）'!CB:CB)} -> 0 | CC15: {=_xlfn.XLOOKUP($A15&$B15,'[1]产值及收款计划（2026）'!$A:$A&'[1]产值及收款计划（2026）'!$B:$B,'[1]产值及收款计划（2026）'!CC:CC)} -> 0 | CD15: {=_xlfn.XLOOKUP($A15&$B15,'[1]产值及收款计划（2026）'!$A:$A&'[1]产值及收款计划（2026）'!$B:$B,'[1]产值及收款计划（2026）'!CD:CD)} -> 0 | CE15: {=_xlfn.XLOOKUP($A15&$B15,'[1]产值及收款计划（2026）'!$A:$A&'[1]产值及收款计划（2026）'!$B:$B,'[1]产值及收款计划（2026）'!CE:CE)} -> 0 | CF15: {=_xlfn.XLOOKUP($A15&$B15,'[1]产值及收款计划（2026）'!$A:$A&'[1]产值及收款计划（2026）'!$B:$B,'[1]产值及收款计划（2026）'!CF:CF)} -> 0 | CG15: {=_xlfn.XLOOKUP($A15&$B15,'[1]产值及收款计划（2026）'!$A:$A&'[1]产值及收款计划（2026）'!$B:$B,'[1]产值及收款计划（2026）'!CG:CG)} -> 0 | CH15: {=_xlfn.XLOOKUP($A15&$B15,'[1]产值及收款计划（2026）'!$A:$A&'[1]产值及收款计划（2026）'!$B:$B,'[1]产值及收款计划（2026）'!CH:CH)} -> 0 | CI15: {=_xlfn.XLOOKUP($A15&$B15,'[1]产值及收款计划（2026）'!$A:$A&'[1]产值及收款计划（2026）'!$B:$B,'[1]产值及收款计划（2026）'!CI:CI)} -> 0 | CJ15: {=_xlfn.XLOOKUP($A15&$B15,'[1]产值及收款计划（2026）'!$A:$A&'[1]产值及收款计划（2026）'!$B:$B,'[1]产值及收款计划（2026）'!CJ:CJ)} -> 0 | CK15: {=_xlfn.XLOOKUP($A15&$B15,'[1]产值及收款计划（2026）'!$A:$A&'[1]产值及收款计划（2026）'!$B:$B,'[1]产值及收款计划（2026）'!CK:CK)} -> 0 | CL15: {=_xlfn.XLOOKUP($A15&$B15,'[1]产值及收款计划（2026）'!$A:$A&'[1]产值及收款计划（2026）'!$B:$B,'[1]产值及收款计划（2026）'!CL:CL)} -> 0 | DA15: {=_xlfn.XLOOKUP($A15&$B15,'[1]产值及收款计划（2026）'!$A:$A&'[1]产值及收款计划（2026）'!$B:$B,'[1]产值及收款计划（2026）'!DA:DA)} -> 0 | DB15: {=_xlfn.XLOOKUP($A15&$B15,'[1]产值及收款计划（2026）'!$A:$A&'[1]产值及收款计划（2026）'!$B:$B,'[1]产值及收款计划（2026）'!DB:DB)} -> 0 | DC15: {=_xlfn.XLOOKUP($A15&$B15,'[1]产值及收款计划（2026）'!$A:$A&'[1]产值及收款计划（2026）'!$B:$B,'[1]产值及收款计划（2026）'!DC:DC)} -> 0 | DD15: {=_xlfn.XLOOKUP($A15&$B15,'[1]产值及收款计划（2026）'!$A:$A&'[1]产值及收款计划（2026）'!$B:$B,'[1]产值及收款计划（2026）'!DD:DD)} -> 0 | DE15: {=_xlfn.XLOOKUP($A15&$B15,'[1]产值及收款计划（2026）'!$A:$A&'[1]产值及收款计划（2026）'!$B:$B,'[1]产值及收款计划（2026）'!DE:DE)} -> 0 | DF15: {=_xlfn.XLOOKUP($A15&$B15,'[1]产值及收款计划（2026）'!$A:$A&'[1]产值及收款计划（2026）'!$B:$B,'[1]产值及收款计划（2026）'!DF:DF)} -> 0 | DG15: {=_xlfn.XLOOKUP($A15&$B15,'[1]产值及收款计划（2026）'!$A:$A&'[1]产值及收款计划（2026）'!$B:$B,'[1]产值及收款计划（2026）'!DG:DG)} -> 0 | DH15: {=_xlfn.XLOOKUP($A15&$B15,'[1]产值及收款计划（2026）'!$A:$A&'[1]产值及收款计划（2026）'!$B:$B,'[1]产值及收款计划（2026）'!DH:DH)} -> 0 | DI15: {=_xlfn.XLOOKUP($A15&$B15,'[1]产值及收款计划（2026）'!$A:$A&'[1]产值及收款计划（2026）'!$B:$B,'[1]产值及收款计划（2026）'!DI:DI)} -> 0 | DJ15: {=_xlfn.XLOOKUP($A15&$B15,'[1]产值及收款计划（2026）'!$A:$A&'[1]产值及收款计划（2026）'!$B:$B,'[1]产值及收款计划（2026）'!DJ:DJ)} -> 0 | DK15: {=_xlfn.XLOOKUP($A15&$B15,'[1]产值及收款计划（2026）'!$A:$A&'[1]产值及收款计划（2026）'!$B:$B,'[1]产值及收款计划（2026）'!DK:DK)} -> 0 | DL15: {=_xlfn.XLOOKUP($A15&$B15,'[1]产值及收款计划（2026）'!$A:$A&'[1]产值及收款计划（2026）'!$B:$B,'[1]产值及收款计划（2026）'!DL:DL)} -> 0
A16: =A15+1 -> 12 | B16: 数字建造中心 | C16: {=_xlfn.XLOOKUP($A16&$B16,'[1]产值及收款计划（2026）'!$A:$A&'[1]产值及收款计划（2026）'!$B:$B,'[1]产值及收款计划（2026）'!C:C)} -> ZHT2021081200096 | D16: {=_xlfn.XLOOKUP($A16&$B16,'[1]产值及收款计划（2026）'!$A:$A&'[1]产值及收款计划（2026）'!$B:$B,'[1]产值及收款计划（2026）'!D:D)} -> 嘉兴经济技术开发区污水管网智能感知系统项目 技术服务协议 | E16: {=_xlfn.XLOOKUP($A16&$B16,'[1]产值及收款计划（2026）'!$A:$A&'[1]产值及收款计划（2026）'!$B:$B,'[1]产值及收款计划（2026）'!E:E)} -> 430.65 | F16: {=_xlfn.XLOOKUP($A16&$B16,'[1]产值及收款计划（2026）'!$A:$A&'[1]产值及收款计划（2026）'!$B:$B,'[1]产值及收款计划（2026）'!F:F)} -> 430.65 | G16: {=_xlfn.XLOOKUP($A16&$B16,'[1]产值及收款计划（2026）'!$A:$A&'[1]产值及收款计划（2026）'!$B:$B,'[1]产值及收款计划（2026）'!G:G)} -> 0 | H16: {=_xlfn.XLOOKUP($A16&$B16,'[1]产值及收款计划（2026）'!$A:$A&'[1]产值及收款计划（2026）'!$B:$B,'[1]产值及收款计划（2026）'!H:H)} -> 308.8425 | I16: {=_xlfn.XLOOKUP($A16&$B16,'[1]产值及收款计划（2026）'!$A:$A&'[1]产值及收款计划（2026）'!$B:$B,'[1]产值及收款计划（2026）'!I:I)} -> 0.7171543 | J16: {=_xlfn.XLOOKUP($A16&$B16,'[1]产值及收款计划（2026）'!$A:$A&'[1]产值及收款计划（2026）'!$B:$B,'[1]产值及收款计划（2026）'!J:J)} -> 0.06 | K16: {=_xlfn.XLOOKUP($A16&$B16,'[1]产值及收款计划（2026）'!$A:$A&'[1]产值及收款计划（2026）'!$B:$B,'[1]产值及收款计划（2026）'!K:K)} -> 0 | L16: {=_xlfn.XLOOKUP($A16&$B16,'[1]产值及收款计划（2026）'!$A:$A&'[1]产值及收款计划（2026）'!$B:$B,'[1]产值及收款计划（2026）'!L:L)} -> 0 | M16: {=_xlfn.XLOOKUP($A16&$B16,'[1]产值及收款计划（2026）'!$A:$A&'[1]产值及收款计划（2026）'!$B:$B,'[1]产值及收款计划（2026）'!M:M)} -> 主导 | N16: {=_xlfn.XLOOKUP($A16&$B16,'[1]产值及收款计划（2026）'!$A:$A&'[1]产值及收款计划（2026）'!$B:$B,'[1]产值及收款计划（2026）'!N:N)} -> 孔祥平团队 | O16: {=_xlfn.XLOOKUP($A16&$B16,'[1]产值及收款计划（2026）'!$A:$A&'[1]产值及收款计划（2026）'!$B:$B,'[1]产值及收款计划（2026）'!O:O)} -> 韩晓军 | P16: {=_xlfn.XLOOKUP($A16&$B16,'[1]产值及收款计划（2026）'!$A:$A&'[1]产值及收款计划（2026）'!$B:$B,'[1]产值及收款计划（2026）'!P:P)} -> 过往已完结 | Q16: {=_xlfn.XLOOKUP($A16&$B16,'[1]产值及收款计划（2026）'!$A:$A&'[1]产值及收款计划（2026）'!$B:$B,'[1]产值及收款计划（2026）'!Q:Q)} -> 0 | R16: {=_xlfn.XLOOKUP($A16&$B16,'[1]产值及收款计划（2026）'!$A:$A&'[1]产值及收款计划（2026）'!$B:$B,'[1]产值及收款计划（2026）'!R:R)} -> 0 | S16: {=_xlfn.XLOOKUP($A16&$B16,'[1]产值及收款计划（2026）'!$A:$A&'[1]产值及收款计划（2026）'!$B:$B,'[1]产值及收款计划（2026）'!S:S)} -> 0 | T16: {=_xlfn.XLOOKUP($A16&$B16,'[1]产值及收款计划（2026）'!$A:$A&'[1]产值及收款计划（2026）'!$B:$B,'[1]产值及收款计划（2026）'!T:T)} -> 430.65 | U16: {=_xlfn.XLOOKUP($A16&$B16,'[1]产值及收款计划（2026）'!$A:$A&'[1]产值及收款计划（2026）'!$B:$B,'[1]产值及收款计划（2026）'!U:U)} -> 0 | V16: {=_xlfn.XLOOKUP($A16&$B16,'[1]产值及收款计划（2026）'!$A:$A&'[1]产值及收款计划（2026）'!$B:$B,'[1]产值及收款计划（2026）'!V:V)} -> 0 | W16: {=_xlfn.XLOOKUP($A16&$B16,'[1]产值及收款计划（2026）'!$A:$A&'[1]产值及收款计划（2026）'!$B:$B,'[1]产值及收款计划（2026）'!W:W)} -> 0 | X16: {=_xlfn.XLOOKUP($A16&$B16,'[1]产值及收款计划（2026）'!$A:$A&'[1]产值及收款计划（2026）'!$B:$B,'[1]产值及收款计划（2026）'!X:X)} -> 0 | Y16: {=_xlfn.XLOOKUP($A16&$B16,'[1]产值及收款计划（2026）'!$A:$A&'[1]产值及收款计划（2026）'!$B:$B,'[1]产值及收款计划（2026）'!Y:Y)} -> 0 | Z16: {=_xlfn.XLOOKUP($A16&$B16,'[1]产值及收款计划（2026）'!$A:$A&'[1]产值及收款计划（2026）'!$B:$B,'[1]产值及收款计划（2026）'!Z:Z)} -> 0 | AA16: {=_xlfn.XLOOKUP($A16&$B16,'[1]产值及收款计划（2026）'!$A:$A&'[1]产值及收款计划（2026）'!$B:$B,'[1]产值及收款计划（2026）'!AA:AA)} -> 0 | AB16: {=_xlfn.XLOOKUP($A16&$B16,'[1]产值及收款计划（2026）'!$A:$A&'[1]产值及收款计划（2026）'!$B:$B,'[1]产值及收款计划（2026）'!AB:AB)} -> 0 | AC16: {=_xlfn.XLOOKUP($A16&$B16,'[1]产值及收款计划（2026）'!$A:$A&'[1]产值及收款计划（2026）'!$B:$B,'[1]产值及收款计划（2026）'!AC:AC)} -> 0 | AD16: {=_xlfn.XLOOKUP($A16&$B16,'[1]产值及收款计划（2026）'!$A:$A&'[1]产值及收款计划（2026）'!$B:$B,'[1]产值及收款计划（2026）'!AD:AD)} -> 0 | AE16: {=_xlfn.XLOOKUP($A16&$B16,'[1]产值及收款计划（2026）'!$A:$A&'[1]产值及收款计划（2026）'!$B:$B,'[1]产值及收款计划（2026）'!AE:AE)} -> 0 | AF16: {=_xlfn.XLOOKUP($A16&$B16,'[1]产值及收款计划（2026）'!$A:$A&'[1]产值及收款计划（2026）'!$B:$B,'[1]产值及收款计划（2026）'!AF:AF)} -> 0 | AG16: {=_xlfn.XLOOKUP($A16&$B16,'[1]产值及收款计划（2026）'!$A:$A&'[1]产值及收款计划（2026）'!$B:$B,'[1]产值及收款计划（2026）'!AG:AG)} -> 0 | AH16: {=_xlfn.XLOOKUP($A16&$B16,'[1]产值及收款计划（2026）'!$A:$A&'[1]产值及收款计划（2026）'!$B:$B,'[1]产值及收款计划（2026）'!AH:AH)} -> 0 | AI16: {=_xlfn.XLOOKUP($A16&$B16,'[1]产值及收款计划（2026）'!$A:$A&'[1]产值及收款计划（2026）'!$B:$B,'[1]产值及收款计划（2026）'!AI:AI)} -> 0 | AJ16: {=_xlfn.XLOOKUP($A16&$B16,'[1]产值及收款计划（2026）'!$A:$A&'[1]产值及收款计划（2026）'!$B:$B,'[1]产值及收款计划（2026）'!AJ:AJ)} -> 0 | AK16: {=_xlfn.XLOOKUP($A16&$B16,'[1]产值及收款计划（2026）'!$A:$A&'[1]产值及收款计划（2026）'!$B:$B,'[1]产值及收款计划（2026）'!AK:AK)} -> 0 | AL16: {=_xlfn.XLOOKUP($A16&$B16,'[1]产值及收款计划（2026）'!$A:$A&'[1]产值及收款计划（2026）'!$B:$B,'[1]产值及收款计划（2026）'!AL:AL)} -> 0 | AM16: {=_xlfn.LET(_xlpm.勾选月份状态数组,TRANSPOSE('PPT(12-15页）-TOP10'!$A$3:$A$14),_xlpm.选择数据区,IF('PPT(12-15页）-TOP10'!$E$3="收款",$BA16:$BL16,$AA16:$AL16),SUM(_xlfn._xlws.FILTER(_xlpm.选择数据区,_xlpm.勾选月份状态数组,"")))} -> #NAME? | AN16: {=_xlfn.LET(_xlpm.勾选月份状态数组,TRANSPOSE('PPT(12-15页）-TOP10'!$A$3:$A$14),_xlpm.选择数据区,IF('PPT(12-15页）-TOP10'!$E$3="收款",$DA16:$DL16,$CA16:$CL16),SUM(_xlfn._xlws.FILTER(_xlpm.选择数据区,_xlpm.勾选月份状态数组,"")))} -> #NAME? | AO16: =SUM(CA16:CC16)+SUM(AD16:AL16) -> 0 | AS16: {=_xlfn.XLOOKUP($A16&$B16,'[1]产值及收款计划（2026）'!$A:$A&'[1]产值及收款计划（2026）'!$B:$B,'[1]产值及收款计划（2026）'!AS:AS)} -> 0 | AT16: {=_xlfn.XLOOKUP($A16&$B16,'[1]产值及收款计划（2026）'!$A:$A&'[1]产值及收款计划（2026）'!$B:$B,'[1]产值及收款计划（2026）'!AT:AT)} -> 0 | AU16: {=_xlfn.XLOOKUP($A16&$B16,'[1]产值及收款计划（2026）'!$A:$A&'[1]产值及收款计划（2026）'!$B:$B,'[1]产值及收款计划（2026）'!AU:AU)} -> 0 | AV16: {=_xlfn.XLOOKUP($A16&$B16,'[1]产值及收款计划（2026）'!$A:$A&'[1]产值及收款计划（2026）'!$B:$B,'[1]产值及收款计划（2026）'!AV:AV)} -> 0 | AW16: {=_xlfn.XLOOKUP($A16&$B16,'[1]产值及收款计划（2026）'!$A:$A&'[1]产值及收款计划（2026）'!$B:$B,'[1]产值及收款计划（2026）'!AW:AW)} -> 346.22115 | AX16: {=_xlfn.XLOOKUP($A16&$B16,'[1]产值及收款计划（2026）'!$A:$A&'[1]产值及收款计划（2026）'!$B:$B,'[1]产值及收款计划（2026）'!AX:AX)} -> 0 | AY16: {=_xlfn.XLOOKUP($A16&$B16,'[1]产值及收款计划（2026）'!$A:$A&'[1]产值及收款计划（2026）'!$B:$B,'[1]产值及收款计划（2026）'!AY:AY)} -> 84.42885 | AZ16: {=_xlfn.XLOOKUP($A16&$B16,'[1]产值及收款计划（2026）'!$A:$A&'[1]产值及收款计划（2026）'!$B:$B,'[1]产值及收款计划（2026）'!AZ:AZ)} -> 84.42885 | BA16: {=_xlfn.XLOOKUP($A16&$B16,'[1]产值及收款计划（2026）'!$A:$A&'[1]产值及收款计划（2026）'!$B:$B,'[1]产值及收款计划（2026）'!BA:BA)} -> 0 | BB16: {=_xlfn.XLOOKUP($A16&$B16,'[1]产值及收款计划（2026）'!$A:$A&'[1]产值及收款计划（2026）'!$B:$B,'[1]产值及收款计划（2026）'!BB:BB)} -> 0 | BC16: {=_xlfn.XLOOKUP($A16&$B16,'[1]产值及收款计划（2026）'!$A:$A&'[1]产值及收款计划（2026）'!$B:$B,'[1]产值及收款计划（2026）'!BC:BC)} -> 0 | BD16: {=_xlfn.XLOOKUP($A16&$B16,'[1]产值及收款计划（2026）'!$A:$A&'[1]产值及收款计划（2026）'!$B:$B,'[1]产值及收款计划（2026）'!BD:BD)} -> 0 | BE16: {=_xlfn.XLOOKUP($A16&$B16,'[1]产值及收款计划（2026）'!$A:$A&'[1]产值及收款计划（2026）'!$B:$B,'[1]产值及收款计划（2026）'!BE:BE)} -> 0 | BF16: {=_xlfn.XLOOKUP($A16&$B16,'[1]产值及收款计划（2026）'!$A:$A&'[1]产值及收款计划（2026）'!$B:$B,'[1]产值及收款计划（2026）'!BF:BF)} -> 0 | BG16: {=_xlfn.XLOOKUP($A16&$B16,'[1]产值及收款计划（2026）'!$A:$A&'[1]产值及收款计划（2026）'!$B:$B,'[1]产值及收款计划（2026）'!BG:BG)} -> 0 | BH16: {=_xlfn.XLOOKUP($A16&$B16,'[1]产值及收款计划（2026）'!$A:$A&'[1]产值及收款计划（2026）'!$B:$B,'[1]产值及收款计划（2026）'!BH:BH)} -> 0 | BI16: {=_xlfn.XLOOKUP($A16&$B16,'[1]产值及收款计划（2026）'!$A:$A&'[1]产值及收款计划（2026）'!$B:$B,'[1]产值及收款计划（2026）'!BI:BI)} -> 0 | BJ16: {=_xlfn.XLOOKUP($A16&$B16,'[1]产值及收款计划（2026）'!$A:$A&'[1]产值及收款计划（2026）'!$B:$B,'[1]产值及收款计划（2026）'!BJ:BJ)} -> 0 | BK16: {=_xlfn.XLOOKUP($A16&$B16,'[1]产值及收款计划（2026）'!$A:$A&'[1]产值及收款计划（2026）'!$B:$B,'[1]产值及收款计划（2026）'!BK:BK)} -> 0 | BL16: {=_xlfn.XLOOKUP($A16&$B16,'[1]产值及收款计划（2026）'!$A:$A&'[1]产值及收款计划（2026）'!$B:$B,'[1]产值及收款计划（2026）'!BL:BL)} -> 0 | BQ16: {=_xlfn.XLOOKUP($A16&$B16,'[1]产值及收款计划（2026）'!$A:$A&'[1]产值及收款计划（2026）'!$B:$B,'[1]产值及收款计划（2026）'!BQ:BQ)} -> 0 | BR16: {=_xlfn.XLOOKUP($A16&$B16,'[1]产值及收款计划（2026）'!$A:$A&'[1]产值及收款计划（2026）'!$B:$B,'[1]产值及收款计划（2026）'!BR:BR)} -> 0 | CA16: {=_xlfn.XLOOKUP($A16&$B16,'[1]产值及收款计划（2026）'!$A:$A&'[1]产值及收款计划（2026）'!$B:$B,'[1]产值及收款计划（2026）'!CA:CA)} -> 0 | CB16: {=_xlfn.XLOOKUP($A16&$B16,'[1]产值及收款计划（2026）'!$A:$A&'[1]产值及收款计划（2026）'!$B:$B,'[1]产值及收款计划（2026）'!CB:CB)} -> 0 | CC16: {=_xlfn.XLOOKUP($A16&$B16,'[1]产值及收款计划（2026）'!$A:$A&'[1]产值及收款计划（2026）'!$B:$B,'[1]产值及收款计划（2026）'!CC:CC)} -> 0 | CD16: {=_xlfn.XLOOKUP($A16&$B16,'[1]产值及收款计划（2026）'!$A:$A&'[1]产值及收款计划（2026）'!$B:$B,'[1]产值及收款计划（2026）'!CD:CD)} -> 0 | CE16: {=_xlfn.XLOOKUP($A16&$B16,'[1]产值及收款计划（2026）'!$A:$A&'[1]产值及收款计划（2026）'!$B:$B,'[1]产值及收款计划（2026）'!CE:CE)} -> 0 | CF16: {=_xlfn.XLOOKUP($A16&$B16,'[1]产值及收款计划（2026）'!$A:$A&'[1]产值及收款计划（2026）'!$B:$B,'[1]产值及收款计划（2026）'!CF:CF)} -> 0 | CG16: {=_xlfn.XLOOKUP($A16&$B16,'[1]产值及收款计划（2026）'!$A:$A&'[1]产值及收款计划（2026）'!$B:$B,'[1]产值及收款计划（2026）'!CG:CG)} -> 0 | CH16: {=_xlfn.XLOOKUP($A16&$B16,'[1]产值及收款计划（2026）'!$A:$A&'[1]产值及收款计划（2026）'!$B:$B,'[1]产值及收款计划（2026）'!CH:CH)} -> 0 | CI16: {=_xlfn.XLOOKUP($A16&$B16,'[1]产值及收款计划（2026）'!$A:$A&'[1]产值及收款计划（2026）'!$B:$B,'[1]产值及收款计划（2026）'!CI:CI)} -> 0 | CJ16: {=_xlfn.XLOOKUP($A16&$B16,'[1]产值及收款计划（2026）'!$A:$A&'[1]产值及收款计划（2026）'!$B:$B,'[1]产值及收款计划（2026）'!CJ:CJ)} -> 0 | CK16: {=_xlfn.XLOOKUP($A16&$B16,'[1]产值及收款计划（2026）'!$A:$A&'[1]产值及收款计划（2026）'!$B:$B,'[1]产值及收款计划（2026）'!CK:CK)} -> 0 | CL16: {=_xlfn.XLOOKUP($A16&$B16,'[1]产值及收款计划（2026）'!$A:$A&'[1]产值及收款计划（2026）'!$B:$B,'[1]产值及收款计划（2026）'!CL:CL)} -> 0 | DA16: {=_xlfn.XLOOKUP($A16&$B16,'[1]产值及收款计划（2026）'!$A:$A&'[1]产值及收款计划（2026）'!$B:$B,'[1]产值及收款计划（2026）'!DA:DA)} -> 0 | DB16: {=_xlfn.XLOOKUP($A16&$B16,'[1]产值及收款计划（2026）'!$A:$A&'[1]产值及收款计划（2026）'!$B:$B,'[1]产值及收款计划（2026）'!DB:DB)} -> 0 | DC16: {=_xlfn.XLOOKUP($A16&$B16,'[1]产值及收款计划（2026）'!$A:$A&'[1]产值及收款计划（2026）'!$B:$B,'[1]产值及收款计划（2026）'!DC:DC)} -> 0 | DD16: {=_xlfn.XLOOKUP($A16&$B16,'[1]产值及收款计划（2026）'!$A:$A&'[1]产值及收款计划（2026）'!$B:$B,'[1]产值及收款计划（2026）'!DD:DD)} -> 0 | DE16: {=_xlfn.XLOOKUP($A16&$B16,'[1]产值及收款计划（2026）'!$A:$A&'[1]产值及收款计划（2026）'!$B:$B,'[1]产值及收款计划（2026）'!DE:DE)} -> 0 | DF16: {=_xlfn.XLOOKUP($A16&$B16,'[1]产值及收款计划（2026）'!$A:$A&'[1]产值及收款计划（2026）'!$B:$B,'[1]产值及收款计划（2026）'!DF:DF)} -> 0 | DG16: {=_xlfn.XLOOKUP($A16&$B16,'[1]产值及收款计划（2026）'!$A:$A&'[1]产值及收款计划（2026）'!$B:$B,'[1]产值及收款计划（2026）'!DG:DG)} -> 0 | DH16: {=_xlfn.XLOOKUP($A16&$B16,'[1]产值及收款计划（2026）'!$A:$A&'[1]产值及收款计划（2026）'!$B:$B,'[1]产值及收款计划（2026）'!DH:DH)} -> 0 | DI16: {=_xlfn.XLOOKUP($A16&$B16,'[1]产值及收款计划（2026）'!$A:$A&'[1]产值及收款计划（2026）'!$B:$B,'[1]产值及收款计划（2026）'!DI:DI)} -> 0 | DJ16: {=_xlfn.XLOOKUP($A16&$B16,'[1]产值及收款计划（2026）'!$A:$A&'[1]产值及收款计划（2026）'!$B:$B,'[1]产值及收款计划（2026）'!DJ:DJ)} -> 0 | DK16: {=_xlfn.XLOOKUP($A16&$B16,'[1]产值及收款计划（2026）'!$A:$A&'[1]产值及收款计划（2026）'!$B:$B,'[1]产值及收款计划（2026）'!DK:DK)} -> 0 | DL16: {=_xlfn.XLOOKUP($A16&$B16,'[1]产值及收款计划（2026）'!$A:$A&'[1]产值及收款计划（2026）'!$B:$B,'[1]产值及收款计划（2026）'!DL:DL)} -> 0
A17: =A16+1 -> 13 | B17: 数字建造中心 | C17: {=_xlfn.XLOOKUP($A17&$B17,'[1]产值及收款计划（2026）'!$A:$A&'[1]产值及收款计划（2026）'!$B:$B,'[1]产值及收款计划（2026）'!C:C)} -> ZHT2021121000146 | D17: {=_xlfn.XLOOKUP($A17&$B17,'[1]产值及收款计划（2026）'!$A:$A&'[1]产值及收款计划（2026）'!$B:$B,'[1]产值及收款计划（2026）'!D:D)} -> 秀洲区污水管网智能感知系统项目 | E17: {=_xlfn.XLOOKUP($A17&$B17,'[1]产值及收款计划（2026）'!$A:$A&'[1]产值及收款计划（2026）'!$B:$B,'[1]产值及收款计划（2026）'!E:E)} -> 361.69 | F17: {=_xlfn.XLOOKUP($A17&$B17,'[1]产值及收款计划（2026）'!$A:$A&'[1]产值及收款计划（2026）'!$B:$B,'[1]产值及收款计划（2026）'!F:F)} -> 361.69 | G17: {=_xlfn.XLOOKUP($A17&$B17,'[1]产值及收款计划（2026）'!$A:$A&'[1]产值及收款计划（2026）'!$B:$B,'[1]产值及收款计划（2026）'!G:G)} -> 0 | H17: {=_xlfn.XLOOKUP($A17&$B17,'[1]产值及收款计划（2026）'!$A:$A&'[1]产值及收款计划（2026）'!$B:$B,'[1]产值及收款计划（2026）'!H:H)} -> 261.69 | I17: {=_xlfn.XLOOKUP($A17&$B17,'[1]产值及收款计划（2026）'!$A:$A&'[1]产值及收款计划（2026）'!$B:$B,'[1]产值及收款计划（2026）'!I:I)} -> 0.72352014 | J17: {=_xlfn.XLOOKUP($A17&$B17,'[1]产值及收款计划（2026）'!$A:$A&'[1]产值及收款计划（2026）'!$B:$B,'[1]产值及收款计划（2026）'!J:J)} -> 0.06 | K17: {=_xlfn.XLOOKUP($A17&$B17,'[1]产值及收款计划（2026）'!$A:$A&'[1]产值及收款计划（2026）'!$B:$B,'[1]产值及收款计划（2026）'!K:K)} -> 0 | L17: {=_xlfn.XLOOKUP($A17&$B17,'[1]产值及收款计划（2026）'!$A:$A&'[1]产值及收款计划（2026）'!$B:$B,'[1]产值及收款计划（2026）'!L:L)} -> 0 | M17: {=_xlfn.XLOOKUP($A17&$B17,'[1]产值及收款计划（2026）'!$A:$A&'[1]产值及收款计划（2026）'!$B:$B,'[1]产值及收款计划（2026）'!M:M)} -> 主导 | N17: {=_xlfn.XLOOKUP($A17&$B17,'[1]产值及收款计划（2026）'!$A:$A&'[1]产值及收款计划（2026）'!$B:$B,'[1]产值及收款计划（2026）'!N:N)} -> 孔祥平团队 | O17: {=_xlfn.XLOOKUP($A17&$B17,'[1]产值及收款计划（2026）'!$A:$A&'[1]产值及收款计划（2026）'!$B:$B,'[1]产值及收款计划（2026）'!O:O)} -> 韩晓军 | P17: {=_xlfn.XLOOKUP($A17&$B17,'[1]产值及收款计划（2026）'!$A:$A&'[1]产值及收款计划（2026）'!$B:$B,'[1]产值及收款计划（2026）'!P:P)} -> 过往已完结 | Q17: {=_xlfn.XLOOKUP($A17&$B17,'[1]产值及收款计划（2026）'!$A:$A&'[1]产值及收款计划（2026）'!$B:$B,'[1]产值及收款计划（2026）'!Q:Q)} -> 0 | R17: {=_xlfn.XLOOKUP($A17&$B17,'[1]产值及收款计划（2026）'!$A:$A&'[1]产值及收款计划（2026）'!$B:$B,'[1]产值及收款计划（2026）'!R:R)} -> 0 | S17: {=_xlfn.XLOOKUP($A17&$B17,'[1]产值及收款计划（2026）'!$A:$A&'[1]产值及收款计划（2026）'!$B:$B,'[1]产值及收款计划（2026）'!S:S)} -> 0 | T17: {=_xlfn.XLOOKUP($A17&$B17,'[1]产值及收款计划（2026）'!$A:$A&'[1]产值及收款计划（2026）'!$B:$B,'[1]产值及收款计划（2026）'!T:T)} -> 361.69 | U17: {=_xlfn.XLOOKUP($A17&$B17,'[1]产值及收款计划（2026）'!$A:$A&'[1]产值及收款计划（2026）'!$B:$B,'[1]产值及收款计划（2026）'!U:U)} -> 0 | V17: {=_xlfn.XLOOKUP($A17&$B17,'[1]产值及收款计划（2026）'!$A:$A&'[1]产值及收款计划（2026）'!$B:$B,'[1]产值及收款计划（2026）'!V:V)} -> 0 | W17: {=_xlfn.XLOOKUP($A17&$B17,'[1]产值及收款计划（2026）'!$A:$A&'[1]产值及收款计划（2026）'!$B:$B,'[1]产值及收款计划（2026）'!W:W)} -> 0 | X17: {=_xlfn.XLOOKUP($A17&$B17,'[1]产值及收款计划（2026）'!$A:$A&'[1]产值及收款计划（2026）'!$B:$B,'[1]产值及收款计划（2026）'!X:X)} -> 0 | Y17: {=_xlfn.XLOOKUP($A17&$B17,'[1]产值及收款计划（2026）'!$A:$A&'[1]产值及收款计划（2026）'!$B:$B,'[1]产值及收款计划（2026）'!Y:Y)} -> 0 | Z17: {=_xlfn.XLOOKUP($A17&$B17,'[1]产值及收款计划（2026）'!$A:$A&'[1]产值及收款计划（2026）'!$B:$B,'[1]产值及收款计划（2026）'!Z:Z)} -> 0 | AA17: {=_xlfn.XLOOKUP($A17&$B17,'[1]产值及收款计划（2026）'!$A:$A&'[1]产值及收款计划（2026）'!$B:$B,'[1]产值及收款计划（2026）'!AA:AA)} -> 0 | AB17: {=_xlfn.XLOOKUP($A17&$B17,'[1]产值及收款计划（2026）'!$A:$A&'[1]产值及收款计划（2026）'!$B:$B,'[1]产值及收款计划（2026）'!AB:AB)} -> 0 | AC17: {=_xlfn.XLOOKUP($A17&$B17,'[1]产值及收款计划（2026）'!$A:$A&'[1]产值及收款计划（2026）'!$B:$B,'[1]产值及收款计划（2026）'!AC:AC)} -> 0 | AD17: {=_xlfn.XLOOKUP($A17&$B17,'[1]产值及收款计划（2026）'!$A:$A&'[1]产值及收款计划（2026）'!$B:$B,'[1]产值及收款计划（2026）'!AD:AD)} -> 0 | AE17: {=_xlfn.XLOOKUP($A17&$B17,'[1]产值及收款计划（2026）'!$A:$A&'[1]产值及收款计划（2026）'!$B:$B,'[1]产值及收款计划（2026）'!AE:AE)} -> 0 | AF17: {=_xlfn.XLOOKUP($A17&$B17,'[1]产值及收款计划（2026）'!$A:$A&'[1]产值及收款计划（2026）'!$B:$B,'[1]产值及收款计划（2026）'!AF:AF)} -> 0 | AG17: {=_xlfn.XLOOKUP($A17&$B17,'[1]产值及收款计划（2026）'!$A:$A&'[1]产值及收款计划（2026）'!$B:$B,'[1]产值及收款计划（2026）'!AG:AG)} -> 0 | AH17: {=_xlfn.XLOOKUP($A17&$B17,'[1]产值及收款计划（2026）'!$A:$A&'[1]产值及收款计划（2026）'!$B:$B,'[1]产值及收款计划（2026）'!AH:AH)} -> 0 | AI17: {=_xlfn.XLOOKUP($A17&$B17,'[1]产值及收款计划（2026）'!$A:$A&'[1]产值及收款计划（2026）'!$B:$B,'[1]产值及收款计划（2026）'!AI:AI)} -> 0 | AJ17: {=_xlfn.XLOOKUP($A17&$B17,'[1]产值及收款计划（2026）'!$A:$A&'[1]产值及收款计划（2026）'!$B:$B,'[1]产值及收款计划（2026）'!AJ:AJ)} -> 0 | AK17: {=_xlfn.XLOOKUP($A17&$B17,'[1]产值及收款计划（2026）'!$A:$A&'[1]产值及收款计划（2026）'!$B:$B,'[1]产值及收款计划（2026）'!AK:AK)} -> 0 | AL17: {=_xlfn.XLOOKUP($A17&$B17,'[1]产值及收款计划（2026）'!$A:$A&'[1]产值及收款计划（2026）'!$B:$B,'[1]产值及收款计划（2026）'!AL:AL)} -> 0 | AM17: {=_xlfn.LET(_xlpm.勾选月份状态数组,TRANSPOSE('PPT(12-15页）-TOP10'!$A$3:$A$14),_xlpm.选择数据区,IF('PPT(12-15页）-TOP10'!$E$3="收款",$BA17:$BL17,$AA17:$AL17),SUM(_xlfn._xlws.FILTER(_xlpm.选择数据区,_xlpm.勾选月份状态数组,"")))} -> #NAME? | AN17: {=_xlfn.LET(_xlpm.勾选月份状态数组,TRANSPOSE('PPT(12-15页）-TOP10'!$A$3:$A$14),_xlpm.选择数据区,IF('PPT(12-15页）-TOP10'!$E$3="收款",$DA17:$DL17,$CA17:$CL17),SUM(_xlfn._xlws.FILTER(_xlpm.选择数据区,_xlpm.勾选月份状态数组,"")))} -> #NAME? | AO17: =SUM(CA17:CC17)+SUM(AD17:AL17) -> 0 | AS17: {=_xlfn.XLOOKUP($A17&$B17,'[1]产值及收款计划（2026）'!$A:$A&'[1]产值及收款计划（2026）'!$B:$B,'[1]产值及收款计划（2026）'!AS:AS)} -> 0 | AT17: {=_xlfn.XLOOKUP($A17&$B17,'[1]产值及收款计划（2026）'!$A:$A&'[1]产值及收款计划（2026）'!$B:$B,'[1]产值及收款计划（2026）'!AT:AT)} -> 0 | AU17: {=_xlfn.XLOOKUP($A17&$B17,'[1]产值及收款计划（2026）'!$A:$A&'[1]产值及收款计划（2026）'!$B:$B,'[1]产值及收款计划（2026）'!AU:AU)} -> 0 | AV17: {=_xlfn.XLOOKUP($A17&$B17,'[1]产值及收款计划（2026）'!$A:$A&'[1]产值及收款计划（2026）'!$B:$B,'[1]产值及收款计划（2026）'!AV:AV)} -> 0 | AW17: {=_xlfn.XLOOKUP($A17&$B17,'[1]产值及收款计划（2026）'!$A:$A&'[1]产值及收款计划（2026）'!$B:$B,'[1]产值及收款计划（2026）'!AW:AW)} -> 319.6246 | AX17: {=_xlfn.XLOOKUP($A17&$B17,'[1]产值及收款计划（2026）'!$A:$A&'[1]产值及收款计划（2026）'!$B:$B,'[1]产值及收款计划（2026）'!AX:AX)} -> 0 | AY17: {=_xlfn.XLOOKUP($A17&$B17,'[1]产值及收款计划（2026）'!$A:$A&'[1]产值及收款计划（2026）'!$B:$B,'[1]产值及收款计划（2026）'!AY:AY)} -> 42.0654 | AZ17: {=_xlfn.XLOOKUP($A17&$B17,'[1]产值及收款计划（2026）'!$A:$A&'[1]产值及收款计划（2026）'!$B:$B,'[1]产值及收款计划（2026）'!AZ:AZ)} -> 42.0654 | BA17: {=_xlfn.XLOOKUP($A17&$B17,'[1]产值及收款计划（2026）'!$A:$A&'[1]产值及收款计划（2026）'!$B:$B,'[1]产值及收款计划（2026）'!BA:BA)} -> 0 | BB17: {=_xlfn.XLOOKUP($A17&$B17,'[1]产值及收款计划（2026）'!$A:$A&'[1]产值及收款计划（2026）'!$B:$B,'[1]产值及收款计划（2026）'!BB:BB)} -> 0 | BC17: {=_xlfn.XLOOKUP($A17&$B17,'[1]产值及收款计划（2026）'!$A:$A&'[1]产值及收款计划（2026）'!$B:$B,'[1]产值及收款计划（2026）'!BC:BC)} -> 0 | BD17: {=_xlfn.XLOOKUP($A17&$B17,'[1]产值及收款计划（2026）'!$A:$A&'[1]产值及收款计划（2026）'!$B:$B,'[1]产值及收款计划（2026）'!BD:BD)} -> 0 | BE17: {=_xlfn.XLOOKUP($A17&$B17,'[1]产值及收款计划（2026）'!$A:$A&'[1]产值及收款计划（2026）'!$B:$B,'[1]产值及收款计划（2026）'!BE:BE)} -> 0 | BF17: {=_xlfn.XLOOKUP($A17&$B17,'[1]产值及收款计划（2026）'!$A:$A&'[1]产值及收款计划（2026）'!$B:$B,'[1]产值及收款计划（2026）'!BF:BF)} -> 0 | BG17: {=_xlfn.XLOOKUP($A17&$B17,'[1]产值及收款计划（2026）'!$A:$A&'[1]产值及收款计划（2026）'!$B:$B,'[1]产值及收款计划（2026）'!BG:BG)} -> 0 | BH17: {=_xlfn.XLOOKUP($A17&$B17,'[1]产值及收款计划（2026）'!$A:$A&'[1]产值及收款计划（2026）'!$B:$B,'[1]产值及收款计划（2026）'!BH:BH)} -> 0 | BI17: {=_xlfn.XLOOKUP($A17&$B17,'[1]产值及收款计划（2026）'!$A:$A&'[1]产值及收款计划（2026）'!$B:$B,'[1]产值及收款计划（2026）'!BI:BI)} -> 0 | BJ17: {=_xlfn.XLOOKUP($A17&$B17,'[1]产值及收款计划（2026）'!$A:$A&'[1]产值及收款计划（2026）'!$B:$B,'[1]产值及收款计划（2026）'!BJ:BJ)} -> 0 | BK17: {=_xlfn.XLOOKUP($A17&$B17,'[1]产值及收款计划（2026）'!$A:$A&'[1]产值及收款计划（2026）'!$B:$B,'[1]产值及收款计划（2026）'!BK:BK)} -> 0 | BL17: {=_xlfn.XLOOKUP($A17&$B17,'[1]产值及收款计划（2026）'!$A:$A&'[1]产值及收款计划（2026）'!$B:$B,'[1]产值及收款计划（2026）'!BL:BL)} -> 0 | BQ17: {=_xlfn.XLOOKUP($A17&$B17,'[1]产值及收款计划（2026）'!$A:$A&'[1]产值及收款计划（2026）'!$B:$B,'[1]产值及收款计划（2026）'!BQ:BQ)} -> 0 | BR17: {=_xlfn.XLOOKUP($A17&$B17,'[1]产值及收款计划（2026）'!$A:$A&'[1]产值及收款计划（2026）'!$B:$B,'[1]产值及收款计划（2026）'!BR:BR)} -> 0 | CA17: {=_xlfn.XLOOKUP($A17&$B17,'[1]产值及收款计划（2026）'!$A:$A&'[1]产值及收款计划（2026）'!$B:$B,'[1]产值及收款计划（2026）'!CA:CA)} -> 0 | CB17: {=_xlfn.XLOOKUP($A17&$B17,'[1]产值及收款计划（2026）'!$A:$A&'[1]产值及收款计划（2026）'!$B:$B,'[1]产值及收款计划（2026）'!CB:CB)} -> 0 | CC17: {=_xlfn.XLOOKUP($A17&$B17,'[1]产值及收款计划（2026）'!$A:$A&'[1]产值及收款计划（2026）'!$B:$B,'[1]产值及收款计划（2026）'!CC:CC)} -> 0 | CD17: {=_xlfn.XLOOKUP($A17&$B17,'[1]产值及收款计划（2026）'!$A:$A&'[1]产值及收款计划（2026）'!$B:$B,'[1]产值及收款计划（2026）'!CD:CD)} -> 0 | CE17: {=_xlfn.XLOOKUP($A17&$B17,'[1]产值及收款计划（2026）'!$A:$A&'[1]产值及收款计划（2026）'!$B:$B,'[1]产值及收款计划（2026）'!CE:CE)} -> 0 | CF17: {=_xlfn.XLOOKUP($A17&$B17,'[1]产值及收款计划（2026）'!$A:$A&'[1]产值及收款计划（2026）'!$B:$B,'[1]产值及收款计划（2026）'!CF:CF)} -> 0 | CG17: {=_xlfn.XLOOKUP($A17&$B17,'[1]产值及收款计划（2026）'!$A:$A&'[1]产值及收款计划（2026）'!$B:$B,'[1]产值及收款计划（2026）'!CG:CG)} -> 0 | CH17: {=_xlfn.XLOOKUP($A17&$B17,'[1]产值及收款计划（2026）'!$A:$A&'[1]产值及收款计划（2026）'!$B:$B,'[1]产值及收款计划（2026）'!CH:CH)} -> 0 | CI17: {=_xlfn.XLOOKUP($A17&$B17,'[1]产值及收款计划（2026）'!$A:$A&'[1]产值及收款计划（2026）'!$B:$B,'[1]产值及收款计划（2026）'!CI:CI)} -> 0 | CJ17: {=_xlfn.XLOOKUP($A17&$B17,'[1]产值及收款计划（2026）'!$A:$A&'[1]产值及收款计划（2026）'!$B:$B,'[1]产值及收款计划（2026）'!CJ:CJ)} -> 0 | CK17: {=_xlfn.XLOOKUP($A17&$B17,'[1]产值及收款计划（2026）'!$A:$A&'[1]产值及收款计划（2026）'!$B:$B,'[1]产值及收款计划（2026）'!CK:CK)} -> 0 | CL17: {=_xlfn.XLOOKUP($A17&$B17,'[1]产值及收款计划（2026）'!$A:$A&'[1]产值及收款计划（2026）'!$B:$B,'[1]产值及收款计划（2026）'!CL:CL)} -> 0 | DA17: {=_xlfn.XLOOKUP($A17&$B17,'[1]产值及收款计划（2026）'!$A:$A&'[1]产值及收款计划（2026）'!$B:$B,'[1]产值及收款计划（2026）'!DA:DA)} -> 0 | DB17: {=_xlfn.XLOOKUP($A17&$B17,'[1]产值及收款计划（2026）'!$A:$A&'[1]产值及收款计划（2026）'!$B:$B,'[1]产值及收款计划（2026）'!DB:DB)} -> 0 | DC17: {=_xlfn.XLOOKUP($A17&$B17,'[1]产值及收款计划（2026）'!$A:$A&'[1]产值及收款计划（2026）'!$B:$B,'[1]产值及收款计划（2026）'!DC:DC)} -> 0 | DD17: {=_xlfn.XLOOKUP($A17&$B17,'[1]产值及收款计划（2026）'!$A:$A&'[1]产值及收款计划（2026）'!$B:$B,'[1]产值及收款计划（2026）'!DD:DD)} -> 0 | DE17: {=_xlfn.XLOOKUP($A17&$B17,'[1]产值及收款计划（2026）'!$A:$A&'[1]产值及收款计划（2026）'!$B:$B,'[1]产值及收款计划（2026）'!DE:DE)} -> 0 | DF17: {=_xlfn.XLOOKUP($A17&$B17,'[1]产值及收款计划（2026）'!$A:$A&'[1]产值及收款计划（2026）'!$B:$B,'[1]产值及收款计划（2026）'!DF:DF)} -> 0 | DG17: {=_xlfn.XLOOKUP($A17&$B17,'[1]产值及收款计划（2026）'!$A:$A&'[1]产值及收款计划（2026）'!$B:$B,'[1]产值及收款计划（2026）'!DG:DG)} -> 0 | DH17: {=_xlfn.XLOOKUP($A17&$B17,'[1]产值及收款计划（2026）'!$A:$A&'[1]产值及收款计划（2026）'!$B:$B,'[1]产值及收款计划（2026）'!DH:DH)} -> 0 | DI17: {=_xlfn.XLOOKUP($A17&$B17,'[1]产值及收款计划（2026）'!$A:$A&'[1]产值及收款计划（2026）'!$B:$B,'[1]产值及收款计划（2026）'!DI:DI)} -> 0 | DJ17: {=_xlfn.XLOOKUP($A17&$B17,'[1]产值及收款计划（2026）'!$A:$A&'[1]产值及收款计划（2026）'!$B:$B,'[1]产值及收款计划（2026）'!DJ:DJ)} -> 0 | DK17: {=_xlfn.XLOOKUP($A17&$B17,'[1]产值及收款计划（2026）'!$A:$A&'[1]产值及收款计划（2026）'!$B:$B,'[1]产值及收款计划（2026）'!DK:DK)} -> 0 | DL17: {=_xlfn.XLOOKUP($A17&$B17,'[1]产值及收款计划（2026）'!$A:$A&'[1]产值及收款计划（2026）'!$B:$B,'[1]产值及收款计划（2026）'!DL:DL)} -> 0
